{
  "data": [
    {
      "tdOfGreatestEclipse": "1701-02-07T23:04:53Z",
      "deltaT": 8,
      "deltaTSigma": 5,
      "lunaNum": -3697,
      "sarosNum": 116,
      "eclType": "A",
      "qle": "-p",
      "gamma": 0.6662,
      "eclMag": 0.9219,
      "lat": 26,
      "long": -172,
      "sunAlt": 48,
      "pathWidth": 393,
      "centralDur": 595
    },
    {
      "tdOfGreatestEclipse": "1701-08-04T09:31:44Z",
      "deltaT": 8,
      "deltaTSigma": 5,
      "lunaNum": -3691,
      "sarosNum": 121,
      "eclType": "T",
      "qle": "-p",
      "gamma": -0.4558,
      "eclMag": 1.0521,
      "lat": -9,
      "long": 34,
      "sunAlt": 63,
      "pathWidth": 193,
      "centralDur": 306
    },
    {
      "tdOfGreatestEclipse": "1702-01-28T01:37:09Z",
      "deltaT": 8,
      "deltaTSigma": 5,
      "lunaNum": -3685,
      "sarosNum": 126,
      "eclType": "A",
      "qle": "nn",
      "gamma": -0.0485,
      "eclMag": 0.9636,
      "lat": -21,
      "long": 160,
      "sunAlt": 87,
      "pathWidth": 132,
      "centralDur": 254
    },
    {
      "tdOfGreatestEclipse": "1702-07-24T21:38:51Z",
      "deltaT": 8,
      "deltaTSigma": 5,
      "lunaNum": -3679,
      "sarosNum": 131,
      "eclType": "H",
      "qle": "n-",
      "gamma": 0.316,
      "eclMag": 1.0002,
      "lat": 38,
      "long": -140,
      "sunAlt": 71,
      "pathWidth": 1,
      "centralDur": 1
    },
    {
      "tdOfGreatestEclipse": "1703-01-17T11:24:25Z",
      "deltaT": 8,
      "deltaTSigma": 5,
      "lunaNum": -3673,
      "sarosNum": 136,
      "eclType": "H2",
      "qle": "p-",
      "gamma": -0.7345,
      "eclMag": 1.012,
      "lat": -68,
      "long": 22,
      "sunAlt": 42,
      "pathWidth": 61,
      "centralDur": 50
    },
    {
      "tdOfGreatestEclipse": "1703-07-14T02:36:33Z",
      "deltaT": 8,
      "deltaTSigma": 5,
      "lunaNum": -3667,
      "sarosNum": 141,
      "eclType": "P",
      "qle": "t-",
      "gamma": 1.1207,
      "eclMag": 0.758,
      "lat": 68,
      "long": -46,
      "sunAlt": 0,
      "pathWidth": 0,
      "centralDur": 0
    },
    {
      "tdOfGreatestEclipse": "1703-12-08T15:41:29Z",
      "deltaT": 8,
      "deltaTSigma": 5,
      "lunaNum": -3662,
      "sarosNum": 108,
      "eclType": "P",
      "qle": "-t",
      "gamma": 1.3086,
      "eclMag": 0.4282,
      "lat": 65,
      "long": -29,
      "sunAlt": 0,
      "pathWidth": 0,
      "centralDur": 0
    },
    {
      "tdOfGreatestEclipse": "1704-01-07T02:14:50Z",
      "deltaT": 8,
      "deltaTSigma": 5,
      "lunaNum": -3661,
      "sarosNum": 146,
      "eclType": "P",
      "qle": "t-",
      "gamma": -1.3669,
      "eclMag": 0.3177,
      "lat": -67,
      "long": -36,
      "sunAlt": 0,
      "pathWidth": 0,
      "centralDur": 0
    },
    {
      "tdOfGreatestEclipse": "1704-06-02T13:02:36Z",
      "deltaT": 8,
      "deltaTSigma": 5,
      "lunaNum": -3656,
      "sarosNum": 113,
      "eclType": "A",
      "qle": "-t",
      "gamma": -0.9561,
      "eclMag": 0.9542,
      "lat": -49,
      "long": 3,
      "sunAlt": 16,
      "pathWidth": 578,
      "centralDur": 266
    },
    {
      "tdOfGreatestEclipse": "1704-11-27T05:33:52Z",
      "deltaT": 8,
      "deltaTSigma": 5,
      "lunaNum": -3650,
      "sarosNum": 118,
      "eclType": "A",
      "qle": "-p",
      "gamma": 0.6716,
      "eclMag": 0.9999,
      "lat": 20,
      "long": 105,
      "sunAlt": 48,
      "pathWidth": 1,
      "centralDur": 1
    },
    {
      "tdOfGreatestEclipse": "1705-05-22T19:55:05Z",
      "deltaT": 9,
      "deltaTSigma": 5,
      "lunaNum": -3644,
      "sarosNum": 123,
      "eclType": "Hm",
      "qle": "nn",
      "gamma": -0.1525,
      "eclMag": 1.0147,
      "lat": 12,
      "long": -117,
      "sunAlt": 81,
      "pathWidth": 51,
      "centralDur": 92
    },
    {
      "tdOfGreatestEclipse": "1705-11-16T13:23:05Z",
      "deltaT": 9,
      "deltaTSigma": 5,
      "lunaNum": -3638,
      "sarosNum": 128,
      "eclType": "A",
      "qle": "nn",
      "gamma": -0.0271,
      "eclMag": 0.9514,
      "lat": -20,
      "long": -25,
      "sunAlt": 88,
      "pathWidth": 178,
      "centralDur": 331
    },
    {
      "tdOfGreatestEclipse": "1706-05-12T09:35:08Z",
      "deltaT": 9,
      "deltaTSigma": 5,
      "lunaNum": -3632,
      "sarosNum": 133,
      "eclType": "T",
      "qle": "p-",
      "gamma": 0.5984,
      "eclMag": 1.0591,
      "lat": 52,
      "long": 15,
      "sunAlt": 53,
      "pathWidth": 242,
      "centralDur": 246
    },
    {
      "tdOfGreatestEclipse": "1706-11-05T14:23:56Z",
      "deltaT": 9,
      "deltaTSigma": 5,
      "lunaNum": -3626,
      "sarosNum": 138,
      "eclType": "A",
      "qle": "p-",
      "gamma": -0.7407,
      "eclMag": 0.9196,
      "lat": -57,
      "long": -73,
      "sunAlt": 42,
      "pathWidth": 449,
      "centralDur": 422
    },
    {
      "tdOfGreatestEclipse": "1707-04-02T18:12:24Z",
      "deltaT": 9,
      "deltaTSigma": 5,
      "lunaNum": -3621,
      "sarosNum": 105,
      "eclType": "P",
      "qle": "-t",
      "gamma": -1.2661,
      "eclMag": 0.5083,
      "lat": -61,
      "long": -11,
      "sunAlt": 0,
      "pathWidth": 0,
      "centralDur": 0
    },
    {
      "tdOfGreatestEclipse": "1707-05-02T02:28:16Z",
      "deltaT": 9,
      "deltaTSigma": 5,
      "lunaNum": -3620,
      "sarosNum": 143,
      "eclType": "P",
      "qle": "t-",
      "gamma": 1.3047,
      "eclMag": 0.4339,
      "lat": 62,
      "long": 21,
      "sunAlt": 0,
      "pathWidth": 0,
      "centralDur": 0
    },
    {
      "tdOfGreatestEclipse": "1707-09-25T23:05:05Z",
      "deltaT": 9,
      "deltaTSigma": 5,
      "lunaNum": -3615,
      "sarosNum": 110,
      "eclType": "P",
      "qle": "-t",
      "gamma": 1.4641,
      "eclMag": 0.1604,
      "lat": 61,
      "long": -80,
      "sunAlt": 0,
      "pathWidth": 0,
      "centralDur": 0
    },
    {
      "tdOfGreatestEclipse": "1707-10-25T14:17:22Z",
      "deltaT": 9,
      "deltaTSigma": 5,
      "lunaNum": -3614,
      "sarosNum": 148,
      "eclType": "P",
      "qle": "t-",
      "gamma": -1.4161,
      "eclMag": 0.2528,
      "lat": -62,
      "long": -151,
      "sunAlt": 0,
      "pathWidth": 0,
      "centralDur": 0
    },
    {
      "tdOfGreatestEclipse": "1708-03-22T06:51:36Z",
      "deltaT": 9,
      "deltaTSigma": 5,
      "lunaNum": -3609,
      "sarosNum": 115,
      "eclType": "A",
      "qle": "-p",
      "gamma": -0.5878,
      "eclMag": 0.9913,
      "lat": -30,
      "long": 98,
      "sunAlt": 54,
      "pathWidth": 37,
      "centralDur": 46
    },
    {
      "tdOfGreatestEclipse": "1708-09-14T09:00:22Z",
      "deltaT": 9,
      "deltaTSigma": 5,
      "lunaNum": -3603,
      "sarosNum": 120,
      "eclType": "T",
      "qle": "-p",
      "gamma": 0.6685,
      "eclMag": 1.0281,
      "lat": 39,
      "long": 68,
      "sunAlt": 48,
      "pathWidth": 126,
      "centralDur": 130
    },
    {
      "tdOfGreatestEclipse": "1709-03-11T12:18:34Z",
      "deltaT": 9,
      "deltaTSigma": 5,
      "lunaNum": -3597,
      "sarosNum": 125,
      "eclType": "Am",
      "qle": "nn",
      "gamma": 0.1395,
      "eclMag": 0.9422,
      "lat": 3,
      "long": -6,
      "sunAlt": 82,
      "pathWidth": 216,
      "centralDur": 389
    },
    {
      "tdOfGreatestEclipse": "1709-09-04T00:32:26Z",
      "deltaT": 9,
      "deltaTSigma": 5,
      "lunaNum": -3591,
      "sarosNum": 130,
      "eclType": "T",
      "qle": "nn",
      "gamma": -0.0725,
      "eclMag": 1.0703,
      "lat": 4,
      "long": 170,
      "sunAlt": 86,
      "pathWidth": 229,
      "centralDur": 347
    },
    {
      "tdOfGreatestEclipse": "1710-02-28T12:07:28Z",
      "deltaT": 9,
      "deltaTSigma": 5,
      "lunaNum": -3585,
      "sarosNum": 135,
      "eclType": "A",
      "qle": "p-",
      "gamma": 0.8509,
      "eclMag": 0.9194,
      "lat": 43,
      "long": -31,
      "sunAlt": 31,
      "pathWidth": 562,
      "centralDur": 480
    },
    {
      "tdOfGreatestEclipse": "1710-08-24T17:17:15Z",
      "deltaT": 9,
      "deltaTSigma": 5,
      "lunaNum": -3579,
      "sarosNum": 140,
      "eclType": "T",
      "qle": "p-",
      "gamma": -0.8031,
      "eclMag": 1.0519,
      "lat": -36,
      "long": -105,
      "sunAlt": 36,
      "pathWidth": 282,
      "centralDur": 240
    },
    {
      "tdOfGreatestEclipse": "1711-01-18T22:23:37Z",
      "deltaT": 9,
      "deltaTSigma": 5,
      "lunaNum": -3574,
      "sarosNum": 107,
      "eclType": "P",
      "qle": "-t",
      "gamma": -1.3796,
      "eclMag": 0.3076,
      "lat": -64,
      "long": -14,
      "sunAlt": 0,
      "pathWidth": 0,
      "centralDur": 0
    },
    {
      "tdOfGreatestEclipse": "1711-02-17T13:30:14Z",
      "deltaT": 9,
      "deltaTSigma": 5,
      "lunaNum": -3573,
      "sarosNum": 145,
      "eclType": "P",
      "qle": "t-",
      "gamma": 1.5077,
      "eclMag": 0.0919,
      "lat": 62,
      "long": -85,
      "sunAlt": 0,
      "pathWidth": 0,
      "centralDur": 0
    },
    {
      "tdOfGreatestEclipse": "1711-07-15T19:22:11Z",
      "deltaT": 9,
      "deltaTSigma": 5,
      "lunaNum": -3568,
      "sarosNum": 112,
      "eclType": "P",
      "qle": "-t",
      "gamma": 1.0894,
      "eclMag": 0.8217,
      "lat": 64,
      "long": 35,
      "sunAlt": 0,
      "pathWidth": 0,
      "centralDur": 0
    },
    {
      "tdOfGreatestEclipse": "1712-01-08T09:58:39Z",
      "deltaT": 9,
      "deltaTSigma": 5,
      "lunaNum": -3562,
      "sarosNum": 117,
      "eclType": "T",
      "qle": "-p",
      "gamma": -0.6406,
      "eclMag": 1.0258,
      "lat": -61,
      "long": 49,
      "sunAlt": 50,
      "pathWidth": 114,
      "centralDur": 108
    },
    {
      "tdOfGreatestEclipse": "1712-07-03T22:34:57Z",
      "deltaT": 9,
      "deltaTSigma": 4,
      "lunaNum": -3556,
      "sarosNum": 122,
      "eclType": "A",
      "qle": "-p",
      "gamma": 0.3433,
      "eclMag": 0.9503,
      "lat": 43,
      "long": -153,
      "sunAlt": 70,
      "pathWidth": 194,
      "centralDur": 318
    },
    {
      "tdOfGreatestEclipse": "1712-12-28T01:24:54Z",
      "deltaT": 9,
      "deltaTSigma": 4,
      "lunaNum": -3550,
      "sarosNum": 127,
      "eclType": "T",
      "qle": "nn",
      "gamma": 0.0347,
      "eclMag": 1.0466,
      "lat": -21,
      "long": 159,
      "sunAlt": 88,
      "pathWidth": 155,
      "centralDur": 255
    },
    {
      "tdOfGreatestEclipse": "1713-06-22T23:15:38Z",
      "deltaT": 9,
      "deltaTSigma": 4,
      "lunaNum": -3544,
      "sarosNum": 132,
      "eclType": "A",
      "qle": "p-",
      "gamma": -0.4217,
      "eclMag": 0.9576,
      "lat": -1,
      "long": -171,
      "sunAlt": 65,
      "pathWidth": 170,
      "centralDur": 345
    },
    {
      "tdOfGreatestEclipse": "1713-12-17T16:04:20Z",
      "deltaT": 9,
      "deltaTSigma": 4,
      "lunaNum": -3538,
      "sarosNum": 137,
      "eclType": "H",
      "qle": "p-",
      "gamma": 0.7249,
      "eclMag": 1.0094,
      "lat": 23,
      "long": -65,
      "sunAlt": 43,
      "pathWidth": 47,
      "centralDur": 56
    },
    {
      "tdOfGreatestEclipse": "1714-05-13T18:39:34Z",
      "deltaT": 9,
      "deltaTSigma": 4,
      "lunaNum": -3533,
      "sarosNum": 104,
      "eclType": "Pe",
      "qle": "-t",
      "gamma": 1.4855,
      "eclMag": 0.1008,
      "lat": 69,
      "long": 107,
      "sunAlt": 0,
      "pathWidth": 0,
      "centralDur": 0
    },
    {
      "tdOfGreatestEclipse": "1714-06-12T04:40:01Z",
      "deltaT": 9,
      "deltaTSigma": 4,
      "lunaNum": -3532,
      "sarosNum": 142,
      "eclType": "P",
      "qle": "t-",
      "gamma": -1.161,
      "eclMag": 0.6976,
      "lat": -67,
      "long": 106,
      "sunAlt": 0,
      "pathWidth": 0,
      "centralDur": 0
    },
    {
      "tdOfGreatestEclipse": "1714-11-07T09:04:34Z",
      "deltaT": 9,
      "deltaTSigma": 4,
      "lunaNum": -3527,
      "sarosNum": 109,
      "eclType": "P",
      "qle": "-t",
      "gamma": -1.463,
      "eclMag": 0.1731,
      "lat": -70,
      "long": -104,
      "sunAlt": 0,
      "pathWidth": 0,
      "centralDur": 0
    },
    {
      "tdOfGreatestEclipse": "1714-12-07T01:27:09Z",
      "deltaT": 9,
      "deltaTSigma": 4,
      "lunaNum": -3526,
      "sarosNum": 147,
      "eclType": "P",
      "qle": "t-",
      "gamma": 1.4772,
      "eclMag": 0.142,
      "lat": 67,
      "long": 159,
      "sunAlt": 0,
      "pathWidth": 0,
      "centralDur": 0
    },
    {
      "tdOfGreatestEclipse": "1715-05-03T09:36:29Z",
      "deltaT": 9,
      "deltaTSigma": 4,
      "lunaNum": -3521,
      "sarosNum": 114,
      "eclType": "T",
      "qle": "-p",
      "gamma": 0.7112,
      "eclMag": 1.0632,
      "lat": 59,
      "long": 18,
      "sunAlt": 44,
      "pathWidth": 295,
      "centralDur": 254
    },
    {
      "tdOfGreatestEclipse": "1715-10-27T09:02:48Z",
      "deltaT": 9,
      "deltaTSigma": 4,
      "lunaNum": -3515,
      "sarosNum": 119,
      "eclType": "A",
      "qle": "-p",
      "gamma": -0.7939,
      "eclMag": 0.9206,
      "lat": -62,
      "long": 16,
      "sunAlt": 37,
      "pathWidth": 494,
      "centralDur": 422
    },
    {
      "tdOfGreatestEclipse": "1716-04-22T02:28:32Z",
      "deltaT": 9,
      "deltaTSigma": 4,
      "lunaNum": -3509,
      "sarosNum": 124,
      "eclType": "T",
      "qle": "nn",
      "gamma": -0.0091,
      "eclMag": 1.0625,
      "lat": 12,
      "long": 143,
      "sunAlt": 90,
      "pathWidth": 205,
      "centralDur": 343
    },
    {
      "tdOfGreatestEclipse": "1716-10-15T10:07:38Z",
      "deltaT": 10,
      "deltaTSigma": 4,
      "lunaNum": -3503,
      "sarosNum": 129,
      "eclType": "A",
      "qle": "nn",
      "gamma": -0.0687,
      "eclMag": 0.957,
      "lat": -13,
      "long": 23,
      "sunAlt": 86,
      "pathWidth": 157,
      "centralDur": 310
    },
    {
      "tdOfGreatestEclipse": "1717-04-11T16:34:40Z",
      "deltaT": 10,
      "deltaTSigma": 4,
      "lunaNum": -3497,
      "sarosNum": 134,
      "eclType": "H",
      "qle": "p-",
      "gamma": -0.766,
      "eclMag": 1.0072,
      "lat": -40,
      "long": -52,
      "sunAlt": 40,
      "pathWidth": 39,
      "centralDur": 39
    },
    {
      "tdOfGreatestEclipse": "1717-10-04T18:08:27Z",
      "deltaT": 10,
      "deltaTSigma": 4,
      "lunaNum": -3491,
      "sarosNum": 139,
      "eclType": "H",
      "qle": "p-",
      "gamma": 0.6563,
      "eclMag": 1.0104,
      "lat": 35,
      "long": -81,
      "sunAlt": 49,
      "pathWidth": 47,
      "centralDur": 56
    },
    {
      "tdOfGreatestEclipse": "1718-03-02T07:31:36Z",
      "deltaT": 10,
      "deltaTSigma": 4,
      "lunaNum": -3486,
      "sarosNum": 106,
      "eclType": "P",
      "qle": "-t",
      "gamma": 1.3723,
      "eclMag": 0.3285,
      "lat": 72,
      "long": 3,
      "sunAlt": 0,
      "pathWidth": 0,
      "centralDur": 0
    },
    {
      "tdOfGreatestEclipse": "1718-08-26T00:41:45Z",
      "deltaT": 10,
      "deltaTSigma": 4,
      "lunaNum": -3480,
      "sarosNum": 111,
      "eclType": "P",
      "qle": "-t",
      "gamma": -1.2267,
      "eclMag": 0.5838,
      "lat": -71,
      "long": 114,
      "sunAlt": 0,
      "pathWidth": 0,
      "centralDur": 0
    },
    {
      "tdOfGreatestEclipse": "1718-09-24T08:34:19Z",
      "deltaT": 10,
      "deltaTSigma": 4,
      "lunaNum": -3479,
      "sarosNum": 149,
      "eclType": "P",
      "qle": "t-",
      "gamma": 1.3283,
      "eclMag": 0.3888,
      "lat": 72,
      "long": 138,
      "sunAlt": 0,
      "pathWidth": 0,
      "centralDur": 0
    },
    {
      "tdOfGreatestEclipse": "1719-02-19T06:52:57Z",
      "deltaT": 10,
      "deltaTSigma": 4,
      "lunaNum": -3474,
      "sarosNum": 116,
      "eclType": "A",
      "qle": "-p",
      "gamma": 0.6855,
      "eclMag": 0.925,
      "lat": 31,
      "long": 69,
      "sunAlt": 47,
      "pathWidth": 384,
      "centralDur": 541
    },
    {
      "tdOfGreatestEclipse": "1719-08-15T16:59:51Z",
      "deltaT": 10,
      "deltaTSigma": 4,
      "lunaNum": -3468,
      "sarosNum": 121,
      "eclType": "T",
      "qle": "-p",
      "gamma": -0.5243,
      "eclMag": 1.0466,
      "lat": -17,
      "long": -81,
      "sunAlt": 58,
      "pathWidth": 181,
      "centralDur": 267
    },
    {
      "tdOfGreatestEclipse": "1720-02-08T09:52:30Z",
      "deltaT": 10,
      "deltaTSigma": 4,
      "lunaNum": -3462,
      "sarosNum": 126,
      "eclType": "A",
      "qle": "nn",
      "gamma": -0.0375,
      "eclMag": 0.9681,
      "lat": -17,
      "long": 36,
      "sunAlt": 88,
      "pathWidth": 115,
      "centralDur": 220
    },
    {
      "tdOfGreatestEclipse": "1720-08-04T04:38:14Z",
      "deltaT": 10,
      "deltaTSigma": 4,
      "lunaNum": -3456,
      "sarosNum": 131,
      "eclType": "A",
      "qle": "nn",
      "gamma": 0.241,
      "eclMag": 0.9957,
      "lat": 31,
      "long": 115,
      "sunAlt": 76,
      "pathWidth": 16,
      "centralDur": 27
    },
    {
      "tdOfGreatestEclipse": "1721-01-27T20:05:11Z",
      "deltaT": 10,
      "deltaTSigma": 4,
      "lunaNum": -3450,
      "sarosNum": 136,
      "eclType": "T",
      "qle": "p-",
      "gamma": -0.7269,
      "eclMag": 1.0158,
      "lat": -64,
      "long": -102,
      "sunAlt": 43,
      "pathWidth": 79,
      "centralDur": 67
    },
    {
      "tdOfGreatestEclipse": "1721-07-24T09:06:55Z",
      "deltaT": 10,
      "deltaTSigma": 4,
      "lunaNum": -3444,
      "sarosNum": 141,
      "eclType": "P",
      "qle": "t-",
      "gamma": 1.0383,
      "eclMag": 0.899,
      "lat": 69,
      "long": -155,
      "sunAlt": 0,
      "pathWidth": 0,
      "centralDur": 0
    },
    {
      "tdOfGreatestEclipse": "1721-12-19T00:31:50Z",
      "deltaT": 10,
      "deltaTSigma": 4,
      "lunaNum": -3439,
      "sarosNum": 108,
      "eclType": "P",
      "qle": "-t",
      "gamma": 1.3144,
      "eclMag": 0.4172,
      "lat": 66,
      "long": -172,
      "sunAlt": 0,
      "pathWidth": 0,
      "centralDur": 0
    },
    {
      "tdOfGreatestEclipse": "1722-01-17T11:07:09Z",
      "deltaT": 10,
      "deltaTSigma": 4,
      "lunaNum": -3438,
      "sarosNum": 146,
      "eclType": "P",
      "qle": "t-",
      "gamma": -1.3629,
      "eclMag": 0.3251,
      "lat": -68,
      "long": -180,
      "sunAlt": 0,
      "pathWidth": 0,
      "centralDur": 0
    },
    {
      "tdOfGreatestEclipse": "1722-06-13T19:40:18Z",
      "deltaT": 10,
      "deltaTSigma": 4,
      "lunaNum": -3433,
      "sarosNum": 113,
      "eclType": "P",
      "qle": "-t",
      "gamma": -1.0364,
      "eclMag": 0.9084,
      "lat": -65,
      "long": -94,
      "sunAlt": 0,
      "pathWidth": 0,
      "centralDur": 0
    },
    {
      "tdOfGreatestEclipse": "1722-12-08T14:07:34Z",
      "deltaT": 10,
      "deltaTSigma": 4,
      "lunaNum": -3427,
      "sarosNum": 118,
      "eclType": "A",
      "qle": "-p",
      "gamma": 0.6808,
      "eclMag": 0.9955,
      "lat": 20,
      "long": -25,
      "sunAlt": 47,
      "pathWidth": 21,
      "centralDur": 28
    },
    {
      "tdOfGreatestEclipse": "1723-06-03T03:05:13Z",
      "deltaT": 10,
      "deltaTSigma": 4,
      "lunaNum": -3421,
      "sarosNum": 123,
      "eclType": "T",
      "qle": "nn",
      "gamma": -0.2251,
      "eclMag": 1.0196,
      "lat": 10,
      "long": 136,
      "sunAlt": 77,
      "pathWidth": 69,
      "centralDur": 125
    },
    {
      "tdOfGreatestEclipse": "1723-11-27T21:28:15Z",
      "deltaT": 10,
      "deltaTSigma": 4,
      "lunaNum": -3415,
      "sarosNum": 128,
      "eclType": "A",
      "qle": "nn",
      "gamma": -0.0125,
      "eclMag": 0.9471,
      "lat": -22,
      "long": -145,
      "sunAlt": 89,
      "pathWidth": 195,
      "centralDur": 372
    },
    {
      "tdOfGreatestEclipse": "1724-05-22T17:10:08Z",
      "deltaT": 10,
      "deltaTSigma": 4,
      "lunaNum": -3409,
      "sarosNum": 133,
      "eclType": "T",
      "qle": "p-",
      "gamma": 0.5319,
      "eclMag": 1.064,
      "lat": 51,
      "long": -93,
      "sunAlt": 58,
      "pathWidth": 247,
      "centralDur": 273
    },
    {
      "tdOfGreatestEclipse": "1724-11-15T22:07:37Z",
      "deltaT": 10,
      "deltaTSigma": 4,
      "lunaNum": -3403,
      "sarosNum": 138,
      "eclType": "A",
      "qle": "p-",
      "gamma": -0.7183,
      "eclMag": 0.9174,
      "lat": -60,
      "long": 175,
      "sunAlt": 44,
      "pathWidth": 448,
      "centralDur": 435
    },
    {
      "tdOfGreatestEclipse": "1725-04-13T02:11:22Z",
      "deltaT": 10,
      "deltaTSigma": 4,
      "lunaNum": -3398,
      "sarosNum": 105,
      "eclType": "P",
      "qle": "-t",
      "gamma": -1.3132,
      "eclMag": 0.4193,
      "lat": -61,
      "long": -140,
      "sunAlt": 0,
      "pathWidth": 0,
      "centralDur": 0
    },
    {
      "tdOfGreatestEclipse": "1725-05-12T10:12:19Z",
      "deltaT": 10,
      "deltaTSigma": 4,
      "lunaNum": -3397,
      "sarosNum": 143,
      "eclType": "P",
      "qle": "t-",
      "gamma": 1.2472,
      "eclMag": 0.5447,
      "lat": 63,
      "long": -104,
      "sunAlt": 0,
      "pathWidth": 0,
      "centralDur": 0
    },
    {
      "tdOfGreatestEclipse": "1725-10-06T06:39:42Z",
      "deltaT": 10,
      "deltaTSigma": 4,
      "lunaNum": -3392,
      "sarosNum": 110,
      "eclType": "P",
      "qle": "-t",
      "gamma": 1.5028,
      "eclMag": 0.0924,
      "lat": 61,
      "long": 158,
      "sunAlt": 0,
      "pathWidth": 0,
      "centralDur": 0
    },
    {
      "tdOfGreatestEclipse": "1725-11-04T22:02:51Z",
      "deltaT": 10,
      "deltaTSigma": 4,
      "lunaNum": -3391,
      "sarosNum": 148,
      "eclType": "P",
      "qle": "t-",
      "gamma": -1.3861,
      "eclMag": 0.3038,
      "lat": -62,
      "long": 83,
      "sunAlt": 0,
      "pathWidth": 0,
      "centralDur": 0
    },
    {
      "tdOfGreatestEclipse": "1726-04-02T14:38:16Z",
      "deltaT": 10,
      "deltaTSigma": 4,
      "lunaNum": -3386,
      "sarosNum": 115,
      "eclType": "A",
      "qle": "-p",
      "gamma": -0.6312,
      "eclMag": 0.9906,
      "lat": -29,
      "long": -18,
      "sunAlt": 51,
      "pathWidth": 42,
      "centralDur": 52
    },
    {
      "tdOfGreatestEclipse": "1726-09-25T16:51:44Z",
      "deltaT": 10,
      "deltaTSigma": 4,
      "lunaNum": -3380,
      "sarosNum": 120,
      "eclType": "T",
      "qle": "-p",
      "gamma": 0.7133,
      "eclMag": 1.0273,
      "lat": 38,
      "long": -49,
      "sunAlt": 44,
      "pathWidth": 129,
      "centralDur": 127
    },
    {
      "tdOfGreatestEclipse": "1727-03-22T19:47:55Z",
      "deltaT": 10,
      "deltaTSigma": 4,
      "lunaNum": -3374,
      "sarosNum": 125,
      "eclType": "A",
      "qle": "nn",
      "gamma": 0.0996,
      "eclMag": 0.9432,
      "lat": 6,
      "long": -118,
      "sunAlt": 84,
      "pathWidth": 211,
      "centralDur": 380
    },
    {
      "tdOfGreatestEclipse": "1727-09-15T08:27:30Z",
      "deltaT": 10,
      "deltaTSigma": 4,
      "lunaNum": -3368,
      "sarosNum": 130,
      "eclType": "T",
      "qle": "nn",
      "gamma": -0.0202,
      "eclMag": 1.0681,
      "lat": 2,
      "long": 51,
      "sunAlt": 89,
      "pathWidth": 222,
      "centralDur": 333
    },
    {
      "tdOfGreatestEclipse": "1728-03-10T19:38:55Z",
      "deltaT": 10,
      "deltaTSigma": 4,
      "lunaNum": -3362,
      "sarosNum": 135,
      "eclType": "A",
      "qle": "p-",
      "gamma": 0.8172,
      "eclMag": 0.9233,
      "lat": 43,
      "long": -145,
      "sunAlt": 35,
      "pathWidth": 485,
      "centralDur": 445
    },
    {
      "tdOfGreatestEclipse": "1728-09-04T00:59:22Z",
      "deltaT": 10,
      "deltaTSigma": 4,
      "lunaNum": -3356,
      "sarosNum": 140,
      "eclType": "T",
      "qle": "p-",
      "gamma": -0.7466,
      "eclMag": 1.0484,
      "lat": -35,
      "long": 140,
      "sunAlt": 41,
      "pathWidth": 236,
      "centralDur": 224
    },
    {
      "tdOfGreatestEclipse": "1729-01-29T06:48:43Z",
      "deltaT": 10,
      "deltaTSigma": 4,
      "lunaNum": -3351,
      "sarosNum": 107,
      "eclType": "P",
      "qle": "-t",
      "gamma": -1.3838,
      "eclMag": 0.2994,
      "lat": -63,
      "long": -150,
      "sunAlt": 0,
      "pathWidth": 0,
      "centralDur": 0
    },
    {
      "tdOfGreatestEclipse": "1729-02-27T21:27:02Z",
      "deltaT": 10,
      "deltaTSigma": 4,
      "lunaNum": -3350,
      "sarosNum": 145,
      "eclType": "P",
      "qle": "t-",
      "gamma": 1.4817,
      "eclMag": 0.1347,
      "lat": 61,
      "long": 147,
      "sunAlt": 0,
      "pathWidth": 0,
      "centralDur": 0
    },
    {
      "tdOfGreatestEclipse": "1729-07-26T02:10:39Z",
      "deltaT": 10,
      "deltaTSigma": 4,
      "lunaNum": -3345,
      "sarosNum": 112,
      "eclType": "P",
      "qle": "-t",
      "gamma": 1.1717,
      "eclMag": 0.6747,
      "lat": 63,
      "long": -77,
      "sunAlt": 0,
      "pathWidth": 0,
      "centralDur": 0
    },
    {
      "tdOfGreatestEclipse": "1729-08-24T13:48:31Z",
      "deltaT": 10,
      "deltaTSigma": 4,
      "lunaNum": -3344,
      "sarosNum": 150,
      "eclType": "Pb",
      "qle": "t-",
      "gamma": -1.543,
      "eclMag": 0.0067,
      "lat": -62,
      "long": -95,
      "sunAlt": 0,
      "pathWidth": 0,
      "centralDur": 0
    },
    {
      "tdOfGreatestEclipse": "1730-01-18T18:45:15Z",
      "deltaT": 10,
      "deltaTSigma": 4,
      "lunaNum": -3339,
      "sarosNum": 117,
      "eclType": "T",
      "qle": "-p",
      "gamma": -0.6439,
      "eclMag": 1.0286,
      "lat": -58,
      "long": -77,
      "sunAlt": 50,
      "pathWidth": 126,
      "centralDur": 119
    },
    {
      "tdOfGreatestEclipse": "1730-07-15T04:59:08Z",
      "deltaT": 10,
      "deltaTSigma": 4,
      "lunaNum": -3333,
      "sarosNum": 122,
      "eclType": "A",
      "qle": "-p",
      "gamma": 0.4325,
      "eclMag": 0.9484,
      "lat": 46,
      "long": 116,
      "sunAlt": 64,
      "pathWidth": 210,
      "centralDur": 313
    },
    {
      "tdOfGreatestEclipse": "1731-01-08T10:17:44Z",
      "deltaT": 10,
      "deltaTSigma": 4,
      "lunaNum": -3327,
      "sarosNum": 127,
      "eclType": "Tm",
      "qle": "nn",
      "gamma": 0.0313,
      "eclMag": 1.0464,
      "lat": -21,
      "long": 27,
      "sunAlt": 88,
      "pathWidth": 155,
      "centralDur": 250
    },
    {
      "tdOfGreatestEclipse": "1731-07-04T05:46:25Z",
      "deltaT": 11,
      "deltaTSigma": 4,
      "lunaNum": -3321,
      "sarosNum": 132,
      "eclType": "A",
      "qle": "p-",
      "gamma": -0.3341,
      "eclMag": 0.9602,
      "lat": 4,
      "long": 91,
      "sunAlt": 71,
      "pathWidth": 153,
      "centralDur": 315
    },
    {
      "tdOfGreatestEclipse": "1731-12-29T00:46:52Z",
      "deltaT": 11,
      "deltaTSigma": 4,
      "lunaNum": -3315,
      "sarosNum": 137,
      "eclType": "H",
      "qle": "p-",
      "gamma": 0.7234,
      "eclMag": 1.0065,
      "lat": 23,
      "long": 162,
      "sunAlt": 44,
      "pathWidth": 32,
      "centralDur": 39
    },
    {
      "tdOfGreatestEclipse": "1732-06-22T11:38:47Z",
      "deltaT": 11,
      "deltaTSigma": 4,
      "lunaNum": -3309,
      "sarosNum": 142,
      "eclType": "P",
      "qle": "t-",
      "gamma": -1.08,
      "eclMag": 0.8457,
      "lat": -66,
      "long": -9,
      "sunAlt": 0,
      "pathWidth": 0,
      "centralDur": 0
    },
    {
      "tdOfGreatestEclipse": "1732-11-17T16:58:50Z",
      "deltaT": 11,
      "deltaTSigma": 4,
      "lunaNum": -3304,
      "sarosNum": 109,
      "eclType": "P",
      "qle": "-t",
      "gamma": -1.4841,
      "eclMag": 0.139,
      "lat": -69,
      "long": 125,
      "sunAlt": 0,
      "pathWidth": 0,
      "centralDur": 0
    },
    {
      "tdOfGreatestEclipse": "1732-12-17T09:46:56Z",
      "deltaT": 11,
      "deltaTSigma": 4,
      "lunaNum": -3303,
      "sarosNum": 147,
      "eclType": "P",
      "qle": "t-",
      "gamma": 1.4752,
      "eclMag": 0.147,
      "lat": 66,
      "long": 23,
      "sunAlt": 0,
      "pathWidth": 0,
      "centralDur": 0
    },
    {
      "tdOfGreatestEclipse": "1733-05-13T17:18:28Z",
      "deltaT": 11,
      "deltaTSigma": 4,
      "lunaNum": -3298,
      "sarosNum": 114,
      "eclType": "T",
      "qle": "-p",
      "gamma": 0.7712,
      "eclMag": 1.0656,
      "lat": 68,
      "long": -99,
      "sunAlt": 39,
      "pathWidth": 339,
      "centralDur": 246
    },
    {
      "tdOfGreatestEclipse": "1733-11-06T16:40:14Z",
      "deltaT": 11,
      "deltaTSigma": 4,
      "lunaNum": -3292,
      "sarosNum": 119,
      "eclType": "A",
      "qle": "-p",
      "gamma": -0.8208,
      "eclMag": 0.9179,
      "lat": -69,
      "long": -101,
      "sunAlt": 34,
      "pathWidth": 548,
      "centralDur": 413
    },
    {
      "tdOfGreatestEclipse": "1734-05-03T10:15:56Z",
      "deltaT": 11,
      "deltaTSigma": 4,
      "lunaNum": -3286,
      "sarosNum": 124,
      "eclType": "T",
      "qle": "nn",
      "gamma": 0.0472,
      "eclMag": 1.0635,
      "lat": 18,
      "long": 25,
      "sunAlt": 87,
      "pathWidth": 208,
      "centralDur": 346
    },
    {
      "tdOfGreatestEclipse": "1734-10-26T17:53:27Z",
      "deltaT": 11,
      "deltaTSigma": 4,
      "lunaNum": -3280,
      "sarosNum": 129,
      "eclType": "A",
      "qle": "nn",
      "gamma": -0.0996,
      "eclMag": 0.9567,
      "lat": -18,
      "long": -94,
      "sunAlt": 84,
      "pathWidth": 159,
      "centralDur": 308
    },
    {
      "tdOfGreatestEclipse": "1735-04-23T00:11:35Z",
      "deltaT": 11,
      "deltaTSigma": 4,
      "lunaNum": -3274,
      "sarosNum": 134,
      "eclType": "H",
      "qle": "p-",
      "gamma": -0.7164,
      "eclMag": 1.0077,
      "lat": -32,
      "long": -171,
      "sunAlt": 44,
      "pathWidth": 38,
      "centralDur": 44
    },
    {
      "tdOfGreatestEclipse": "1735-10-16T02:10:33Z",
      "deltaT": 11,
      "deltaTSigma": 4,
      "lunaNum": -3268,
      "sarosNum": 139,
      "eclType": "H",
      "qle": "p-",
      "gamma": 0.6202,
      "eclMag": 1.011,
      "lat": 28,
      "long": 155,
      "sunAlt": 51,
      "pathWidth": 48,
      "centralDur": 62
    },
    {
      "tdOfGreatestEclipse": "1736-03-12T15:05:55Z",
      "deltaT": 11,
      "deltaTSigma": 4,
      "lunaNum": -3263,
      "sarosNum": 106,
      "eclType": "P",
      "qle": "-t",
      "gamma": 1.4049,
      "eclMag": 0.2733,
      "lat": 72,
      "long": -124,
      "sunAlt": 0,
      "pathWidth": 0,
      "centralDur": 0
    },
    {
      "tdOfGreatestEclipse": "1736-04-11T07:18:06Z",
      "deltaT": 11,
      "deltaTSigma": 4,
      "lunaNum": -3262,
      "sarosNum": 144,
      "eclType": "Pb",
      "qle": "t-",
      "gamma": -1.5166,
      "eclMag": 0.0748,
      "lat": -72,
      "long": 134,
      "sunAlt": 0,
      "pathWidth": 0,
      "centralDur": 0
    },
    {
      "tdOfGreatestEclipse": "1736-09-05T08:30:25Z",
      "deltaT": 11,
      "deltaTSigma": 4,
      "lunaNum": -3257,
      "sarosNum": 111,
      "eclType": "P",
      "qle": "-t",
      "gamma": -1.2817,
      "eclMag": 0.4776,
      "lat": -72,
      "long": -17,
      "sunAlt": 0,
      "pathWidth": 0,
      "centralDur": 0
    },
    {
      "tdOfGreatestEclipse": "1736-10-04T16:41:33Z",
      "deltaT": 11,
      "deltaTSigma": 4,
      "lunaNum": -3256,
      "sarosNum": 149,
      "eclType": "P",
      "qle": "t-",
      "gamma": 1.2874,
      "eclMag": 0.467,
      "lat": 72,
      "long": 2,
      "sunAlt": 0,
      "pathWidth": 0,
      "centralDur": 0
    },
    {
      "tdOfGreatestEclipse": "1737-03-01T14:35:17Z",
      "deltaT": 11,
      "deltaTSigma": 4,
      "lunaNum": -3251,
      "sarosNum": 116,
      "eclType": "A",
      "qle": "-p",
      "gamma": 0.7098,
      "eclMag": 0.9283,
      "lat": 36,
      "long": -50,
      "sunAlt": 45,
      "pathWidth": 378,
      "centralDur": 484
    },
    {
      "tdOfGreatestEclipse": "1737-08-26T00:32:08Z",
      "deltaT": 11,
      "deltaTSigma": 3,
      "lunaNum": -3245,
      "sarosNum": 121,
      "eclType": "T",
      "qle": "-p",
      "gamma": -0.5885,
      "eclMag": 1.0407,
      "lat": -24,
      "long": 163,
      "sunAlt": 54,
      "pathWidth": 167,
      "centralDur": 224
    },
    {
      "tdOfGreatestEclipse": "1738-02-18T18:02:31Z",
      "deltaT": 11,
      "deltaTSigma": 3,
      "lunaNum": -3239,
      "sarosNum": 126,
      "eclType": "A",
      "qle": "nn",
      "gamma": -0.0211,
      "eclMag": 0.9732,
      "lat": -13,
      "long": -87,
      "sunAlt": 89,
      "pathWidth": 96,
      "centralDur": 183
    },
    {
      "tdOfGreatestEclipse": "1738-08-15T11:40:12Z",
      "deltaT": 11,
      "deltaTSigma": 3,
      "lunaNum": -3233,
      "sarosNum": 131,
      "eclType": "A",
      "qle": "nn",
      "gamma": 0.1688,
      "eclMag": 0.9907,
      "lat": 24,
      "long": 8,
      "sunAlt": 80,
      "pathWidth": 33,
      "centralDur": 60
    },
    {
      "tdOfGreatestEclipse": "1739-02-08T04:41:13Z",
      "deltaT": 11,
      "deltaTSigma": 3,
      "lunaNum": -3227,
      "sarosNum": 136,
      "eclType": "T",
      "qle": "p-",
      "gamma": -0.715,
      "eclMag": 1.0203,
      "lat": -59,
      "long": 131,
      "sunAlt": 44,
      "pathWidth": 99,
      "centralDur": 87
    },
    {
      "tdOfGreatestEclipse": "1739-08-04T15:40:56Z",
      "deltaT": 11,
      "deltaTSigma": 3,
      "lunaNum": -3221,
      "sarosNum": 141,
      "eclType": "A",
      "qle": "t-",
      "gamma": 0.9588,
      "eclMag": 0.9408,
      "lat": 80,
      "long": 43,
      "sunAlt": 16,
      "pathWidth": 801,
      "centralDur": 239
    },
    {
      "tdOfGreatestEclipse": "1739-12-30T09:22:03Z",
      "deltaT": 11,
      "deltaTSigma": 3,
      "lunaNum": -3216,
      "sarosNum": 108,
      "eclType": "P",
      "qle": "-t",
      "gamma": 1.3203,
      "eclMag": 0.4062,
      "lat": 67,
      "long": 45,
      "sunAlt": 0,
      "pathWidth": 0,
      "centralDur": 0
    },
    {
      "tdOfGreatestEclipse": "1740-01-28T19:54:59Z",
      "deltaT": 11,
      "deltaTSigma": 3,
      "lunaNum": -3215,
      "sarosNum": 146,
      "eclType": "P",
      "qle": "t-",
      "gamma": -1.3556,
      "eclMag": 0.3387,
      "lat": -69,
      "long": 36,
      "sunAlt": 0,
      "pathWidth": 0,
      "centralDur": 0
    },
    {
      "tdOfGreatestEclipse": "1740-06-24T02:18:53Z",
      "deltaT": 11,
      "deltaTSigma": 3,
      "lunaNum": -3210,
      "sarosNum": 113,
      "eclType": "P",
      "qle": "-t",
      "gamma": -1.1163,
      "eclMag": 0.7697,
      "lat": -66,
      "long": 157,
      "sunAlt": 0,
      "pathWidth": 0,
      "centralDur": 0
    },
    {
      "tdOfGreatestEclipse": "1740-12-18T22:43:17Z",
      "deltaT": 11,
      "deltaTSigma": 3,
      "lunaNum": -3204,
      "sarosNum": 118,
      "eclType": "A",
      "qle": "-p",
      "gamma": 0.6876,
      "eclMag": 0.9917,
      "lat": 20,
      "long": -156,
      "sunAlt": 46,
      "pathWidth": 40,
      "centralDur": 53
    },
    {
      "tdOfGreatestEclipse": "1741-06-13T10:12:47Z",
      "deltaT": 12,
      "deltaTSigma": 3,
      "lunaNum": -3198,
      "sarosNum": 123,
      "eclType": "T",
      "qle": "-n",
      "gamma": -0.3007,
      "eclMag": 1.0239,
      "lat": 6,
      "long": 29,
      "sunAlt": 73,
      "pathWidth": 85,
      "centralDur": 155
    },
    {
      "tdOfGreatestEclipse": "1741-12-08T05:37:59Z",
      "deltaT": 12,
      "deltaTSigma": 3,
      "lunaNum": -3192,
      "sarosNum": 128,
      "eclType": "A",
      "qle": "nn",
      "gamma": -0.0024,
      "eclMag": 0.9434,
      "lat": -23,
      "long": 94,
      "sunAlt": 90,
      "pathWidth": 209,
      "centralDur": 411
    },
    {
      "tdOfGreatestEclipse": "1742-06-03T00:39:56Z",
      "deltaT": 12,
      "deltaTSigma": 3,
      "lunaNum": -3186,
      "sarosNum": 133,
      "eclType": "T",
      "qle": "p-",
      "gamma": 0.4607,
      "eclMag": 1.0683,
      "lat": 49,
      "long": 160,
      "sunAlt": 62,
      "pathWidth": 251,
      "centralDur": 300
    },
    {
      "tdOfGreatestEclipse": "1742-11-27T05:58:59Z",
      "deltaT": 12,
      "deltaTSigma": 3,
      "lunaNum": -3180,
      "sarosNum": 138,
      "eclType": "A",
      "qle": "p-",
      "gamma": -0.7019,
      "eclMag": 0.9156,
      "lat": -63,
      "long": 62,
      "sunAlt": 45,
      "pathWidth": 450,
      "centralDur": 446
    },
    {
      "tdOfGreatestEclipse": "1743-04-24T10:00:09Z",
      "deltaT": 12,
      "deltaTSigma": 3,
      "lunaNum": -3175,
      "sarosNum": 105,
      "eclType": "P",
      "qle": "-t",
      "gamma": -1.3682,
      "eclMag": 0.3153,
      "lat": -62,
      "long": 94,
      "sunAlt": 0,
      "pathWidth": 0,
      "centralDur": 0
    },
    {
      "tdOfGreatestEclipse": "1743-05-23T17:48:55Z",
      "deltaT": 12,
      "deltaTSigma": 3,
      "lunaNum": -3174,
      "sarosNum": 143,
      "eclType": "P",
      "qle": "t-",
      "gamma": 1.1838,
      "eclMag": 0.6671,
      "lat": 64,
      "long": 133,
      "sunAlt": 0,
      "pathWidth": 0,
      "centralDur": 0
    },
    {
      "tdOfGreatestEclipse": "1743-10-17T14:25:41Z",
      "deltaT": 12,
      "deltaTSigma": 3,
      "lunaNum": -3169,
      "sarosNum": 110,
      "eclType": "Pe",
      "qle": "-t",
      "gamma": 1.5334,
      "eclMag": 0.0388,
      "lat": 61,
      "long": 32,
      "sunAlt": 0,
      "pathWidth": 0,
      "centralDur": 0
    },
    {
      "tdOfGreatestEclipse": "1743-11-16T05:58:24Z",
      "deltaT": 12,
      "deltaTSigma": 3,
      "lunaNum": -3168,
      "sarosNum": 148,
      "eclType": "P",
      "qle": "t-",
      "gamma": -1.3634,
      "eclMag": 0.3424,
      "lat": -63,
      "long": -44,
      "sunAlt": 0,
      "pathWidth": 0,
      "centralDur": 0
    },
    {
      "tdOfGreatestEclipse": "1744-04-12T22:15:24Z",
      "deltaT": 12,
      "deltaTSigma": 3,
      "lunaNum": -3163,
      "sarosNum": 115,
      "eclType": "A",
      "qle": "-p",
      "gamma": -0.6819,
      "eclMag": 0.9895,
      "lat": -29,
      "long": -133,
      "sunAlt": 47,
      "pathWidth": 49,
      "centralDur": 59
    },
    {
      "tdOfGreatestEclipse": "1744-10-06T00:51:23Z",
      "deltaT": 12,
      "deltaTSigma": 3,
      "lunaNum": -3157,
      "sarosNum": 120,
      "eclType": "T",
      "qle": "-p",
      "gamma": 0.7521,
      "eclMag": 1.0263,
      "lat": 37,
      "long": -169,
      "sunAlt": 41,
      "pathWidth": 132,
      "centralDur": 124
    },
    {
      "tdOfGreatestEclipse": "1745-04-02T03:09:18Z",
      "deltaT": 12,
      "deltaTSigma": 3,
      "lunaNum": -3151,
      "sarosNum": 125,
      "eclType": "A",
      "qle": "nn",
      "gamma": 0.0536,
      "eclMag": 0.9444,
      "lat": 8,
      "long": 132,
      "sunAlt": 87,
      "pathWidth": 205,
      "centralDur": 373
    },
    {
      "tdOfGreatestEclipse": "1745-09-25T16:28:55Z",
      "deltaT": 12,
      "deltaTSigma": 3,
      "lunaNum": -3145,
      "sarosNum": 130,
      "eclType": "Tm",
      "qle": "nn",
      "gamma": 0.0269,
      "eclMag": 1.0655,
      "lat": 0,
      "long": -69,
      "sunAlt": 88,
      "pathWidth": 214,
      "centralDur": 321
    },
    {
      "tdOfGreatestEclipse": "1746-03-22T03:02:48Z",
      "deltaT": 12,
      "deltaTSigma": 3,
      "lunaNum": -3139,
      "sarosNum": 135,
      "eclType": "A",
      "qle": "p-",
      "gamma": 0.7771,
      "eclMag": 0.9277,
      "lat": 43,
      "long": 105,
      "sunAlt": 39,
      "pathWidth": 419,
      "centralDur": 411
    },
    {
      "tdOfGreatestEclipse": "1746-09-15T08:46:36Z",
      "deltaT": 12,
      "deltaTSigma": 3,
      "lunaNum": -3133,
      "sarosNum": 140,
      "eclType": "T",
      "qle": "p-",
      "gamma": -0.6948,
      "eclMag": 1.0441,
      "lat": -35,
      "long": 23,
      "sunAlt": 46,
      "pathWidth": 201,
      "centralDur": 203
    },
    {
      "tdOfGreatestEclipse": "1747-02-09T15:11:17Z",
      "deltaT": 12,
      "deltaTSigma": 3,
      "lunaNum": -3128,
      "sarosNum": 107,
      "eclType": "P",
      "qle": "-t",
      "gamma": -1.3908,
      "eclMag": 0.2861,
      "lat": -62,
      "long": 75,
      "sunAlt": 0,
      "pathWidth": 0,
      "centralDur": 0
    },
    {
      "tdOfGreatestEclipse": "1747-03-11T05:18:08Z",
      "deltaT": 12,
      "deltaTSigma": 3,
      "lunaNum": -3127,
      "sarosNum": 145,
      "eclType": "P",
      "qle": "t-",
      "gamma": 1.4504,
      "eclMag": 0.1872,
      "lat": 61,
      "long": 20,
      "sunAlt": 0,
      "pathWidth": 0,
      "centralDur": 0
    },
    {
      "tdOfGreatestEclipse": "1747-08-06T09:01:21Z",
      "deltaT": 12,
      "deltaTSigma": 3,
      "lunaNum": -3122,
      "sarosNum": 112,
      "eclType": "P",
      "qle": "-t",
      "gamma": 1.2512,
      "eclMag": 0.534,
      "lat": 62,
      "long": 171,
      "sunAlt": 0,
      "pathWidth": 0,
      "centralDur": 0
    },
    {
      "tdOfGreatestEclipse": "1747-09-04T21:07:56Z",
      "deltaT": 12,
      "deltaTSigma": 3,
      "lunaNum": -3121,
      "sarosNum": 150,
      "eclType": "P",
      "qle": "t-",
      "gamma": -1.4881,
      "eclMag": 0.1086,
      "lat": -61,
      "long": 146,
      "sunAlt": 0,
      "pathWidth": 0,
      "centralDur": 0
    },
    {
      "tdOfGreatestEclipse": "1748-01-30T03:29:13Z",
      "deltaT": 12,
      "deltaTSigma": 3,
      "lunaNum": -3116,
      "sarosNum": 117,
      "eclType": "T",
      "qle": "-p",
      "gamma": -0.6501,
      "eclMag": 1.0317,
      "lat": -54,
      "long": 155,
      "sunAlt": 49,
      "pathWidth": 140,
      "centralDur": 132
    },
    {
      "tdOfGreatestEclipse": "1748-07-25T11:27:02Z",
      "deltaT": 12,
      "deltaTSigma": 3,
      "lunaNum": -3110,
      "sarosNum": 122,
      "eclType": "A",
      "qle": "-p",
      "gamma": 0.5183,
      "eclMag": 0.9461,
      "lat": 49,
      "long": 25,
      "sunAlt": 59,
      "pathWidth": 231,
      "centralDur": 312
    },
    {
      "tdOfGreatestEclipse": "1749-01-18T19:08:56Z",
      "deltaT": 13,
      "deltaTSigma": 3,
      "lunaNum": -3104,
      "sarosNum": 127,
      "eclType": "T",
      "qle": "nn",
      "gamma": 0.0265,
      "eclMag": 1.0465,
      "lat": -19,
      "long": -105,
      "sunAlt": 89,
      "pathWidth": 155,
      "centralDur": 247
    },
    {
      "tdOfGreatestEclipse": "1749-07-14T12:19:20Z",
      "deltaT": 13,
      "deltaTSigma": 3,
      "lunaNum": -3098,
      "sarosNum": 132,
      "eclType": "A",
      "qle": "pn",
      "gamma": -0.2476,
      "eclMag": 0.9623,
      "lat": 8,
      "long": -7,
      "sunAlt": 76,
      "pathWidth": 141,
      "centralDur": 286
    },
    {
      "tdOfGreatestEclipse": "1750-01-08T09:28:42Z",
      "deltaT": 13,
      "deltaTSigma": 3,
      "lunaNum": -3092,
      "sarosNum": 137,
      "eclType": "H",
      "qle": "p-",
      "gamma": 0.7217,
      "eclMag": 1.0041,
      "lat": 23,
      "long": 29,
      "sunAlt": 44,
      "pathWidth": 20,
      "centralDur": 24
    },
    {
      "tdOfGreatestEclipse": "1750-07-03T18:38:51Z",
      "deltaT": 13,
      "deltaTSigma": 3,
      "lunaNum": -3086,
      "sarosNum": 142,
      "eclType": "P",
      "qle": "t-",
      "gamma": -0.9985,
      "eclMag": 0.9956,
      "lat": -65,
      "long": -124,
      "sunAlt": 0,
      "pathWidth": 0,
      "centralDur": 0
    },
    {
      "tdOfGreatestEclipse": "1750-11-29T00:58:14Z",
      "deltaT": 13,
      "deltaTSigma": 3,
      "lunaNum": -3081,
      "sarosNum": 109,
      "eclType": "P",
      "qle": "-t",
      "gamma": -1.5004,
      "eclMag": 0.113,
      "lat": -68,
      "long": -6,
      "sunAlt": 0,
      "pathWidth": 0,
      "centralDur": 0
    },
    {
      "tdOfGreatestEclipse": "1750-12-28T18:06:51Z",
      "deltaT": 13,
      "deltaTSigma": 3,
      "lunaNum": -3080,
      "sarosNum": 147,
      "eclType": "P",
      "qle": "t-",
      "gamma": 1.4737,
      "eclMag": 0.1506,
      "lat": 65,
      "long": -112,
      "sunAlt": 0,
      "pathWidth": 0,
      "centralDur": 0
    },
    {
      "tdOfGreatestEclipse": "1751-05-25T00:55:15Z",
      "deltaT": 13,
      "deltaTSigma": 3,
      "lunaNum": -3075,
      "sarosNum": 114,
      "eclType": "T",
      "qle": "-p",
      "gamma": 0.8359,
      "eclMag": 1.067,
      "lat": 77,
      "long": 145,
      "sunAlt": 33,
      "pathWidth": 402,
      "centralDur": 233
    },
    {
      "tdOfGreatestEclipse": "1751-11-18T00:26:00Z",
      "deltaT": 13,
      "deltaTSigma": 3,
      "lunaNum": -3069,
      "sarosNum": 119,
      "eclType": "A",
      "qle": "-p",
      "gamma": -0.8411,
      "eclMag": 0.9159,
      "lat": -75,
      "long": 143,
      "sunAlt": 32,
      "pathWidth": 597,
      "centralDur": 405
    },
    {
      "tdOfGreatestEclipse": "1752-05-13T17:56:28Z",
      "deltaT": 13,
      "deltaTSigma": 3,
      "lunaNum": -3063,
      "sarosNum": 124,
      "eclType": "T",
      "qle": "nn",
      "gamma": 0.109,
      "eclMag": 1.0637,
      "lat": 25,
      "long": -91,
      "sunAlt": 84,
      "pathWidth": 210,
      "centralDur": 342
    },
    {
      "tdOfGreatestEclipse": "1752-11-06T01:48:14Z",
      "deltaT": 13,
      "deltaTSigma": 3,
      "lunaNum": -3057,
      "sarosNum": 129,
      "eclType": "A",
      "qle": "nn",
      "gamma": -0.1239,
      "eclMag": 0.9567,
      "lat": -23,
      "long": 147,
      "sunAlt": 83,
      "pathWidth": 159,
      "centralDur": 303
    },
    {
      "tdOfGreatestEclipse": "1753-05-03T07:39:39Z",
      "deltaT": 13,
      "deltaTSigma": 3,
      "lunaNum": -3051,
      "sarosNum": 134,
      "eclType": "H",
      "qle": "p-",
      "gamma": -0.6601,
      "eclMag": 1.0079,
      "lat": -25,
      "long": 73,
      "sunAlt": 49,
      "pathWidth": 36,
      "centralDur": 48
    },
    {
      "tdOfGreatestEclipse": "1753-10-26T10:22:00Z",
      "deltaT": 13,
      "deltaTSigma": 3,
      "lunaNum": -3045,
      "sarosNum": 139,
      "eclType": "H",
      "qle": "p-",
      "gamma": 0.5911,
      "eclMag": 1.0115,
      "lat": 23,
      "long": 30,
      "sunAlt": 54,
      "pathWidth": 49,
      "centralDur": 68
    },
    {
      "tdOfGreatestEclipse": "1754-03-23T22:28:58Z",
      "deltaT": 13,
      "deltaTSigma": 3,
      "lunaNum": -3040,
      "sarosNum": 106,
      "eclType": "P",
      "qle": "-t",
      "gamma": 1.4463,
      "eclMag": 0.2032,
      "lat": 72,
      "long": 111,
      "sunAlt": 0,
      "pathWidth": 0,
      "centralDur": 0
    },
    {
      "tdOfGreatestEclipse": "1754-04-22T14:25:56Z",
      "deltaT": 13,
      "deltaTSigma": 3,
      "lunaNum": -3039,
      "sarosNum": 144,
      "eclType": "P",
      "qle": "t-",
      "gamma": -1.4631,
      "eclMag": 0.1669,
      "lat": -71,
      "long": 14,
      "sunAlt": 0,
      "pathWidth": 0,
      "centralDur": 0
    },
    {
      "tdOfGreatestEclipse": "1754-09-16T16:25:41Z",
      "deltaT": 13,
      "deltaTSigma": 3,
      "lunaNum": -3034,
      "sarosNum": 111,
      "eclType": "P",
      "qle": "-t",
      "gamma": -1.3314,
      "eclMag": 0.3822,
      "lat": -72,
      "long": -150,
      "sunAlt": 0,
      "pathWidth": 0,
      "centralDur": 0
    },
    {
      "tdOfGreatestEclipse": "1754-10-16T00:57:45Z",
      "deltaT": 13,
      "deltaTSigma": 3,
      "lunaNum": -3033,
      "sarosNum": 149,
      "eclType": "P",
      "qle": "t-",
      "gamma": 1.2535,
      "eclMag": 0.5314,
      "lat": 71,
      "long": -136,
      "sunAlt": 0,
      "pathWidth": 0,
      "centralDur": 0
    },
    {
      "tdOfGreatestEclipse": "1755-03-12T22:09:32Z",
      "deltaT": 14,
      "deltaTSigma": 3,
      "lunaNum": -3028,
      "sarosNum": 116,
      "eclType": "A",
      "qle": "-p",
      "gamma": 0.7413,
      "eclMag": 0.9319,
      "lat": 42,
      "long": -167,
      "sunAlt": 42,
      "pathWidth": 375,
      "centralDur": 427
    },
    {
      "tdOfGreatestEclipse": "1755-09-06T08:09:45Z",
      "deltaT": 14,
      "deltaTSigma": 3,
      "lunaNum": -3022,
      "sarosNum": 121,
      "eclType": "T",
      "qle": "-p",
      "gamma": -0.6478,
      "eclMag": 1.0342,
      "lat": -32,
      "long": 44,
      "sunAlt": 49,
      "pathWidth": 150,
      "centralDur": 180
    },
    {
      "tdOfGreatestEclipse": "1756-03-01T02:07:09Z",
      "deltaT": 14,
      "deltaTSigma": 3,
      "lunaNum": -3016,
      "sarosNum": 126,
      "eclType": "A",
      "qle": "nn",
      "gamma": 0.0006,
      "eclMag": 0.9787,
      "lat": -7,
      "long": 151,
      "sunAlt": 90,
      "pathWidth": 76,
      "centralDur": 144
    },
    {
      "tdOfGreatestEclipse": "1756-08-25T18:46:17Z",
      "deltaT": 14,
      "deltaTSigma": 3,
      "lunaNum": -3010,
      "sarosNum": 131,
      "eclType": "Am",
      "qle": "nn",
      "gamma": 0.1009,
      "eclMag": 0.9853,
      "lat": 16,
      "long": -100,
      "sunAlt": 84,
      "pathWidth": 52,
      "centralDur": 98
    },
    {
      "tdOfGreatestEclipse": "1757-02-18T13:14:12Z",
      "deltaT": 14,
      "deltaTSigma": 3,
      "lunaNum": -3004,
      "sarosNum": 136,
      "eclType": "T",
      "qle": "p-",
      "gamma": -0.6999,
      "eclMag": 1.0251,
      "lat": -54,
      "long": 3,
      "sunAlt": 45,
      "pathWidth": 119,
      "centralDur": 111
    },
    {
      "tdOfGreatestEclipse": "1757-08-14T22:16:45Z",
      "deltaT": 14,
      "deltaTSigma": 3,
      "lunaNum": -2998,
      "sarosNum": 141,
      "eclType": "A",
      "qle": "p-",
      "gamma": 0.8807,
      "eclMag": 0.9407,
      "lat": 72,
      "long": -113,
      "sunAlt": 28,
      "pathWidth": 467,
      "centralDur": 276
    },
    {
      "tdOfGreatestEclipse": "1758-01-09T18:13:42Z",
      "deltaT": 14,
      "deltaTSigma": 3,
      "lunaNum": -2993,
      "sarosNum": 108,
      "eclType": "P",
      "qle": "-t",
      "gamma": 1.3251,
      "eclMag": 0.3972,
      "lat": 68,
      "long": -99,
      "sunAlt": 0,
      "pathWidth": 0,
      "centralDur": 0
    },
    {
      "tdOfGreatestEclipse": "1758-02-08T04:40:51Z",
      "deltaT": 14,
      "deltaTSigma": 3,
      "lunaNum": -2992,
      "sarosNum": 146,
      "eclType": "P",
      "qle": "t-",
      "gamma": -1.3468,
      "eclMag": 0.3549,
      "lat": -70,
      "long": -108,
      "sunAlt": 0,
      "pathWidth": 0,
      "centralDur": 0
    },
    {
      "tdOfGreatestEclipse": "1758-07-05T08:57:44Z",
      "deltaT": 14,
      "deltaTSigma": 3,
      "lunaNum": -2987,
      "sarosNum": 113,
      "eclType": "P",
      "qle": "-t",
      "gamma": -1.1961,
      "eclMag": 0.6303,
      "lat": -67,
      "long": 46,
      "sunAlt": 0,
      "pathWidth": 0,
      "centralDur": 0
    },
    {
      "tdOfGreatestEclipse": "1758-12-30T07:20:12Z",
      "deltaT": 14,
      "deltaTSigma": 3,
      "lunaNum": -2981,
      "sarosNum": 118,
      "eclType": "A",
      "qle": "-p",
      "gamma": 0.6929,
      "eclMag": 0.9885,
      "lat": 21,
      "long": 72,
      "sunAlt": 46,
      "pathWidth": 56,
      "centralDur": 75
    },
    {
      "tdOfGreatestEclipse": "1759-06-24T17:20:59Z",
      "deltaT": 14,
      "deltaTSigma": 3,
      "lunaNum": -2975,
      "sarosNum": 123,
      "eclType": "T",
      "qle": "-n",
      "gamma": -0.3768,
      "eclMag": 1.0275,
      "lat": 1,
      "long": -78,
      "sunAlt": 68,
      "pathWidth": 101,
      "centralDur": 179
    },
    {
      "tdOfGreatestEclipse": "1759-12-19T13:50:05Z",
      "deltaT": 14,
      "deltaTSigma": 3,
      "lunaNum": -2969,
      "sarosNum": 128,
      "eclType": "A",
      "qle": "nn",
      "gamma": 0.0051,
      "eclMag": 0.9404,
      "lat": -23,
      "long": -28,
      "sunAlt": 90,
      "pathWidth": 221,
      "centralDur": 445
    },
    {
      "tdOfGreatestEclipse": "1760-06-13T08:09:15Z",
      "deltaT": 14,
      "deltaTSigma": 3,
      "lunaNum": -2963,
      "sarosNum": 133,
      "eclType": "T",
      "qle": "p-",
      "gamma": 0.3883,
      "eclMag": 1.0719,
      "lat": 46,
      "long": 53,
      "sunAlt": 67,
      "pathWidth": 254,
      "centralDur": 327
    },
    {
      "tdOfGreatestEclipse": "1760-12-07T13:53:44Z",
      "deltaT": 14,
      "deltaTSigma": 3,
      "lunaNum": -2957,
      "sarosNum": 138,
      "eclType": "A",
      "qle": "p-",
      "gamma": -0.6882,
      "eclMag": 0.9144,
      "lat": -65,
      "long": -49,
      "sunAlt": 46,
      "pathWidth": 451,
      "centralDur": 456
    },
    {
      "tdOfGreatestEclipse": "1761-05-04T17:43:11Z",
      "deltaT": 14,
      "deltaTSigma": 3,
      "lunaNum": -2952,
      "sarosNum": 105,
      "eclType": "P",
      "qle": "-t",
      "gamma": -1.4274,
      "eclMag": 0.2032,
      "lat": -62,
      "long": -30,
      "sunAlt": 0,
      "pathWidth": 0,
      "centralDur": 0
    },
    {
      "tdOfGreatestEclipse": "1761-06-03T01:22:37Z",
      "deltaT": 14,
      "deltaTSigma": 3,
      "lunaNum": -2951,
      "sarosNum": 143,
      "eclType": "P",
      "qle": "t-",
      "gamma": 1.1182,
      "eclMag": 0.7939,
      "lat": 64,
      "long": 10,
      "sunAlt": 0,
      "pathWidth": 0,
      "centralDur": 0
    },
    {
      "tdOfGreatestEclipse": "1761-11-26T14:00:27Z",
      "deltaT": 15,
      "deltaTSigma": 3,
      "lunaNum": -2945,
      "sarosNum": 148,
      "eclType": "P",
      "qle": "t-",
      "gamma": -1.3451,
      "eclMag": 0.3732,
      "lat": -64,
      "long": -174,
      "sunAlt": 0,
      "pathWidth": 0,
      "centralDur": 0
    },
    {
      "tdOfGreatestEclipse": "1762-04-24T05:42:10Z",
      "deltaT": 15,
      "deltaTSigma": 3,
      "lunaNum": -2940,
      "sarosNum": 115,
      "eclType": "A",
      "qle": "-p",
      "gamma": -0.7402,
      "eclMag": 0.9881,
      "lat": -30,
      "long": 116,
      "sunAlt": 42,
      "pathWidth": 61,
      "centralDur": 68
    },
    {
      "tdOfGreatestEclipse": "1762-10-17T09:00:34Z",
      "deltaT": 15,
      "deltaTSigma": 2,
      "lunaNum": -2934,
      "sarosNum": 120,
      "eclType": "T",
      "qle": "-p",
      "gamma": 0.7836,
      "eclMag": 1.0253,
      "lat": 36,
      "long": 68,
      "sunAlt": 38,
      "pathWidth": 135,
      "centralDur": 122
    },
    {
      "tdOfGreatestEclipse": "1763-04-13T10:19:31Z",
      "deltaT": 15,
      "deltaTSigma": 2,
      "lunaNum": -2928,
      "sarosNum": 125,
      "eclType": "A",
      "qle": "nn",
      "gamma": -0.001,
      "eclMag": 0.9455,
      "lat": 9,
      "long": 25,
      "sunAlt": 90,
      "pathWidth": 201,
      "centralDur": 371
    },
    {
      "tdOfGreatestEclipse": "1763-10-07T00:39:04Z",
      "deltaT": 15,
      "deltaTSigma": 2,
      "lunaNum": -2922,
      "sarosNum": 130,
      "eclType": "T",
      "qle": "nn",
      "gamma": 0.0666,
      "eclMag": 1.0627,
      "lat": -2,
      "long": 169,
      "sunAlt": 86,
      "pathWidth": 206,
      "centralDur": 309
    },
    {
      "tdOfGreatestEclipse": "1764-04-01T10:17:14Z",
      "deltaT": 15,
      "deltaTSigma": 2,
      "lunaNum": -2916,
      "sarosNum": 135,
      "eclType": "A",
      "qle": "p-",
      "gamma": 0.7289,
      "eclMag": 0.9323,
      "lat": 44,
      "long": -3,
      "sunAlt": 43,
      "pathWidth": 361,
      "centralDur": 380
    },
    {
      "tdOfGreatestEclipse": "1764-09-25T16:41:43Z",
      "deltaT": 15,
      "deltaTSigma": 2,
      "lunaNum": -2910,
      "sarosNum": 140,
      "eclType": "T",
      "qle": "p-",
      "gamma": -0.6502,
      "eclMag": 1.0394,
      "lat": -36,
      "long": -95,
      "sunAlt": 49,
      "pathWidth": 171,
      "centralDur": 181
    },
    {
      "tdOfGreatestEclipse": "1765-02-19T23:28:38Z",
      "deltaT": 15,
      "deltaTSigma": 2,
      "lunaNum": -2905,
      "sarosNum": 107,
      "eclType": "P",
      "qle": "-t",
      "gamma": -1.4028,
      "eclMag": 0.2635,
      "lat": -62,
      "long": -58,
      "sunAlt": 0,
      "pathWidth": 0,
      "centralDur": 0
    },
    {
      "tdOfGreatestEclipse": "1765-03-21T13:01:44Z",
      "deltaT": 15,
      "deltaTSigma": 2,
      "lunaNum": -2904,
      "sarosNum": 145,
      "eclType": "P",
      "qle": "t-",
      "gamma": 1.412,
      "eclMag": 0.2525,
      "lat": 61,
      "long": -104,
      "sunAlt": 0,
      "pathWidth": 0,
      "centralDur": 0
    },
    {
      "tdOfGreatestEclipse": "1765-08-16T15:54:01Z",
      "deltaT": 15,
      "deltaTSigma": 2,
      "lunaNum": -2899,
      "sarosNum": 112,
      "eclType": "P",
      "qle": "-t",
      "gamma": 1.3278,
      "eclMag": 0.3995,
      "lat": 62,
      "long": 59,
      "sunAlt": 0,
      "pathWidth": 0,
      "centralDur": 0
    },
    {
      "tdOfGreatestEclipse": "1765-09-15T04:32:34Z",
      "deltaT": 15,
      "deltaTSigma": 2,
      "lunaNum": -2898,
      "sarosNum": 150,
      "eclType": "P",
      "qle": "t-",
      "gamma": -1.4378,
      "eclMag": 0.2009,
      "lat": -61,
      "long": 26,
      "sunAlt": 0,
      "pathWidth": 0,
      "centralDur": 0
    },
    {
      "tdOfGreatestEclipse": "1766-02-09T12:09:44Z",
      "deltaT": 15,
      "deltaTSigma": 2,
      "lunaNum": -2893,
      "sarosNum": 117,
      "eclType": "T",
      "qle": "-p",
      "gamma": -0.6597,
      "eclMag": 1.0352,
      "lat": -51,
      "long": 27,
      "sunAlt": 48,
      "pathWidth": 156,
      "centralDur": 147
    },
    {
      "tdOfGreatestEclipse": "1766-08-05T17:56:57Z",
      "deltaT": 15,
      "deltaTSigma": 2,
      "lunaNum": -2887,
      "sarosNum": 122,
      "eclType": "A",
      "qle": "-p",
      "gamma": 0.6023,
      "eclMag": 0.9433,
      "lat": 50,
      "long": -67,
      "sunAlt": 53,
      "pathWidth": 260,
      "centralDur": 315
    },
    {
      "tdOfGreatestEclipse": "1767-01-30T03:56:55Z",
      "deltaT": 15,
      "deltaTSigma": 2,
      "lunaNum": -2881,
      "sarosNum": 127,
      "eclType": "T",
      "qle": "nn",
      "gamma": 0.019,
      "eclMag": 1.0471,
      "lat": -17,
      "long": 124,
      "sunAlt": 89,
      "pathWidth": 157,
      "centralDur": 246
    },
    {
      "tdOfGreatestEclipse": "1767-07-25T18:55:47Z",
      "deltaT": 15,
      "deltaTSigma": 2,
      "lunaNum": -2875,
      "sarosNum": 132,
      "eclType": "A",
      "qle": "nn",
      "gamma": -0.163,
      "eclMag": 0.9638,
      "lat": 11,
      "long": -105,
      "sunAlt": 81,
      "pathWidth": 132,
      "centralDur": 261
    },
    {
      "tdOfGreatestEclipse": "1768-01-19T18:09:29Z",
      "deltaT": 15,
      "deltaTSigma": 2,
      "lunaNum": -2869,
      "sarosNum": 137,
      "eclType": "H",
      "qle": "p-",
      "gamma": 0.7195,
      "eclMag": 1.0022,
      "lat": 24,
      "long": -103,
      "sunAlt": 44,
      "pathWidth": 11,
      "centralDur": 13
    },
    {
      "tdOfGreatestEclipse": "1768-07-14T01:40:57Z",
      "deltaT": 16,
      "deltaTSigma": 2,
      "lunaNum": -2863,
      "sarosNum": 142,
      "eclType": "H",
      "qle": "t-",
      "gamma": -0.9176,
      "eclMag": 1.0055,
      "lat": -43,
      "long": 137,
      "sunAlt": 23,
      "pathWidth": 48,
      "centralDur": 29
    },
    {
      "tdOfGreatestEclipse": "1768-12-09T09:01:38Z",
      "deltaT": 16,
      "deltaTSigma": 2,
      "lunaNum": -2858,
      "sarosNum": 109,
      "eclType": "P",
      "qle": "-t",
      "gamma": -1.5129,
      "eclMag": 0.0933,
      "lat": -67,
      "long": -138,
      "sunAlt": 0,
      "pathWidth": 0,
      "centralDur": 0
    },
    {
      "tdOfGreatestEclipse": "1769-01-08T02:26:41Z",
      "deltaT": 16,
      "deltaTSigma": 2,
      "lunaNum": -2857,
      "sarosNum": 147,
      "eclType": "P",
      "qle": "t-",
      "gamma": 1.4728,
      "eclMag": 0.1531,
      "lat": 64,
      "long": 113,
      "sunAlt": 0,
      "pathWidth": 0,
      "centralDur": 0
    },
    {
      "tdOfGreatestEclipse": "1769-06-04T08:28:34Z",
      "deltaT": 16,
      "deltaTSigma": 2,
      "lunaNum": -2852,
      "sarosNum": 114,
      "eclType": "T",
      "qle": "-t",
      "gamma": 0.9037,
      "eclMag": 1.0671,
      "lat": 87,
      "long": 26,
      "sunAlt": 25,
      "pathWidth": 521,
      "centralDur": 216
    },
    {
      "tdOfGreatestEclipse": "1769-11-28T08:18:39Z",
      "deltaT": 16,
      "deltaTSigma": 2,
      "lunaNum": -2846,
      "sarosNum": 119,
      "eclType": "A",
      "qle": "-p",
      "gamma": -0.8559,
      "eclMag": 0.9144,
      "lat": -80,
      "long": 32,
      "sunAlt": 31,
      "pathWidth": 638,
      "centralDur": 398
    },
    {
      "tdOfGreatestEclipse": "1770-05-25T01:30:11Z",
      "deltaT": 16,
      "deltaTSigma": 2,
      "lunaNum": -2840,
      "sarosNum": 124,
      "eclType": "T",
      "qle": "-n",
      "gamma": 0.176,
      "eclMag": 1.0634,
      "lat": 31,
      "long": 156,
      "sunAlt": 80,
      "pathWidth": 211,
      "centralDur": 331
    },
    {
      "tdOfGreatestEclipse": "1770-11-17T09:51:53Z",
      "deltaT": 16,
      "deltaTSigma": 2,
      "lunaNum": -2834,
      "sarosNum": 129,
      "eclType": "A",
      "qle": "nn",
      "gamma": -0.1416,
      "eclMag": 0.9571,
      "lat": -27,
      "long": 27,
      "sunAlt": 82,
      "pathWidth": 158,
      "centralDur": 296
    },
    {
      "tdOfGreatestEclipse": "1771-05-14T15:00:02Z",
      "deltaT": 16,
      "deltaTSigma": 2,
      "lunaNum": -2828,
      "sarosNum": 134,
      "eclType": "H",
      "qle": "p-",
      "gamma": -0.5981,
      "eclMag": 1.0076,
      "lat": -18,
      "long": -40,
      "sunAlt": 53,
      "pathWidth": 33,
      "centralDur": 49
    },
    {
      "tdOfGreatestEclipse": "1771-11-06T18:41:02Z",
      "deltaT": 16,
      "deltaTSigma": 2,
      "lunaNum": -2822,
      "sarosNum": 139,
      "eclType": "H",
      "qle": "p-",
      "gamma": 0.5676,
      "eclMag": 1.012,
      "lat": 18,
      "long": -97,
      "sunAlt": 55,
      "pathWidth": 50,
      "centralDur": 73
    },
    {
      "tdOfGreatestEclipse": "1772-04-03T05:43:52Z",
      "deltaT": 16,
      "deltaTSigma": 2,
      "lunaNum": -2817,
      "sarosNum": 106,
      "eclType": "P",
      "qle": "-t",
      "gamma": 1.4935,
      "eclMag": 0.1229,
      "lat": 72,
      "long": -12,
      "sunAlt": 0,
      "pathWidth": 0,
      "centralDur": 0
    },
    {
      "tdOfGreatestEclipse": "1772-05-02T21:26:41Z",
      "deltaT": 16,
      "deltaTSigma": 2,
      "lunaNum": -2816,
      "sarosNum": 144,
      "eclType": "P",
      "qle": "t-",
      "gamma": -1.4044,
      "eclMag": 0.2683,
      "lat": -70,
      "long": -104,
      "sunAlt": 0,
      "pathWidth": 0,
      "centralDur": 0
    },
    {
      "tdOfGreatestEclipse": "1772-09-27T00:28:19Z",
      "deltaT": 16,
      "deltaTSigma": 2,
      "lunaNum": -2811,
      "sarosNum": 111,
      "eclType": "P",
      "qle": "-t",
      "gamma": -1.3751,
      "eclMag": 0.2988,
      "lat": -72,
      "long": 75,
      "sunAlt": 0,
      "pathWidth": 0,
      "centralDur": 0
    },
    {
      "tdOfGreatestEclipse": "1772-10-26T09:21:17Z",
      "deltaT": 16,
      "deltaTSigma": 2,
      "lunaNum": -2810,
      "sarosNum": 149,
      "eclType": "P",
      "qle": "t-",
      "gamma": 1.2255,
      "eclMag": 0.5846,
      "lat": 71,
      "long": 85,
      "sunAlt": 0,
      "pathWidth": 0,
      "centralDur": 0
    },
    {
      "tdOfGreatestEclipse": "1773-03-23T05:36:57Z",
      "deltaT": 16,
      "deltaTSigma": 2,
      "lunaNum": -2805,
      "sarosNum": 116,
      "eclType": "A",
      "qle": "-p",
      "gamma": 0.7785,
      "eclMag": 0.9357,
      "lat": 49,
      "long": 76,
      "sunAlt": 39,
      "pathWidth": 378,
      "centralDur": 373
    },
    {
      "tdOfGreatestEclipse": "1773-09-16T15:52:23Z",
      "deltaT": 16,
      "deltaTSigma": 2,
      "lunaNum": -2799,
      "sarosNum": 121,
      "eclType": "T",
      "qle": "-p",
      "gamma": -0.702,
      "eclMag": 1.0275,
      "lat": -40,
      "long": -76,
      "sunAlt": 45,
      "pathWidth": 130,
      "centralDur": 138
    },
    {
      "tdOfGreatestEclipse": "1774-03-12T10:05:14Z",
      "deltaT": 16,
      "deltaTSigma": 2,
      "lunaNum": -2793,
      "sarosNum": 126,
      "eclType": "A",
      "qle": "nn",
      "gamma": 0.0284,
      "eclMag": 0.9845,
      "lat": -2,
      "long": 31,
      "sunAlt": 88,
      "pathWidth": 55,
      "centralDur": 103
    },
    {
      "tdOfGreatestEclipse": "1774-09-06T01:57:40Z",
      "deltaT": 16,
      "deltaTSigma": 2,
      "lunaNum": -2787,
      "sarosNum": 131,
      "eclType": "A",
      "qle": "nn",
      "gamma": 0.0385,
      "eclMag": 0.9797,
      "lat": 9,
      "long": 151,
      "sunAlt": 88,
      "pathWidth": 72,
      "centralDur": 140
    },
    {
      "tdOfGreatestEclipse": "1775-03-01T21:39:20Z",
      "deltaT": 16,
      "deltaTSigma": 2,
      "lunaNum": -2781,
      "sarosNum": 136,
      "eclType": "T",
      "qle": "p-",
      "gamma": -0.6783,
      "eclMag": 1.0304,
      "lat": -48,
      "long": -125,
      "sunAlt": 47,
      "pathWidth": 139,
      "centralDur": 140
    },
    {
      "tdOfGreatestEclipse": "1775-08-26T04:59:40Z",
      "deltaT": 16,
      "deltaTSigma": 2,
      "lunaNum": -2775,
      "sarosNum": 141,
      "eclType": "A",
      "qle": "p-",
      "gamma": 0.8088,
      "eclMag": 0.9391,
      "lat": 61,
      "long": 132,
      "sunAlt": 36,
      "pathWidth": 383,
      "centralDur": 316
    },
    {
      "tdOfGreatestEclipse": "1776-01-21T03:02:27Z",
      "deltaT": 16,
      "deltaTSigma": 2,
      "lunaNum": -2770,
      "sarosNum": 108,
      "eclType": "P",
      "qle": "-t",
      "gamma": 1.3318,
      "eclMag": 0.3848,
      "lat": 69,
      "long": 118,
      "sunAlt": 0,
      "pathWidth": 0,
      "centralDur": 0
    },
    {
      "tdOfGreatestEclipse": "1776-02-19T13:20:10Z",
      "deltaT": 16,
      "deltaTSigma": 2,
      "lunaNum": -2769,
      "sarosNum": 146,
      "eclType": "P",
      "qle": "t-",
      "gamma": -1.3334,
      "eclMag": 0.38,
      "lat": -71,
      "long": 109,
      "sunAlt": 0,
      "pathWidth": 0,
      "centralDur": 0
    },
    {
      "tdOfGreatestEclipse": "1776-07-15T15:39:29Z",
      "deltaT": 16,
      "deltaTSigma": 2,
      "lunaNum": -2764,
      "sarosNum": 113,
      "eclType": "P",
      "qle": "-t",
      "gamma": -1.2739,
      "eclMag": 0.4935,
      "lat": -68,
      "long": -65,
      "sunAlt": 0,
      "pathWidth": 0,
      "centralDur": 0
    },
    {
      "tdOfGreatestEclipse": "1776-08-14T05:22:56Z",
      "deltaT": 16,
      "deltaTSigma": 2,
      "lunaNum": -2763,
      "sarosNum": 151,
      "eclType": "Pb",
      "qle": "t-",
      "gamma": 1.5357,
      "eclMag": 0.0435,
      "lat": 71,
      "long": -124,
      "sunAlt": 0,
      "pathWidth": 0,
      "centralDur": 0
    },
    {
      "tdOfGreatestEclipse": "1777-01-09T15:55:35Z",
      "deltaT": 16,
      "deltaTSigma": 2,
      "lunaNum": -2758,
      "sarosNum": 118,
      "eclType": "A",
      "qle": "-p",
      "gamma": 0.6987,
      "eclMag": 0.9859,
      "lat": 22,
      "long": -59,
      "sunAlt": 46,
      "pathWidth": 70,
      "centralDur": 92
    },
    {
      "tdOfGreatestEclipse": "1777-07-05T00:29:29Z",
      "deltaT": 16,
      "deltaTSigma": 2,
      "lunaNum": -2752,
      "sarosNum": 123,
      "eclType": "T",
      "qle": "-p",
      "gamma": -0.4531,
      "eclMag": 1.0305,
      "lat": -4,
      "long": 174,
      "sunAlt": 63,
      "pathWidth": 115,
      "centralDur": 197
    },
    {
      "tdOfGreatestEclipse": "1777-12-29T22:03:28Z",
      "deltaT": 17,
      "deltaTSigma": 2,
      "lunaNum": -2746,
      "sarosNum": 128,
      "eclType": "A",
      "qle": "nn",
      "gamma": 0.0109,
      "eclMag": 0.938,
      "lat": -23,
      "long": -150,
      "sunAlt": 90,
      "pathWidth": 231,
      "centralDur": 473
    },
    {
      "tdOfGreatestEclipse": "1778-06-24T15:34:55Z",
      "deltaT": 17,
      "deltaTSigma": 2,
      "lunaNum": -2740,
      "sarosNum": 133,
      "eclType": "T",
      "qle": "n-",
      "gamma": 0.3127,
      "eclMag": 1.0746,
      "lat": 42,
      "long": -55,
      "sunAlt": 72,
      "pathWidth": 255,
      "centralDur": 352
    },
    {
      "tdOfGreatestEclipse": "1778-12-18T21:53:53Z",
      "deltaT": 17,
      "deltaTSigma": 2,
      "lunaNum": -2734,
      "sarosNum": 138,
      "eclType": "A",
      "qle": "p-",
      "gamma": -0.6788,
      "eclMag": 0.9137,
      "lat": -66,
      "long": -161,
      "sunAlt": 47,
      "pathWidth": 450,
      "centralDur": 464
    },
    {
      "tdOfGreatestEclipse": "1779-05-16T01:17:39Z",
      "deltaT": 17,
      "deltaTSigma": 2,
      "lunaNum": -2729,
      "sarosNum": 105,
      "eclType": "Pe",
      "qle": "-t",
      "gamma": -1.4928,
      "eclMag": 0.0796,
      "lat": -63,
      "long": -153,
      "sunAlt": 0,
      "pathWidth": 0,
      "centralDur": 0
    },
    {
      "tdOfGreatestEclipse": "1779-06-14T08:51:28Z",
      "deltaT": 17,
      "deltaTSigma": 2,
      "lunaNum": -2728,
      "sarosNum": 143,
      "eclType": "P",
      "qle": "t-",
      "gamma": 1.0489,
      "eclMag": 0.9275,
      "lat": 65,
      "long": -112,
      "sunAlt": 0,
      "pathWidth": 0,
      "centralDur": 0
    },
    {
      "tdOfGreatestEclipse": "1779-12-07T22:08:56Z",
      "deltaT": 17,
      "deltaTSigma": 2,
      "lunaNum": -2722,
      "sarosNum": 148,
      "eclType": "P",
      "qle": "t-",
      "gamma": -1.3315,
      "eclMag": 0.3962,
      "lat": -65,
      "long": 54,
      "sunAlt": 0,
      "pathWidth": 0,
      "centralDur": 0
    },
    {
      "tdOfGreatestEclipse": "1780-05-04T13:00:41Z",
      "deltaT": 17,
      "deltaTSigma": 2,
      "lunaNum": -2717,
      "sarosNum": 115,
      "eclType": "A",
      "qle": "-p",
      "gamma": -0.8043,
      "eclMag": 0.9861,
      "lat": -33,
      "long": 6,
      "sunAlt": 36,
      "pathWidth": 81,
      "centralDur": 81
    },
    {
      "tdOfGreatestEclipse": "1780-10-27T17:18:27Z",
      "deltaT": 17,
      "deltaTSigma": 2,
      "lunaNum": -2711,
      "sarosNum": 120,
      "eclType": "T",
      "qle": "-p",
      "gamma": 0.8083,
      "eclMag": 1.0244,
      "lat": 36,
      "long": -59,
      "sunAlt": 36,
      "pathWidth": 138,
      "centralDur": 120
    },
    {
      "tdOfGreatestEclipse": "1781-04-23T17:21:25Z",
      "deltaT": 17,
      "deltaTSigma": 2,
      "lunaNum": -2705,
      "sarosNum": 125,
      "eclType": "A",
      "qle": "nn",
      "gamma": -0.062,
      "eclMag": 0.9467,
      "lat": 10,
      "long": -79,
      "sunAlt": 87,
      "pathWidth": 197,
      "centralDur": 373
    },
    {
      "tdOfGreatestEclipse": "1781-10-17T08:55:58Z",
      "deltaT": 17,
      "deltaTSigma": 2,
      "lunaNum": -2699,
      "sarosNum": 130,
      "eclType": "T",
      "qle": "-n",
      "gamma": 0.1007,
      "eclMag": 1.0596,
      "lat": -4,
      "long": 45,
      "sunAlt": 84,
      "pathWidth": 197,
      "centralDur": 299
    },
    {
      "tdOfGreatestEclipse": "1782-04-12T17:24:47Z",
      "deltaT": 17,
      "deltaTSigma": 2,
      "lunaNum": -2693,
      "sarosNum": 135,
      "eclType": "A",
      "qle": "p-",
      "gamma": 0.6745,
      "eclMag": 0.937,
      "lat": 45,
      "long": -107,
      "sunAlt": 47,
      "pathWidth": 311,
      "centralDur": 351
    },
    {
      "tdOfGreatestEclipse": "1782-10-07T00:43:19Z",
      "deltaT": 17,
      "deltaTSigma": 2,
      "lunaNum": -2687,
      "sarosNum": 140,
      "eclType": "T",
      "qle": "p-",
      "gamma": -0.6113,
      "eclMag": 1.0344,
      "lat": -38,
      "long": 145,
      "sunAlt": 52,
      "pathWidth": 144,
      "centralDur": 157
    },
    {
      "tdOfGreatestEclipse": "1783-03-03T07:40:30Z",
      "deltaT": 17,
      "deltaTSigma": 2,
      "lunaNum": -2682,
      "sarosNum": 107,
      "eclType": "P",
      "qle": "-t",
      "gamma": -1.42,
      "eclMag": 0.2313,
      "lat": -61,
      "long": 171,
      "sunAlt": 0,
      "pathWidth": 0,
      "centralDur": 0
    },
    {
      "tdOfGreatestEclipse": "1783-04-01T20:38:38Z",
      "deltaT": 17,
      "deltaTSigma": 2,
      "lunaNum": -2681,
      "sarosNum": 145,
      "eclType": "P",
      "qle": "t-",
      "gamma": 1.3671,
      "eclMag": 0.33,
      "lat": 61,
      "long": 133,
      "sunAlt": 0,
      "pathWidth": 0,
      "centralDur": 0
    },
    {
      "tdOfGreatestEclipse": "1783-08-27T22:52:05Z",
      "deltaT": 17,
      "deltaTSigma": 2,
      "lunaNum": -2676,
      "sarosNum": 112,
      "eclType": "P",
      "qle": "-t",
      "gamma": 1.3991,
      "eclMag": 0.2758,
      "lat": 61,
      "long": -54,
      "sunAlt": 0,
      "pathWidth": 0,
      "centralDur": 0
    },
    {
      "tdOfGreatestEclipse": "1783-09-26T12:04:17Z",
      "deltaT": 17,
      "deltaTSigma": 2,
      "lunaNum": -2675,
      "sarosNum": 150,
      "eclType": "P",
      "qle": "t-",
      "gamma": -1.3935,
      "eclMag": 0.2814,
      "lat": -61,
      "long": -95,
      "sunAlt": 0,
      "pathWidth": 0,
      "centralDur": 0
    },
    {
      "tdOfGreatestEclipse": "1784-02-20T20:45:38Z",
      "deltaT": 17,
      "deltaTSigma": 2,
      "lunaNum": -2670,
      "sarosNum": 117,
      "eclType": "T",
      "qle": "-p",
      "gamma": -0.6739,
      "eclMag": 1.0389,
      "lat": -47,
      "long": -102,
      "sunAlt": 47,
      "pathWidth": 174,
      "centralDur": 164
    },
    {
      "tdOfGreatestEclipse": "1784-08-16T00:31:53Z",
      "deltaT": 17,
      "deltaTSigma": 2,
      "lunaNum": -2664,
      "sarosNum": 122,
      "eclType": "A",
      "qle": "-p",
      "gamma": 0.6819,
      "eclMag": 0.9402,
      "lat": 51,
      "long": -160,
      "sunAlt": 47,
      "pathWidth": 299,
      "centralDur": 323
    },
    {
      "tdOfGreatestEclipse": "1785-02-09T12:40:41Z",
      "deltaT": 17,
      "deltaTSigma": 2,
      "lunaNum": -2658,
      "sarosNum": 127,
      "eclType": "T",
      "qle": "nn",
      "gamma": 0.008,
      "eclMag": 1.048,
      "lat": -14,
      "long": -7,
      "sunAlt": 90,
      "pathWidth": 159,
      "centralDur": 247
    },
    {
      "tdOfGreatestEclipse": "1785-08-05T01:37:22Z",
      "deltaT": 17,
      "deltaTSigma": 2,
      "lunaNum": -2652,
      "sarosNum": 132,
      "eclType": "A",
      "qle": "nn",
      "gamma": -0.0817,
      "eclMag": 0.965,
      "lat": 13,
      "long": 155,
      "sunAlt": 85,
      "pathWidth": 127,
      "centralDur": 241
    },
    {
      "tdOfGreatestEclipse": "1786-01-30T02:45:26Z",
      "deltaT": 17,
      "deltaTSigma": 2,
      "lunaNum": -2646,
      "sarosNum": 137,
      "eclType": "H",
      "qle": "p-",
      "gamma": 0.7141,
      "eclMag": 1.0009,
      "lat": 25,
      "long": 125,
      "sunAlt": 44,
      "pathWidth": 5,
      "centralDur": 5
    },
    {
      "tdOfGreatestEclipse": "1786-07-25T08:46:33Z",
      "deltaT": 17,
      "deltaTSigma": 2,
      "lunaNum": -2640,
      "sarosNum": 142,
      "eclType": "T",
      "qle": "t-",
      "gamma": -0.8384,
      "eclMag": 1.0106,
      "lat": -35,
      "long": 31,
      "sunAlt": 33,
      "pathWidth": 66,
      "centralDur": 59
    },
    {
      "tdOfGreatestEclipse": "1786-12-20T17:07:24Z",
      "deltaT": 16,
      "deltaTSigma": 2,
      "lunaNum": -2635,
      "sarosNum": 109,
      "eclType": "P",
      "qle": "-t",
      "gamma": -1.5232,
      "eclMag": 0.0773,
      "lat": -66,
      "long": 90,
      "sunAlt": 0,
      "pathWidth": 0,
      "centralDur": 0
    },
    {
      "tdOfGreatestEclipse": "1787-01-19T10:43:13Z",
      "deltaT": 16,
      "deltaTSigma": 2,
      "lunaNum": -2634,
      "sarosNum": 147,
      "eclType": "P",
      "qle": "t-",
      "gamma": 1.4697,
      "eclMag": 0.1591,
      "lat": 63,
      "long": -20,
      "sunAlt": 0,
      "pathWidth": 0,
      "centralDur": 0
    },
    {
      "tdOfGreatestEclipse": "1787-06-15T15:59:25Z",
      "deltaT": 16,
      "deltaTSigma": 2,
      "lunaNum": -2629,
      "sarosNum": 114,
      "eclType": "T",
      "qle": "-t",
      "gamma": 0.9738,
      "eclMag": 1.0648,
      "lat": 79,
      "long": 105,
      "sunAlt": 12,
      "pathWidth": 997,
      "centralDur": 189
    },
    {
      "tdOfGreatestEclipse": "1787-12-09T16:15:38Z",
      "deltaT": 16,
      "deltaTSigma": 1,
      "lunaNum": -2623,
      "sarosNum": 119,
      "eclType": "A",
      "qle": "-p",
      "gamma": -0.8674,
      "eclMag": 0.9136,
      "lat": -83,
      "long": -63,
      "sunAlt": 29,
      "pathWidth": 672,
      "centralDur": 392
    },
    {
      "tdOfGreatestEclipse": "1788-06-04T08:59:30Z",
      "deltaT": 16,
      "deltaTSigma": 1,
      "lunaNum": -2617,
      "sarosNum": 124,
      "eclType": "T",
      "qle": "-n",
      "gamma": 0.2465,
      "eclMag": 1.0623,
      "lat": 37,
      "long": 44,
      "sunAlt": 76,
      "pathWidth": 211,
      "centralDur": 315
    },
    {
      "tdOfGreatestEclipse": "1788-11-27T18:02:53Z",
      "deltaT": 16,
      "deltaTSigma": 1,
      "lunaNum": -2611,
      "sarosNum": 129,
      "eclType": "A",
      "qle": "nn",
      "gamma": -0.1542,
      "eclMag": 0.9579,
      "lat": -30,
      "long": -94,
      "sunAlt": 81,
      "pathWidth": 155,
      "centralDur": 286
    },
    {
      "tdOfGreatestEclipse": "1789-05-24T22:11:58Z",
      "deltaT": 16,
      "deltaTSigma": 1,
      "lunaNum": -2605,
      "sarosNum": 134,
      "eclType": "H",
      "qle": "p-",
      "gamma": -0.5297,
      "eclMag": 1.0068,
      "lat": -11,
      "long": -151,
      "sunAlt": 58,
      "pathWidth": 28,
      "centralDur": 46
    },
    {
      "tdOfGreatestEclipse": "1789-11-17T03:08:34Z",
      "deltaT": 16,
      "deltaTSigma": 1,
      "lunaNum": -2599,
      "sarosNum": 139,
      "eclType": "H",
      "qle": "p-",
      "gamma": 0.5505,
      "eclMag": 1.0126,
      "lat": 14,
      "long": 134,
      "sunAlt": 57,
      "pathWidth": 52,
      "centralDur": 79
    },
    {
      "tdOfGreatestEclipse": "1790-04-14T12:48:14Z",
      "deltaT": 16,
      "deltaTSigma": 1,
      "lunaNum": -2594,
      "sarosNum": 106,
      "eclType": "Pe",
      "qle": "-t",
      "gamma": 1.5487,
      "eclMag": 0.0287,
      "lat": 71,
      "long": -132,
      "sunAlt": 0,
      "pathWidth": 0,
      "centralDur": 0
    },
    {
      "tdOfGreatestEclipse": "1790-05-14T04:17:21Z",
      "deltaT": 16,
      "deltaTSigma": 1,
      "lunaNum": -2593,
      "sarosNum": 144,
      "eclType": "P",
      "qle": "t-",
      "gamma": -1.3374,
      "eclMag": 0.384,
      "lat": -69,
      "long": 141,
      "sunAlt": 0,
      "pathWidth": 0,
      "centralDur": 0
    },
    {
      "tdOfGreatestEclipse": "1790-10-08T08:38:51Z",
      "deltaT": 16,
      "deltaTSigma": 1,
      "lunaNum": -2588,
      "sarosNum": 111,
      "eclType": "P",
      "qle": "-t",
      "gamma": -1.4122,
      "eclMag": 0.2287,
      "lat": -72,
      "long": -61,
      "sunAlt": 0,
      "pathWidth": 0,
      "centralDur": 0
    },
    {
      "tdOfGreatestEclipse": "1790-11-06T17:53:11Z",
      "deltaT": 16,
      "deltaTSigma": 1,
      "lunaNum": -2587,
      "sarosNum": 149,
      "eclType": "P",
      "qle": "t-",
      "gamma": 1.2044,
      "eclMag": 0.6245,
      "lat": 70,
      "long": -56,
      "sunAlt": 0,
      "pathWidth": 0,
      "centralDur": 0
    },
    {
      "tdOfGreatestEclipse": "1791-04-03T12:55:13Z",
      "deltaT": 16,
      "deltaTSigma": 1,
      "lunaNum": -2582,
      "sarosNum": 116,
      "eclType": "A",
      "qle": "-p",
      "gamma": 0.8236,
      "eclMag": 0.9394,
      "lat": 57,
      "long": -40,
      "sunAlt": 34,
      "pathWidth": 394,
      "centralDur": 321
    },
    {
      "tdOfGreatestEclipse": "1791-09-27T23:42:29Z",
      "deltaT": 16,
      "deltaTSigma": 1,
      "lunaNum": -2576,
      "sarosNum": 121,
      "eclType": "T",
      "qle": "-p",
      "gamma": -0.7492,
      "eclMag": 1.0206,
      "lat": -48,
      "long": 162,
      "sunAlt": 41,
      "pathWidth": 106,
      "centralDur": 98
    },
    {
      "tdOfGreatestEclipse": "1792-03-22T17:57:34Z",
      "deltaT": 16,
      "deltaTSigma": 1,
      "lunaNum": -2570,
      "sarosNum": 126,
      "eclType": "A",
      "qle": "nn",
      "gamma": 0.0618,
      "eclMag": 0.9906,
      "lat": 5,
      "long": -89,
      "sunAlt": 86,
      "pathWidth": 33,
      "centralDur": 62
    },
    {
      "tdOfGreatestEclipse": "1792-09-16T09:13:51Z",
      "deltaT": 16,
      "deltaTSigma": 1,
      "lunaNum": -2564,
      "sarosNum": 131,
      "eclType": "A",
      "qle": "nn",
      "gamma": -0.0191,
      "eclMag": 0.9739,
      "lat": 1,
      "long": 40,
      "sunAlt": 89,
      "pathWidth": 93,
      "centralDur": 182
    },
    {
      "tdOfGreatestEclipse": "1793-03-12T06:00:07Z",
      "deltaT": 16,
      "deltaTSigma": 1,
      "lunaNum": -2558,
      "sarosNum": 136,
      "eclType": "T",
      "qle": "p-",
      "gamma": -0.6524,
      "eclMag": 1.0359,
      "lat": -42,
      "long": 108,
      "sunAlt": 49,
      "pathWidth": 158,
      "centralDur": 171
    },
    {
      "tdOfGreatestEclipse": "1793-09-05T11:47:24Z",
      "deltaT": 15,
      "deltaTSigma": 1,
      "lunaNum": -2552,
      "sarosNum": 141,
      "eclType": "A",
      "qle": "p-",
      "gamma": 0.7408,
      "eclMag": 0.937,
      "lat": 52,
      "long": 23,
      "sunAlt": 42,
      "pathWidth": 346,
      "centralDur": 362
    },
    {
      "tdOfGreatestEclipse": "1794-01-31T11:48:45Z",
      "deltaT": 15,
      "deltaTSigma": 1,
      "lunaNum": -2547,
      "sarosNum": 108,
      "eclType": "P",
      "qle": "-t",
      "gamma": 1.3407,
      "eclMag": 0.3681,
      "lat": 70,
      "long": -26,
      "sunAlt": 0,
      "pathWidth": 0,
      "centralDur": 0
    },
    {
      "tdOfGreatestEclipse": "1794-03-01T21:53:59Z",
      "deltaT": 15,
      "deltaTSigma": 1,
      "lunaNum": -2546,
      "sarosNum": 146,
      "eclType": "P",
      "qle": "t-",
      "gamma": -1.3155,
      "eclMag": 0.4136,
      "lat": -72,
      "long": -33,
      "sunAlt": 0,
      "pathWidth": 0,
      "centralDur": 0
    },
    {
      "tdOfGreatestEclipse": "1794-07-26T22:24:27Z",
      "deltaT": 15,
      "deltaTSigma": 1,
      "lunaNum": -2541,
      "sarosNum": 113,
      "eclType": "P",
      "qle": "-t",
      "gamma": -1.3496,
      "eclMag": 0.3599,
      "lat": -69,
      "long": -178,
      "sunAlt": 0,
      "pathWidth": 0,
      "centralDur": 0
    },
    {
      "tdOfGreatestEclipse": "1794-08-25T12:08:56Z",
      "deltaT": 15,
      "deltaTSigma": 1,
      "lunaNum": -2540,
      "sarosNum": 151,
      "eclType": "P",
      "qle": "t-",
      "gamma": 1.4616,
      "eclMag": 0.1709,
      "lat": 71,
      "long": 122,
      "sunAlt": 0,
      "pathWidth": 0,
      "centralDur": 0
    },
    {
      "tdOfGreatestEclipse": "1795-01-21T00:29:13Z",
      "deltaT": 15,
      "deltaTSigma": 1,
      "lunaNum": -2535,
      "sarosNum": 118,
      "eclType": "A",
      "qle": "-p",
      "gamma": 0.7055,
      "eclMag": 0.9837,
      "lat": 25,
      "long": 170,
      "sunAlt": 45,
      "pathWidth": 81,
      "centralDur": 104
    },
    {
      "tdOfGreatestEclipse": "1795-07-16T07:41:36Z",
      "deltaT": 15,
      "deltaTSigma": 1,
      "lunaNum": -2529,
      "sarosNum": 123,
      "eclType": "T",
      "qle": "-p",
      "gamma": -0.5274,
      "eclMag": 1.0327,
      "lat": -10,
      "long": 64,
      "sunAlt": 58,
      "pathWidth": 130,
      "centralDur": 206
    },
    {
      "tdOfGreatestEclipse": "1796-01-10T06:14:52Z",
      "deltaT": 15,
      "deltaTSigma": 1,
      "lunaNum": -2523,
      "sarosNum": 128,
      "eclType": "A",
      "qle": "nn",
      "gamma": 0.0179,
      "eclMag": 0.9362,
      "lat": -21,
      "long": 88,
      "sunAlt": 89,
      "pathWidth": 238,
      "centralDur": 495
    },
    {
      "tdOfGreatestEclipse": "1796-07-04T23:02:54Z",
      "deltaT": 15,
      "deltaTSigma": 1,
      "lunaNum": -2517,
      "sarosNum": 133,
      "eclType": "T",
      "qle": "n-",
      "gamma": 0.2385,
      "eclMag": 1.0764,
      "lat": 37,
      "long": -165,
      "sunAlt": 76,
      "pathWidth": 255,
      "centralDur": 375
    },
    {
      "tdOfGreatestEclipse": "1796-12-29T05:54:58Z",
      "deltaT": 15,
      "deltaTSigma": 1,
      "lunaNum": -2511,
      "sarosNum": 138,
      "eclType": "A",
      "qle": "p-",
      "gamma": -0.6703,
      "eclMag": 0.9136,
      "lat": -66,
      "long": 89,
      "sunAlt": 48,
      "pathWidth": 446,
      "centralDur": 471
    },
    {
      "tdOfGreatestEclipse": "1797-06-24T16:18:13Z",
      "deltaT": 14,
      "deltaTSigma": 1,
      "lunaNum": -2505,
      "sarosNum": 143,
      "eclType": "T",
      "qle": "t-",
      "gamma": 0.978,
      "eclMag": 1.057,
      "lat": 77,
      "long": 134,
      "sunAlt": 11,
      "pathWidth": 975,
      "centralDur": 167
    },
    {
      "tdOfGreatestEclipse": "1797-12-18T06:21:51Z",
      "deltaT": 14,
      "deltaTSigma": 1,
      "lunaNum": -2499,
      "sarosNum": 148,
      "eclType": "P",
      "qle": "t-",
      "gamma": -1.3208,
      "eclMag": 0.4142,
      "lat": -66,
      "long": -79,
      "sunAlt": 0,
      "pathWidth": 0,
      "centralDur": 0
    },
    {
      "tdOfGreatestEclipse": "1798-05-15T20:10:32Z",
      "deltaT": 14,
      "deltaTSigma": 1,
      "lunaNum": -2494,
      "sarosNum": 115,
      "eclType": "A",
      "qle": "-t",
      "gamma": -0.8744,
      "eclMag": 0.9832,
      "lat": -39,
      "long": -102,
      "sunAlt": 29,
      "pathWidth": 121,
      "centralDur": 96
    },
    {
      "tdOfGreatestEclipse": "1798-11-08T01:44:38Z",
      "deltaT": 14,
      "deltaTSigma": 1,
      "lunaNum": -2488,
      "sarosNum": 120,
      "eclType": "T",
      "qle": "-p",
      "gamma": 0.827,
      "eclMag": 1.0237,
      "lat": 35,
      "long": 173,
      "sunAlt": 34,
      "pathWidth": 141,
      "centralDur": 119
    },
    {
      "tdOfGreatestEclipse": "1799-05-05T00:13:07Z",
      "deltaT": 14,
      "deltaTSigma": 1,
      "lunaNum": -2482,
      "sarosNum": 125,
      "eclType": "A",
      "qle": "nn",
      "gamma": -0.131,
      "eclMag": 0.9476,
      "lat": 9,
      "long": 179,
      "sunAlt": 83,
      "pathWidth": 194,
      "centralDur": 380
    },
    {
      "tdOfGreatestEclipse": "1799-10-28T17:21:46Z",
      "deltaT": 13,
      "deltaTSigma": 1,
      "lunaNum": -2476,
      "sarosNum": 130,
      "eclType": "T",
      "qle": "-n",
      "gamma": 0.1274,
      "eclMag": 1.0566,
      "lat": -7,
      "long": -81,
      "sunAlt": 83,
      "pathWidth": 188,
      "centralDur": 290
    },
    {
      "tdOfGreatestEclipse": "1800-04-24T00:23:59Z",
      "deltaT": 13,
      "deltaTSigma": 1,
      "lunaNum": -2470,
      "sarosNum": 135,
      "eclType": "A",
      "qle": "p-",
      "gamma": 0.6125,
      "eclMag": 0.9417,
      "lat": 46,
      "long": 151,
      "sunAlt": 52,
      "pathWidth": 269,
      "centralDur": 327
    },
    {
      "tdOfGreatestEclipse": "1800-10-18T08:51:52Z",
      "deltaT": 13,
      "deltaTSigma": 1,
      "lunaNum": -2464,
      "sarosNum": 140,
      "eclType": "T",
      "qle": "p-",
      "gamma": -0.5788,
      "eclMag": 1.0293,
      "lat": -40,
      "long": 23,
      "sunAlt": 54,
      "pathWidth": 120,
      "centralDur": 134
    }
  ]
}