{
  "data": [
    {
      "tdOfGreatestEclipse": "2701-05-29T23:16:44Z",
      "deltaT": 2182,
      "deltaTSigma": 516,
      "lunaNum": 8675,
      "sarosNum": 168,
      "eclType": "A",
      "qle": "p-",
      "gamma": -0.8725,
      "eclMag": 0.972,
      "lat": -39,
      "long": -157,
      "sunAlt": 29,
      "pathWidth": 206,
      "centralDur": 174
    },
    {
      "tdOfGreatestEclipse": "2701-11-22T06:34:40Z",
      "deltaT": 2185,
      "deltaTSigma": 516,
      "lunaNum": 8681,
      "sarosNum": 173,
      "eclType": "T",
      "qle": "p-",
      "gamma": 0.8025,
      "eclMag": 1.0331,
      "lat": 33,
      "long": 93,
      "sunAlt": 36,
      "pathWidth": 187,
      "centralDur": 176
    },
    {
      "tdOfGreatestEclipse": "2702-04-19T09:30:31Z",
      "deltaT": 2187,
      "deltaTSigma": 517,
      "lunaNum": 8686,
      "sarosNum": 140,
      "eclType": "P",
      "qle": "-t",
      "gamma": 1.2736,
      "eclMag": 0.4941,
      "lat": 71,
      "long": -79,
      "sunAlt": 0,
      "pathWidth": 0,
      "centralDur": 0
    },
    {
      "tdOfGreatestEclipse": "2702-10-13T13:25:50Z",
      "deltaT": 2190,
      "deltaTSigma": 517,
      "lunaNum": 8692,
      "sarosNum": 145,
      "eclType": "P",
      "qle": "-t",
      "gamma": -1.1505,
      "eclMag": 0.726,
      "lat": -72,
      "long": -130,
      "sunAlt": 0,
      "pathWidth": 0,
      "centralDur": 0
    },
    {
      "tdOfGreatestEclipse": "2702-11-11T22:34:28Z",
      "deltaT": 2191,
      "deltaTSigma": 517,
      "lunaNum": 8693,
      "sarosNum": 183,
      "eclType": "P",
      "qle": "t-",
      "gamma": 1.46,
      "eclMag": 0.1391,
      "lat": 70,
      "long": -122,
      "sunAlt": 0,
      "pathWidth": 0,
      "centralDur": 0
    },
    {
      "tdOfGreatestEclipse": "2703-04-08T11:13:57Z",
      "deltaT": 2193,
      "deltaTSigma": 518,
      "lunaNum": 8698,
      "sarosNum": 150,
      "eclType": "A",
      "qle": "-p",
      "gamma": 0.5257,
      "eclMag": 0.9605,
      "lat": 37,
      "long": 10,
      "sunAlt": 58,
      "pathWidth": 167,
      "centralDur": 241
    },
    {
      "tdOfGreatestEclipse": "2703-10-03T02:21:22Z",
      "deltaT": 2196,
      "deltaTSigma": 518,
      "lunaNum": 8704,
      "sarosNum": 155,
      "eclType": "H",
      "qle": "-p",
      "gamma": -0.4571,
      "eclMag": 1.0006,
      "lat": -30,
      "long": 142,
      "sunAlt": 63,
      "pathWidth": 2,
      "centralDur": 3
    },
    {
      "tdOfGreatestEclipse": "2704-03-27T19:45:54Z",
      "deltaT": 2199,
      "deltaTSigma": 519,
      "lunaNum": 8710,
      "sarosNum": 160,
      "eclType": "H",
      "qle": "n-",
      "gamma": -0.221,
      "eclMag": 1.0148,
      "lat": -10,
      "long": -102,
      "sunAlt": 77,
      "pathWidth": 52,
      "centralDur": 89
    },
    {
      "tdOfGreatestEclipse": "2704-09-21T08:23:49Z",
      "deltaT": 2201,
      "deltaTSigma": 520,
      "lunaNum": 8716,
      "sarosNum": 165,
      "eclType": "A",
      "qle": "nn",
      "gamma": 0.2984,
      "eclMag": 0.9545,
      "lat": 17,
      "long": 67,
      "sunAlt": 73,
      "pathWidth": 173,
      "centralDur": 326
    },
    {
      "tdOfGreatestEclipse": "2705-03-17T10:10:55Z",
      "deltaT": 2204,
      "deltaTSigma": 520,
      "lunaNum": 8722,
      "sarosNum": 170,
      "eclType": "T",
      "qle": "p-",
      "gamma": -0.903,
      "eclMag": 1.0419,
      "lat": -61,
      "long": 73,
      "sunAlt": 25,
      "pathWidth": 327,
      "centralDur": 164
    },
    {
      "tdOfGreatestEclipse": "2705-09-10T08:59:51Z",
      "deltaT": 2207,
      "deltaTSigma": 521,
      "lunaNum": 8728,
      "sarosNum": 175,
      "eclType": "P",
      "qle": "t-",
      "gamma": 1.0483,
      "eclMag": 0.8768,
      "lat": 72,
      "long": 159,
      "sunAlt": 0,
      "pathWidth": 0,
      "centralDur": 0
    },
    {
      "tdOfGreatestEclipse": "2706-02-05T15:07:10Z",
      "deltaT": 2209,
      "deltaTSigma": 521,
      "lunaNum": 8733,
      "sarosNum": 142,
      "eclType": "P",
      "qle": "-t",
      "gamma": 1.1219,
      "eclMag": 0.7712,
      "lat": 70,
      "long": -71,
      "sunAlt": 0,
      "pathWidth": 0,
      "centralDur": 0
    },
    {
      "tdOfGreatestEclipse": "2706-07-31T23:20:36Z",
      "deltaT": 2212,
      "deltaTSigma": 522,
      "lunaNum": 8739,
      "sarosNum": 147,
      "eclType": "A",
      "qle": "-t",
      "gamma": -0.989,
      "eclMag": 0.9911,
      "lat": -63,
      "long": -180,
      "sunAlt": 7,
      "pathWidth": 241,
      "centralDur": 41
    },
    {
      "tdOfGreatestEclipse": "2707-01-26T00:42:03Z",
      "deltaT": 2215,
      "deltaTSigma": 522,
      "lunaNum": 8745,
      "sarosNum": 152,
      "eclType": "A",
      "qle": "-p",
      "gamma": 0.4646,
      "eclMag": 0.9587,
      "lat": 8,
      "long": 178,
      "sunAlt": 62,
      "pathWidth": 169,
      "centralDur": 308
    },
    {
      "tdOfGreatestEclipse": "2707-07-21T11:58:08Z",
      "deltaT": 2218,
      "deltaTSigma": 523,
      "lunaNum": 8751,
      "sarosNum": 157,
      "eclType": "T",
      "qle": "nn",
      "gamma": -0.1871,
      "eclMag": 1.0593,
      "lat": 10,
      "long": 11,
      "sunAlt": 79,
      "pathWidth": 199,
      "centralDur": 348
    },
    {
      "tdOfGreatestEclipse": "2708-01-15T02:56:15Z",
      "deltaT": 2221,
      "deltaTSigma": 524,
      "lunaNum": 8757,
      "sarosNum": 162,
      "eclType": "A",
      "qle": "nn",
      "gamma": -0.2276,
      "eclMag": 0.9212,
      "lat": -35,
      "long": 148,
      "sunAlt": 77,
      "pathWidth": 306,
      "centralDur": 578
    },
    {
      "tdOfGreatestEclipse": "2708-07-10T04:49:14Z",
      "deltaT": 2224,
      "deltaTSigma": 524,
      "lunaNum": 8763,
      "sarosNum": 167,
      "eclType": "T",
      "qle": "p-",
      "gamma": 0.555,
      "eclMag": 1.0774,
      "lat": 56,
      "long": 121,
      "sunAlt": 56,
      "pathWidth": 302,
      "centralDur": 322
    },
    {
      "tdOfGreatestEclipse": "2709-01-03T01:57:48Z",
      "deltaT": 2226,
      "deltaTSigma": 525,
      "lunaNum": 8769,
      "sarosNum": 172,
      "eclType": "A",
      "qle": "p-",
      "gamma": -0.9017,
      "eclMag": 0.9176,
      "lat": -88,
      "long": 147,
      "sunAlt": 25,
      "pathWidth": 737,
      "centralDur": 355
    },
    {
      "tdOfGreatestEclipse": "2709-05-31T12:21:15Z",
      "deltaT": 2229,
      "deltaTSigma": 525,
      "lunaNum": 8774,
      "sarosNum": 139,
      "eclType": "P",
      "qle": "-t",
      "gamma": -1.2869,
      "eclMag": 0.4696,
      "lat": -64,
      "long": 37,
      "sunAlt": 0,
      "pathWidth": 0,
      "centralDur": 0
    },
    {
      "tdOfGreatestEclipse": "2709-06-29T21:16:21Z",
      "deltaT": 2229,
      "deltaTSigma": 525,
      "lunaNum": 8775,
      "sarosNum": 177,
      "eclType": "P",
      "qle": "t-",
      "gamma": 1.3156,
      "eclMag": 0.4141,
      "lat": 67,
      "long": 56,
      "sunAlt": 0,
      "pathWidth": 0,
      "centralDur": 0
    },
    {
      "tdOfGreatestEclipse": "2709-11-23T15:53:38Z",
      "deltaT": 2232,
      "deltaTSigma": 526,
      "lunaNum": 8780,
      "sarosNum": 144,
      "eclType": "P",
      "qle": "-t",
      "gamma": 1.2838,
      "eclMag": 0.4758,
      "lat": 64,
      "long": -11,
      "sunAlt": 0,
      "pathWidth": 0,
      "centralDur": 0
    },
    {
      "tdOfGreatestEclipse": "2709-12-23T05:25:42Z",
      "deltaT": 2232,
      "deltaTSigma": 526,
      "lunaNum": 8781,
      "sarosNum": 182,
      "eclType": "P",
      "qle": "t-",
      "gamma": -1.5349,
      "eclMag": 0.0373,
      "lat": -66,
      "long": -60,
      "sunAlt": 0,
      "pathWidth": 0,
      "centralDur": 0
    },
    {
      "tdOfGreatestEclipse": "2710-05-20T20:07:00Z",
      "deltaT": 2234,
      "deltaTSigma": 526,
      "lunaNum": 8786,
      "sarosNum": 149,
      "eclType": "A",
      "qle": "-p",
      "gamma": -0.5739,
      "eclMag": 0.962,
      "lat": -14,
      "long": -102,
      "sunAlt": 55,
      "pathWidth": 166,
      "centralDur": 274
    },
    {
      "tdOfGreatestEclipse": "2710-11-13T05:50:16Z",
      "deltaT": 2237,
      "deltaTSigma": 527,
      "lunaNum": 8792,
      "sarosNum": 154,
      "eclType": "T",
      "qle": "-p",
      "gamma": 0.5489,
      "eclMag": 1.0485,
      "lat": 14,
      "long": 109,
      "sunAlt": 57,
      "pathWidth": 191,
      "centralDur": 260
    },
    {
      "tdOfGreatestEclipse": "2711-05-09T21:21:39Z",
      "deltaT": 2240,
      "deltaTSigma": 528,
      "lunaNum": 8798,
      "sarosNum": 159,
      "eclType": "A",
      "qle": "nn",
      "gamma": 0.17,
      "eclMag": 0.9385,
      "lat": 26,
      "long": -136,
      "sunAlt": 80,
      "pathWidth": 231,
      "centralDur": 425
    },
    {
      "tdOfGreatestEclipse": "2711-11-02T22:04:59Z",
      "deltaT": 2243,
      "deltaTSigma": 528,
      "lunaNum": 8804,
      "sarosNum": 164,
      "eclType": "T",
      "qle": "n-",
      "gamma": -0.1447,
      "eclMag": 1.0523,
      "lat": -22,
      "long": -150,
      "sunAlt": 82,
      "pathWidth": 175,
      "centralDur": 261
    },
    {
      "tdOfGreatestEclipse": "2712-04-27T22:19:05Z",
      "deltaT": 2246,
      "deltaTSigma": 529,
      "lunaNum": 8810,
      "sarosNum": 169,
      "eclType": "A",
      "qle": "t-",
      "gamma": 0.8955,
      "eclMag": 0.9492,
      "lat": 64,
      "long": 156,
      "sunAlt": 26,
      "pathWidth": 417,
      "centralDur": 221
    },
    {
      "tdOfGreatestEclipse": "2712-10-22T11:55:14Z",
      "deltaT": 2249,
      "deltaTSigma": 529,
      "lunaNum": 8816,
      "sarosNum": 174,
      "eclType": "H",
      "qle": "p-",
      "gamma": -0.8872,
      "eclMag": 1.0009,
      "lat": -61,
      "long": -46,
      "sunAlt": 27,
      "pathWidth": 6,
      "centralDur": 3
    },
    {
      "tdOfGreatestEclipse": "2713-03-18T18:21:30Z",
      "deltaT": 2251,
      "deltaTSigma": 530,
      "lunaNum": 8821,
      "sarosNum": 141,
      "eclType": "P",
      "qle": "-t",
      "gamma": -1.1428,
      "eclMag": 0.7361,
      "lat": -61,
      "long": 8,
      "sunAlt": 0,
      "pathWidth": 0,
      "centralDur": 0
    },
    {
      "tdOfGreatestEclipse": "2713-09-12T04:18:09Z",
      "deltaT": 2254,
      "deltaTSigma": 530,
      "lunaNum": 8827,
      "sarosNum": 146,
      "eclType": "P",
      "qle": "-t",
      "gamma": 1.1807,
      "eclMag": 0.6535,
      "lat": 61,
      "long": -138,
      "sunAlt": 0,
      "pathWidth": 0,
      "centralDur": 0
    },
    {
      "tdOfGreatestEclipse": "2714-03-08T09:37:11Z",
      "deltaT": 2257,
      "deltaTSigma": 531,
      "lunaNum": 8833,
      "sarosNum": 151,
      "eclType": "T",
      "qle": "-n",
      "gamma": -0.4343,
      "eclMag": 1.052,
      "lat": -28,
      "long": 61,
      "sunAlt": 64,
      "pathWidth": 189,
      "centralDur": 241
    },
    {
      "tdOfGreatestEclipse": "2714-09-01T04:36:47Z",
      "deltaT": 2260,
      "deltaTSigma": 532,
      "lunaNum": 8839,
      "sarosNum": 156,
      "eclType": "A",
      "qle": "-p",
      "gamma": 0.4397,
      "eclMag": 0.9474,
      "lat": 31,
      "long": 134,
      "sunAlt": 64,
      "pathWidth": 213,
      "centralDur": 324
    },
    {
      "tdOfGreatestEclipse": "2715-02-26T01:11:16Z",
      "deltaT": 2263,
      "deltaTSigma": 532,
      "lunaNum": 8845,
      "sarosNum": 161,
      "eclType": "T",
      "qle": "n-",
      "gamma": 0.2495,
      "eclMag": 1.0302,
      "lat": 4,
      "long": 168,
      "sunAlt": 76,
      "pathWidth": 105,
      "centralDur": 162
    },
    {
      "tdOfGreatestEclipse": "2715-08-21T08:26:50Z",
      "deltaT": 2265,
      "deltaTSigma": 533,
      "lunaNum": 8851,
      "sarosNum": 166,
      "eclType": "A",
      "qle": "p-",
      "gamma": -0.3332,
      "eclMag": 0.9901,
      "lat": -5,
      "long": 56,
      "sunAlt": 71,
      "pathWidth": 37,
      "centralDur": 63
    },
    {
      "tdOfGreatestEclipse": "2716-02-15T12:26:23Z",
      "deltaT": 2268,
      "deltaTSigma": 533,
      "lunaNum": 8857,
      "sarosNum": 171,
      "eclType": "An",
      "qle": "p-",
      "gamma": 0.9874,
      "eclMag": 0.9617,
      "lat": 57,
      "long": -45,
      "sunAlt": 8,
      "pathWidth": null,
      "centralDur": 175
    },
    {
      "tdOfGreatestEclipse": "2716-07-11T12:01:40Z",
      "deltaT": 2271,
      "deltaTSigma": 534,
      "lunaNum": 8862,
      "sarosNum": 138,
      "eclType": "Pe",
      "qle": "-t",
      "gamma": 1.4666,
      "eclMag": 0.1218,
      "lat": 64,
      "long": 158,
      "sunAlt": 0,
      "pathWidth": 0,
      "centralDur": 0
    },
    {
      "tdOfGreatestEclipse": "2716-08-09T19:35:28Z",
      "deltaT": 2271,
      "deltaTSigma": 534,
      "lunaNum": 8863,
      "sarosNum": 176,
      "eclType": "P",
      "qle": "t-",
      "gamma": -1.0674,
      "eclMag": 0.8831,
      "lat": -62,
      "long": -161,
      "sunAlt": 0,
      "pathWidth": 0,
      "centralDur": 0
    },
    {
      "tdOfGreatestEclipse": "2717-01-04T21:20:50Z",
      "deltaT": 2274,
      "deltaTSigma": 535,
      "lunaNum": 8868,
      "sarosNum": 143,
      "eclType": "P",
      "qle": "-t",
      "gamma": -1.3123,
      "eclMag": 0.4307,
      "lat": -65,
      "long": 22,
      "sunAlt": 0,
      "pathWidth": 0,
      "centralDur": 0
    },
    {
      "tdOfGreatestEclipse": "2717-07-01T05:13:28Z",
      "deltaT": 2276,
      "deltaTSigma": 535,
      "lunaNum": 8874,
      "sarosNum": 148,
      "eclType": "T",
      "qle": "-p",
      "gamma": 0.7369,
      "eclMag": 1.0707,
      "lat": 69,
      "long": 133,
      "sunAlt": 42,
      "pathWidth": 342,
      "centralDur": 260
    },
    {
      "tdOfGreatestEclipse": "2717-12-24T20:58:03Z",
      "deltaT": 2279,
      "deltaTSigma": 536,
      "lunaNum": 8880,
      "sarosNum": 153,
      "eclType": "A",
      "qle": "-p",
      "gamma": -0.6211,
      "eclMag": 0.9329,
      "lat": -62,
      "long": -117,
      "sunAlt": 51,
      "pathWidth": 321,
      "centralDur": 360
    },
    {
      "tdOfGreatestEclipse": "2718-06-20T20:43:12Z",
      "deltaT": 2282,
      "deltaTSigma": 536,
      "lunaNum": 8886,
      "sarosNum": 158,
      "eclType": "T",
      "qle": "nn",
      "gamma": -0.0033,
      "eclMag": 1.0362,
      "lat": 23,
      "long": -121,
      "sunAlt": 90,
      "pathWidth": 122,
      "centralDur": 214
    },
    {
      "tdOfGreatestEclipse": "2718-12-14T02:32:43Z",
      "deltaT": 2285,
      "deltaTSigma": 537,
      "lunaNum": 8892,
      "sarosNum": 163,
      "eclType": "A",
      "qle": "n-",
      "gamma": 0.1027,
      "eclMag": 0.9885,
      "lat": -17,
      "long": 149,
      "sunAlt": 84,
      "pathWidth": 41,
      "centralDur": 77
    },
    {
      "tdOfGreatestEclipse": "2719-06-10T06:16:07Z",
      "deltaT": 2288,
      "deltaTSigma": 537,
      "lunaNum": 8898,
      "sarosNum": 168,
      "eclType": "A",
      "qle": "p-",
      "gamma": -0.8032,
      "eclMag": 0.9726,
      "lat": -31,
      "long": 95,
      "sunAlt": 36,
      "pathWidth": 165,
      "centralDur": 184
    },
    {
      "tdOfGreatestEclipse": "2719-12-03T15:07:58Z",
      "deltaT": 2291,
      "deltaTSigma": 538,
      "lunaNum": 8904,
      "sarosNum": 173,
      "eclType": "T",
      "qle": "p-",
      "gamma": 0.7836,
      "eclMag": 1.0331,
      "lat": 30,
      "long": -38,
      "sunAlt": 38,
      "pathWidth": 180,
      "centralDur": 181
    },
    {
      "tdOfGreatestEclipse": "2720-04-29T16:37:14Z",
      "deltaT": 2293,
      "deltaTSigma": 539,
      "lunaNum": 8909,
      "sarosNum": 140,
      "eclType": "P",
      "qle": "-t",
      "gamma": 1.3258,
      "eclMag": 0.406,
      "lat": 71,
      "long": 162,
      "sunAlt": 0,
      "pathWidth": 0,
      "centralDur": 0
    },
    {
      "tdOfGreatestEclipse": "2720-10-23T21:30:11Z",
      "deltaT": 2296,
      "deltaTSigma": 539,
      "lunaNum": 8915,
      "sarosNum": 145,
      "eclType": "P",
      "qle": "-t",
      "gamma": -1.1917,
      "eclMag": 0.6474,
      "lat": -71,
      "long": 96,
      "sunAlt": 0,
      "pathWidth": 0,
      "centralDur": 0
    },
    {
      "tdOfGreatestEclipse": "2720-11-22T07:03:44Z",
      "deltaT": 2297,
      "deltaTSigma": 539,
      "lunaNum": 8916,
      "sarosNum": 183,
      "eclType": "P",
      "qle": "t-",
      "gamma": 1.4388,
      "eclMag": 0.1807,
      "lat": 69,
      "long": 99,
      "sunAlt": 0,
      "pathWidth": 0,
      "centralDur": 0
    },
    {
      "tdOfGreatestEclipse": "2721-04-18T18:47:23Z",
      "deltaT": 2299,
      "deltaTSigma": 540,
      "lunaNum": 8921,
      "sarosNum": 150,
      "eclType": "A",
      "qle": "-p",
      "gamma": 0.5666,
      "eclMag": 0.9657,
      "lat": 44,
      "long": -104,
      "sunAlt": 55,
      "pathWidth": 150,
      "centralDur": 197
    },
    {
      "tdOfGreatestEclipse": "2721-10-13T09:57:36Z",
      "deltaT": 2302,
      "deltaTSigma": 540,
      "lunaNum": 8927,
      "sarosNum": 155,
      "eclType": "A",
      "qle": "-p",
      "gamma": -0.5078,
      "eclMag": 0.994,
      "lat": -37,
      "long": 27,
      "sunAlt": 59,
      "pathWidth": 24,
      "centralDur": 34
    },
    {
      "tdOfGreatestEclipse": "2722-04-08T03:51:01Z",
      "deltaT": 2305,
      "deltaTSigma": 541,
      "lunaNum": 8933,
      "sarosNum": 160,
      "eclType": "T",
      "qle": "n-",
      "gamma": -0.188,
      "eclMag": 1.0208,
      "lat": -3,
      "long": 135,
      "sunAlt": 79,
      "pathWidth": 72,
      "centralDur": 126
    },
    {
      "tdOfGreatestEclipse": "2722-10-02T15:28:03Z",
      "deltaT": 2308,
      "deltaTSigma": 542,
      "lunaNum": 8939,
      "sarosNum": 165,
      "eclType": "A",
      "qle": "nn",
      "gamma": 0.2383,
      "eclMag": 0.9501,
      "lat": 10,
      "long": -41,
      "sunAlt": 76,
      "pathWidth": 188,
      "centralDur": 372
    },
    {
      "tdOfGreatestEclipse": "2723-03-28T18:35:40Z",
      "deltaT": 2311,
      "deltaTSigma": 542,
      "lunaNum": 8945,
      "sarosNum": 170,
      "eclType": "T",
      "qle": "p-",
      "gamma": -0.8766,
      "eclMag": 1.0465,
      "lat": -55,
      "long": -61,
      "sunAlt": 28,
      "pathWidth": 321,
      "centralDur": 193
    },
    {
      "tdOfGreatestEclipse": "2723-09-21T15:48:52Z",
      "deltaT": 2313,
      "deltaTSigma": 543,
      "lunaNum": 8951,
      "sarosNum": 175,
      "eclType": "An",
      "qle": "t-",
      "gamma": 0.9799,
      "eclMag": 0.9291,
      "lat": 70,
      "long": 11,
      "sunAlt": 11,
      "pathWidth": null,
      "centralDur": 324
    },
    {
      "tdOfGreatestEclipse": "2724-02-16T23:45:22Z",
      "deltaT": 2316,
      "deltaTSigma": 543,
      "lunaNum": 8956,
      "sarosNum": 142,
      "eclType": "P",
      "qle": "-t",
      "gamma": 1.1327,
      "eclMag": 0.751,
      "lat": 71,
      "long": 147,
      "sunAlt": 0,
      "pathWidth": 0,
      "centralDur": 0
    },
    {
      "tdOfGreatestEclipse": "2724-08-11T06:23:23Z",
      "deltaT": 2319,
      "deltaTSigma": 544,
      "lunaNum": 8962,
      "sarosNum": 147,
      "eclType": "P",
      "qle": "-t",
      "gamma": -1.061,
      "eclMag": 0.8796,
      "lat": -70,
      "long": 55,
      "sunAlt": 0,
      "pathWidth": 0,
      "centralDur": 0
    },
    {
      "tdOfGreatestEclipse": "2725-02-05T09:01:58Z",
      "deltaT": 2322,
      "deltaTSigma": 544,
      "lunaNum": 8968,
      "sarosNum": 152,
      "eclType": "A",
      "qle": "-p",
      "gamma": 0.4734,
      "eclMag": 0.9567,
      "lat": 12,
      "long": 52,
      "sunAlt": 62,
      "pathWidth": 178,
      "centralDur": 317
    },
    {
      "tdOfGreatestEclipse": "2725-07-31T19:21:11Z",
      "deltaT": 2325,
      "deltaTSigma": 545,
      "lunaNum": 8974,
      "sarosNum": 157,
      "eclType": "T",
      "qle": "-n",
      "gamma": -0.2611,
      "eclMag": 1.0612,
      "lat": 3,
      "long": -101,
      "sunAlt": 75,
      "pathWidth": 208,
      "centralDur": 357
    },
    {
      "tdOfGreatestEclipse": "2726-01-25T10:59:21Z",
      "deltaT": 2327,
      "deltaTSigma": 546,
      "lunaNum": 8980,
      "sarosNum": 162,
      "eclType": "A",
      "qle": "nn",
      "gamma": -0.2188,
      "eclMag": 0.9206,
      "lat": -32,
      "long": 30,
      "sunAlt": 77,
      "pathWidth": 308,
      "centralDur": 592
    },
    {
      "tdOfGreatestEclipse": "2726-07-21T12:17:46Z",
      "deltaT": 2330,
      "deltaTSigma": 546,
      "lunaNum": 8986,
      "sarosNum": 167,
      "eclType": "T",
      "qle": "p-",
      "gamma": 0.4807,
      "eclMag": 1.078,
      "lat": 49,
      "long": 12,
      "sunAlt": 61,
      "pathWidth": 288,
      "centralDur": 343
    },
    {
      "tdOfGreatestEclipse": "2727-01-14T10:03:49Z",
      "deltaT": 2333,
      "deltaTSigma": 547,
      "lunaNum": 8992,
      "sarosNum": 172,
      "eclType": "A",
      "qle": "p-",
      "gamma": -0.892,
      "eclMag": 0.9189,
      "lat": -84,
      "long": 74,
      "sunAlt": 26,
      "pathWidth": 691,
      "centralDur": 357
    },
    {
      "tdOfGreatestEclipse": "2727-06-11T19:38:58Z",
      "deltaT": 2336,
      "deltaTSigma": 547,
      "lunaNum": 8997,
      "sarosNum": 139,
      "eclType": "P",
      "qle": "-t",
      "gamma": -1.3591,
      "eclMag": 0.3371,
      "lat": -65,
      "long": -81,
      "sunAlt": 0,
      "pathWidth": 0,
      "centralDur": 0
    },
    {
      "tdOfGreatestEclipse": "2727-07-11T04:36:02Z",
      "deltaT": 2336,
      "deltaTSigma": 547,
      "lunaNum": 8998,
      "sarosNum": 177,
      "eclType": "P",
      "qle": "t-",
      "gamma": 1.2467,
      "eclMag": 0.5443,
      "lat": 68,
      "long": -64,
      "sunAlt": 0,
      "pathWidth": 0,
      "centralDur": 0
    },
    {
      "tdOfGreatestEclipse": "2727-12-05T00:17:19Z",
      "deltaT": 2339,
      "deltaTSigma": 548,
      "lunaNum": 9003,
      "sarosNum": 144,
      "eclType": "P",
      "qle": "-t",
      "gamma": 1.2968,
      "eclMag": 0.452,
      "lat": 64,
      "long": -146,
      "sunAlt": 0,
      "pathWidth": 0,
      "centralDur": 0
    },
    {
      "tdOfGreatestEclipse": "2728-01-03T13:50:30Z",
      "deltaT": 2339,
      "deltaTSigma": 548,
      "lunaNum": 9004,
      "sarosNum": 182,
      "eclType": "P",
      "qle": "t-",
      "gamma": -1.5232,
      "eclMag": 0.0568,
      "lat": -67,
      "long": 164,
      "sunAlt": 0,
      "pathWidth": 0,
      "centralDur": 0
    },
    {
      "tdOfGreatestEclipse": "2728-05-31T03:03:52Z",
      "deltaT": 2342,
      "deltaTSigma": 549,
      "lunaNum": 9009,
      "sarosNum": 149,
      "eclType": "A",
      "qle": "-p",
      "gamma": -0.6459,
      "eclMag": 0.9608,
      "lat": -17,
      "long": 153,
      "sunAlt": 50,
      "pathWidth": 185,
      "centralDur": 288
    },
    {
      "tdOfGreatestEclipse": "2728-11-23T14:20:43Z",
      "deltaT": 2344,
      "deltaTSigma": 549,
      "lunaNum": 9015,
      "sarosNum": 154,
      "eclType": "T",
      "qle": "-p",
      "gamma": 0.5701,
      "eclMag": 1.0468,
      "lat": 13,
      "long": -19,
      "sunAlt": 55,
      "pathWidth": 188,
      "centralDur": 257
    },
    {
      "tdOfGreatestEclipse": "2729-05-20T04:11:48Z",
      "deltaT": 2347,
      "deltaTSigma": 550,
      "lunaNum": 9021,
      "sarosNum": 159,
      "eclType": "A",
      "qle": "nn",
      "gamma": 0.1016,
      "eclMag": 0.9412,
      "lat": 26,
      "long": 124,
      "sunAlt": 84,
      "pathWidth": 219,
      "centralDur": 421
    },
    {
      "tdOfGreatestEclipse": "2729-11-13T06:26:07Z",
      "deltaT": 2350,
      "deltaTSigma": 550,
      "lunaNum": 9027,
      "sarosNum": 164,
      "eclType": "T",
      "qle": "n-",
      "gamma": -0.1162,
      "eclMag": 1.048,
      "lat": -24,
      "long": 87,
      "sunAlt": 83,
      "pathWidth": 161,
      "centralDur": 245
    },
    {
      "tdOfGreatestEclipse": "2730-05-09T05:30:50Z",
      "deltaT": 2353,
      "deltaTSigma": 551,
      "lunaNum": 9033,
      "sarosNum": 169,
      "eclType": "A",
      "qle": "p-",
      "gamma": 0.8363,
      "eclMag": 0.956,
      "lat": 65,
      "long": 59,
      "sunAlt": 33,
      "pathWidth": 291,
      "centralDur": 196
    },
    {
      "tdOfGreatestEclipse": "2730-11-02T19:52:55Z",
      "deltaT": 2356,
      "deltaTSigma": 552,
      "lunaNum": 9039,
      "sarosNum": 174,
      "eclType": "A",
      "qle": "p-",
      "gamma": -0.8541,
      "eclMag": 0.9959,
      "lat": -63,
      "long": -162,
      "sunAlt": 31,
      "pathWidth": 28,
      "centralDur": 17
    },
    {
      "tdOfGreatestEclipse": "2731-03-30T02:38:12Z",
      "deltaT": 2359,
      "deltaTSigma": 552,
      "lunaNum": 9044,
      "sarosNum": 141,
      "eclType": "P",
      "qle": "-t",
      "gamma": -1.167,
      "eclMag": 0.6924,
      "lat": -61,
      "long": -125,
      "sunAlt": 0,
      "pathWidth": 0,
      "centralDur": 0
    },
    {
      "tdOfGreatestEclipse": "2731-04-28T13:11:23Z",
      "deltaT": 2359,
      "deltaTSigma": 552,
      "lunaNum": 9045,
      "sarosNum": 179,
      "eclType": "Pb",
      "qle": "t-",
      "gamma": 1.5159,
      "eclMag": 0.0519,
      "lat": 62,
      "long": -127,
      "sunAlt": 0,
      "pathWidth": 0,
      "centralDur": 0
    },
    {
      "tdOfGreatestEclipse": "2731-09-23T11:10:43Z",
      "deltaT": 2362,
      "deltaTSigma": 553,
      "lunaNum": 9050,
      "sarosNum": 146,
      "eclType": "P",
      "qle": "-t",
      "gamma": 1.2491,
      "eclMag": 0.5365,
      "lat": 61,
      "long": 110,
      "sunAlt": 0,
      "pathWidth": 0,
      "centralDur": 0
    },
    {
      "tdOfGreatestEclipse": "2732-03-18T18:10:33Z",
      "deltaT": 2364,
      "deltaTSigma": 553,
      "lunaNum": 9056,
      "sarosNum": 151,
      "eclType": "T",
      "qle": "-n",
      "gamma": -0.4552,
      "eclMag": 1.0544,
      "lat": -24,
      "long": -67,
      "sunAlt": 63,
      "pathWidth": 200,
      "centralDur": 255
    },
    {
      "tdOfGreatestEclipse": "2732-09-11T11:21:51Z",
      "deltaT": 2367,
      "deltaTSigma": 554,
      "lunaNum": 9062,
      "sarosNum": 156,
      "eclType": "A",
      "qle": "-p",
      "gamma": 0.5138,
      "eclMag": 0.9461,
      "lat": 31,
      "long": 36,
      "sunAlt": 59,
      "pathWidth": 227,
      "centralDur": 329
    },
    {
      "tdOfGreatestEclipse": "2733-03-08T09:44:47Z",
      "deltaT": 2370,
      "deltaTSigma": 554,
      "lunaNum": 9068,
      "sarosNum": 161,
      "eclType": "T",
      "qle": "n-",
      "gamma": 0.2342,
      "eclMag": 1.0301,
      "lat": 7,
      "long": 40,
      "sunAlt": 76,
      "pathWidth": 104,
      "centralDur": 159
    },
    {
      "tdOfGreatestEclipse": "2733-08-31T15:30:14Z",
      "deltaT": 2373,
      "deltaTSigma": 555,
      "lunaNum": 9074,
      "sarosNum": 166,
      "eclType": "A",
      "qle": "n-",
      "gamma": -0.2587,
      "eclMag": 0.992,
      "lat": -5,
      "long": -49,
      "sunAlt": 75,
      "pathWidth": 29,
      "centralDur": 49
    },
    {
      "tdOfGreatestEclipse": "2734-02-25T20:45:23Z",
      "deltaT": 2376,
      "deltaTSigma": 556,
      "lunaNum": 9080,
      "sarosNum": 171,
      "eclType": "A",
      "qle": "p-",
      "gamma": 0.9773,
      "eclMag": 0.9615,
      "lat": 56,
      "long": -172,
      "sunAlt": 11,
      "pathWidth": 673,
      "centralDur": 175
    },
    {
      "tdOfGreatestEclipse": "2734-08-21T02:59:11Z",
      "deltaT": 2379,
      "deltaTSigma": 556,
      "lunaNum": 9086,
      "sarosNum": 176,
      "eclType": "Ts",
      "qle": "t-",
      "gamma": -0.9936,
      "eclMag": 1.0332,
      "lat": -59,
      "long": 89,
      "sunAlt": 5,
      "pathWidth": null,
      "centralDur": 128
    },
    {
      "tdOfGreatestEclipse": "2735-01-16T05:21:33Z",
      "deltaT": 2382,
      "deltaTSigma": 557,
      "lunaNum": 9091,
      "sarosNum": 143,
      "eclType": "P",
      "qle": "-t",
      "gamma": -1.3223,
      "eclMag": 0.4142,
      "lat": -64,
      "long": -107,
      "sunAlt": 0,
      "pathWidth": 0,
      "centralDur": 0
    },
    {
      "tdOfGreatestEclipse": "2735-07-12T12:43:08Z",
      "deltaT": 2385,
      "deltaTSigma": 557,
      "lunaNum": 9097,
      "sarosNum": 148,
      "eclType": "T",
      "qle": "-p",
      "gamma": 0.8101,
      "eclMag": 1.0682,
      "lat": 72,
      "long": 39,
      "sunAlt": 36,
      "pathWidth": 381,
      "centralDur": 239
    },
    {
      "tdOfGreatestEclipse": "2736-01-05T05:06:09Z",
      "deltaT": 2387,
      "deltaTSigma": 558,
      "lunaNum": 9103,
      "sarosNum": 153,
      "eclType": "A",
      "qle": "-p",
      "gamma": -0.63,
      "eclMag": 0.934,
      "lat": -61,
      "long": 129,
      "sunAlt": 51,
      "pathWidth": 318,
      "centralDur": 350
    },
    {
      "tdOfGreatestEclipse": "2736-07-01T03:59:43Z",
      "deltaT": 2390,
      "deltaTSigma": 559,
      "lunaNum": 9109,
      "sarosNum": 158,
      "eclType": "T",
      "qle": "nn",
      "gamma": 0.0708,
      "eclMag": 1.0339,
      "lat": 27,
      "long": 132,
      "sunAlt": 86,
      "pathWidth": 114,
      "centralDur": 195
    },
    {
      "tdOfGreatestEclipse": "2736-12-24T11:00:54Z",
      "deltaT": 2393,
      "deltaTSigma": 559,
      "lunaNum": 9115,
      "sarosNum": 163,
      "eclType": "A",
      "qle": "n-",
      "gamma": 0.0927,
      "eclMag": 0.99,
      "lat": -18,
      "long": 24,
      "sunAlt": 85,
      "pathWidth": 35,
      "centralDur": 66
    },
    {
      "tdOfGreatestEclipse": "2737-06-20T13:07:57Z",
      "deltaT": 2396,
      "deltaTSigma": 560,
      "lunaNum": 9121,
      "sarosNum": 168,
      "eclType": "A",
      "qle": "p-",
      "gamma": -0.7281,
      "eclMag": 0.9726,
      "lat": -23,
      "long": -10,
      "sunAlt": 43,
      "pathWidth": 143,
      "centralDur": 194
    },
    {
      "tdOfGreatestEclipse": "2737-12-13T23:47:40Z",
      "deltaT": 2399,
      "deltaTSigma": 560,
      "lunaNum": 9127,
      "sarosNum": 173,
      "eclType": "T",
      "qle": "p-",
      "gamma": 0.7697,
      "eclMag": 1.0332,
      "lat": 27,
      "long": -170,
      "sunAlt": 39,
      "pathWidth": 176,
      "centralDur": 184
    },
    {
      "tdOfGreatestEclipse": "2738-05-10T23:34:28Z",
      "deltaT": 2402,
      "deltaTSigma": 561,
      "lunaNum": 9132,
      "sarosNum": 140,
      "eclType": "P",
      "qle": "-t",
      "gamma": 1.3856,
      "eclMag": 0.3041,
      "lat": 70,
      "long": 46,
      "sunAlt": 0,
      "pathWidth": 0,
      "centralDur": 0
    },
    {
      "tdOfGreatestEclipse": "2738-06-09T15:22:59Z",
      "deltaT": 2402,
      "deltaTSigma": 561,
      "lunaNum": 9133,
      "sarosNum": 178,
      "eclType": "Pb",
      "qle": "t-",
      "gamma": -1.5104,
      "eclMag": 0.0906,
      "lat": -67,
      "long": -42,
      "sunAlt": 0,
      "pathWidth": 0,
      "centralDur": 0
    },
    {
      "tdOfGreatestEclipse": "2738-11-04T05:42:24Z",
      "deltaT": 2405,
      "deltaTSigma": 562,
      "lunaNum": 9138,
      "sarosNum": 145,
      "eclType": "P",
      "qle": "-t",
      "gamma": -1.226,
      "eclMag": 0.5826,
      "lat": -71,
      "long": -40,
      "sunAlt": 0,
      "pathWidth": 0,
      "centralDur": 0
    },
    {
      "tdOfGreatestEclipse": "2738-12-03T15:40:11Z",
      "deltaT": 2405,
      "deltaTSigma": 562,
      "lunaNum": 9139,
      "sarosNum": 183,
      "eclType": "P",
      "qle": "t-",
      "gamma": 1.4236,
      "eclMag": 0.2103,
      "lat": 68,
      "long": -41,
      "sunAlt": 0,
      "pathWidth": 0,
      "centralDur": 0
    },
    {
      "tdOfGreatestEclipse": "2739-04-30T02:11:53Z",
      "deltaT": 2408,
      "deltaTSigma": 562,
      "lunaNum": 9144,
      "sarosNum": 150,
      "eclType": "A",
      "qle": "-p",
      "gamma": 0.6158,
      "eclMag": 0.9708,
      "lat": 51,
      "long": 144,
      "sunAlt": 52,
      "pathWidth": 133,
      "centralDur": 157
    },
    {
      "tdOfGreatestEclipse": "2739-10-24T17:41:45Z",
      "deltaT": 2411,
      "deltaTSigma": 563,
      "lunaNum": 9150,
      "sarosNum": 155,
      "eclType": "A",
      "qle": "-p",
      "gamma": -0.5511,
      "eclMag": 0.9874,
      "lat": -44,
      "long": -90,
      "sunAlt": 56,
      "pathWidth": 53,
      "centralDur": 68
    },
    {
      "tdOfGreatestEclipse": "2740-04-18T11:49:20Z",
      "deltaT": 2414,
      "deltaTSigma": 563,
      "lunaNum": 9156,
      "sarosNum": 160,
      "eclType": "T",
      "qle": "n-",
      "gamma": -0.1486,
      "eclMag": 1.0268,
      "lat": 3,
      "long": 15,
      "sunAlt": 81,
      "pathWidth": 92,
      "centralDur": 163
    },
    {
      "tdOfGreatestEclipse": "2740-10-12T22:38:21Z",
      "deltaT": 2417,
      "deltaTSigma": 564,
      "lunaNum": 9162,
      "sarosNum": 165,
      "eclType": "A",
      "qle": "nn",
      "gamma": 0.1837,
      "eclMag": 0.9456,
      "lat": 2,
      "long": -150,
      "sunAlt": 79,
      "pathWidth": 204,
      "centralDur": 419
    },
    {
      "tdOfGreatestEclipse": "2741-04-08T02:54:47Z",
      "deltaT": 2419,
      "deltaTSigma": 565,
      "lunaNum": 9168,
      "sarosNum": 170,
      "eclType": "T",
      "qle": "p-",
      "gamma": -0.8453,
      "eclMag": 1.0513,
      "lat": -48,
      "long": 168,
      "sunAlt": 32,
      "pathWidth": 317,
      "centralDur": 226
    },
    {
      "tdOfGreatestEclipse": "2741-10-01T22:44:39Z",
      "deltaT": 2422,
      "deltaTSigma": 565,
      "lunaNum": 9174,
      "sarosNum": 175,
      "eclType": "A",
      "qle": "t-",
      "gamma": 0.9162,
      "eclMag": 0.9303,
      "lat": 59,
      "long": -122,
      "sunAlt": 23,
      "pathWidth": 651,
      "centralDur": 374
    },
    {
      "tdOfGreatestEclipse": "2742-02-27T08:19:25Z",
      "deltaT": 2425,
      "deltaTSigma": 566,
      "lunaNum": 9179,
      "sarosNum": 142,
      "eclType": "P",
      "qle": "-t",
      "gamma": 1.1469,
      "eclMag": 0.7249,
      "lat": 72,
      "long": 5,
      "sunAlt": 0,
      "pathWidth": 0,
      "centralDur": 0
    },
    {
      "tdOfGreatestEclipse": "2742-08-22T13:29:52Z",
      "deltaT": 2428,
      "deltaTSigma": 566,
      "lunaNum": 9185,
      "sarosNum": 147,
      "eclType": "P",
      "qle": "-t",
      "gamma": -1.1308,
      "eclMag": 0.7533,
      "lat": -71,
      "long": -64,
      "sunAlt": 0,
      "pathWidth": 0,
      "centralDur": 0
    },
    {
      "tdOfGreatestEclipse": "2743-02-16T17:18:51Z",
      "deltaT": 2431,
      "deltaTSigma": 567,
      "lunaNum": 9191,
      "sarosNum": 152,
      "eclType": "A",
      "qle": "-p",
      "gamma": 0.4843,
      "eclMag": 0.9553,
      "lat": 16,
      "long": -73,
      "sunAlt": 61,
      "pathWidth": 185,
      "centralDur": 320
    },
    {
      "tdOfGreatestEclipse": "2743-08-12T02:47:37Z",
      "deltaT": 2434,
      "deltaTSigma": 568,
      "lunaNum": 9197,
      "sarosNum": 157,
      "eclType": "T",
      "qle": "-n",
      "gamma": -0.333,
      "eclMag": 1.0623,
      "lat": -4,
      "long": 146,
      "sunAlt": 71,
      "pathWidth": 216,
      "centralDur": 356
    },
    {
      "tdOfGreatestEclipse": "2744-02-05T19:00:27Z",
      "deltaT": 2437,
      "deltaTSigma": 568,
      "lunaNum": 9203,
      "sarosNum": 162,
      "eclType": "A",
      "qle": "nn",
      "gamma": -0.2085,
      "eclMag": 0.9205,
      "lat": -28,
      "long": -89,
      "sunAlt": 78,
      "pathWidth": 308,
      "centralDur": 601
    },
    {
      "tdOfGreatestEclipse": "2744-07-31T19:48:22Z",
      "deltaT": 2440,
      "deltaTSigma": 569,
      "lunaNum": 9209,
      "sarosNum": 167,
      "eclType": "T",
      "qle": "p-",
      "gamma": 0.4081,
      "eclMag": 1.0778,
      "lat": 42,
      "long": -100,
      "sunAlt": 66,
      "pathWidth": 276,
      "centralDur": 359
    },
    {
      "tdOfGreatestEclipse": "2745-01-24T18:10:35Z",
      "deltaT": 2443,
      "deltaTSigma": 569,
      "lunaNum": 9215,
      "sarosNum": 172,
      "eclType": "A",
      "qle": "p-",
      "gamma": -0.8824,
      "eclMag": 0.9207,
      "lat": -79,
      "long": -41,
      "sunAlt": 28,
      "pathWidth": 646,
      "centralDur": 358
    },
    {
      "tdOfGreatestEclipse": "2745-06-22T02:51:27Z",
      "deltaT": 2445,
      "deltaTSigma": 570,
      "lunaNum": 9220,
      "sarosNum": 139,
      "eclType": "P",
      "qle": "-t",
      "gamma": -1.4346,
      "eclMag": 0.1991,
      "lat": -66,
      "long": 161,
      "sunAlt": 0,
      "pathWidth": 0,
      "centralDur": 0
    },
    {
      "tdOfGreatestEclipse": "2745-07-21T11:53:44Z",
      "deltaT": 2446,
      "deltaTSigma": 570,
      "lunaNum": 9221,
      "sarosNum": 177,
      "eclType": "P",
      "qle": "t-",
      "gamma": 1.1767,
      "eclMag": 0.6761,
      "lat": 69,
      "long": 176,
      "sunAlt": 0,
      "pathWidth": 0,
      "centralDur": 0
    },
    {
      "tdOfGreatestEclipse": "2745-12-15T08:47:05Z",
      "deltaT": 2448,
      "deltaTSigma": 570,
      "lunaNum": 9226,
      "sarosNum": 144,
      "eclType": "P",
      "qle": "-t",
      "gamma": 1.3057,
      "eclMag": 0.4358,
      "lat": 65,
      "long": 78,
      "sunAlt": 0,
      "pathWidth": 0,
      "centralDur": 0
    },
    {
      "tdOfGreatestEclipse": "2746-01-13T22:18:09Z",
      "deltaT": 2449,
      "deltaTSigma": 571,
      "lunaNum": 9227,
      "sarosNum": 182,
      "eclType": "P",
      "qle": "t-",
      "gamma": -1.5132,
      "eclMag": 0.0733,
      "lat": -68,
      "long": 27,
      "sunAlt": 0,
      "pathWidth": 0,
      "centralDur": 0
    },
    {
      "tdOfGreatestEclipse": "2746-06-11T09:53:41Z",
      "deltaT": 2451,
      "deltaTSigma": 571,
      "lunaNum": 9232,
      "sarosNum": 149,
      "eclType": "A",
      "qle": "-p",
      "gamma": -0.7227,
      "eclMag": 0.9591,
      "lat": -23,
      "long": 50,
      "sunAlt": 44,
      "pathWidth": 214,
      "centralDur": 299
    },
    {
      "tdOfGreatestEclipse": "2746-12-04T22:57:36Z",
      "deltaT": 2454,
      "deltaTSigma": 572,
      "lunaNum": 9238,
      "sarosNum": 154,
      "eclType": "T",
      "qle": "-p",
      "gamma": 0.5865,
      "eclMag": 1.0454,
      "lat": 13,
      "long": -149,
      "sunAlt": 54,
      "pathWidth": 186,
      "centralDur": 255
    },
    {
      "tdOfGreatestEclipse": "2747-05-31T10:54:34Z",
      "deltaT": 2457,
      "deltaTSigma": 572,
      "lunaNum": 9244,
      "sarosNum": 159,
      "eclType": "A",
      "qle": "nn",
      "gamma": 0.027,
      "eclMag": 0.9436,
      "lat": 23,
      "long": 26,
      "sunAlt": 88,
      "pathWidth": 208,
      "centralDur": 421
    },
    {
      "tdOfGreatestEclipse": "2747-11-24T14:54:26Z",
      "deltaT": 2460,
      "deltaTSigma": 573,
      "lunaNum": 9250,
      "sarosNum": 164,
      "eclType": "T",
      "qle": "nn",
      "gamma": -0.094,
      "eclMag": 1.0438,
      "lat": -26,
      "long": -39,
      "sunAlt": 84,
      "pathWidth": 147,
      "centralDur": 229
    },
    {
      "tdOfGreatestEclipse": "2748-05-19T12:36:21Z",
      "deltaT": 2463,
      "deltaTSigma": 574,
      "lunaNum": 9256,
      "sarosNum": 169,
      "eclType": "A",
      "qle": "p-",
      "gamma": 0.7708,
      "eclMag": 0.9624,
      "lat": 65,
      "long": -34,
      "sunAlt": 39,
      "pathWidth": 213,
      "centralDur": 173
    },
    {
      "tdOfGreatestEclipse": "2748-11-13T03:56:35Z",
      "deltaT": 2466,
      "deltaTSigma": 574,
      "lunaNum": 9262,
      "sarosNum": 174,
      "eclType": "A",
      "qle": "p-",
      "gamma": -0.8265,
      "eclMag": 0.9908,
      "lat": -65,
      "long": 82,
      "sunAlt": 34,
      "pathWidth": 57,
      "centralDur": 37
    },
    {
      "tdOfGreatestEclipse": "2749-04-09T10:47:44Z",
      "deltaT": 2469,
      "deltaTSigma": 575,
      "lunaNum": 9267,
      "sarosNum": 141,
      "eclType": "P",
      "qle": "-t",
      "gamma": -1.1976,
      "eclMag": 0.6362,
      "lat": -61,
      "long": 104,
      "sunAlt": 0,
      "pathWidth": 0,
      "centralDur": 0
    },
    {
      "tdOfGreatestEclipse": "2749-05-08T20:49:40Z",
      "deltaT": 2469,
      "deltaTSigma": 575,
      "lunaNum": 9268,
      "sarosNum": 179,
      "eclType": "P",
      "qle": "t-",
      "gamma": 1.4606,
      "eclMag": 0.1508,
      "lat": 63,
      "long": 110,
      "sunAlt": 0,
      "pathWidth": 0,
      "centralDur": 0
    },
    {
      "tdOfGreatestEclipse": "2749-10-03T18:09:49Z",
      "deltaT": 2472,
      "deltaTSigma": 575,
      "lunaNum": 9273,
      "sarosNum": 146,
      "eclType": "P",
      "qle": "-t",
      "gamma": 1.3116,
      "eclMag": 0.4304,
      "lat": 61,
      "long": -2,
      "sunAlt": 0,
      "pathWidth": 0,
      "centralDur": 0
    },
    {
      "tdOfGreatestEclipse": "2750-03-30T02:35:22Z",
      "deltaT": 2475,
      "deltaTSigma": 576,
      "lunaNum": 9279,
      "sarosNum": 151,
      "eclType": "T",
      "qle": "-p",
      "gamma": -0.4833,
      "eclMag": 1.057,
      "lat": -22,
      "long": 167,
      "sunAlt": 61,
      "pathWidth": 212,
      "centralDur": 271
    },
    {
      "tdOfGreatestEclipse": "2750-09-22T18:14:42Z",
      "deltaT": 2478,
      "deltaTSigma": 576,
      "lunaNum": 9285,
      "sarosNum": 156,
      "eclType": "A",
      "qle": "-p",
      "gamma": 0.5818,
      "eclMag": 0.9445,
      "lat": 31,
      "long": -66,
      "sunAlt": 54,
      "pathWidth": 246,
      "centralDur": 340
    },
    {
      "tdOfGreatestEclipse": "2751-03-19T18:10:32Z",
      "deltaT": 2481,
      "deltaTSigma": 577,
      "lunaNum": 9291,
      "sarosNum": 161,
      "eclType": "T",
      "qle": "n-",
      "gamma": 0.213,
      "eclMag": 1.0303,
      "lat": 10,
      "long": -87,
      "sunAlt": 78,
      "pathWidth": 105,
      "centralDur": 158
    },
    {
      "tdOfGreatestEclipse": "2751-09-11T22:41:02Z",
      "deltaT": 2484,
      "deltaTSigma": 578,
      "lunaNum": 9297,
      "sarosNum": 166,
      "eclType": "A",
      "qle": "n-",
      "gamma": -0.1894,
      "eclMag": 0.9934,
      "lat": -5,
      "long": -156,
      "sunAlt": 79,
      "pathWidth": 24,
      "centralDur": 40
    },
    {
      "tdOfGreatestEclipse": "2752-03-08T04:57:51Z",
      "deltaT": 2487,
      "deltaTSigma": 578,
      "lunaNum": 9303,
      "sarosNum": 171,
      "eclType": "A",
      "qle": "p-",
      "gamma": 0.9626,
      "eclMag": 0.9618,
      "lat": 56,
      "long": 64,
      "sunAlt": 15,
      "pathWidth": 510,
      "centralDur": 172
    },
    {
      "tdOfGreatestEclipse": "2752-08-31T10:28:15Z",
      "deltaT": 2490,
      "deltaTSigma": 579,
      "lunaNum": 9309,
      "sarosNum": 176,
      "eclType": "T",
      "qle": "t-",
      "gamma": -0.9235,
      "eclMag": 1.0394,
      "lat": -49,
      "long": -7,
      "sunAlt": 22,
      "pathWidth": 339,
      "centralDur": 166
    },
    {
      "tdOfGreatestEclipse": "2753-01-26T13:23:36Z",
      "deltaT": 2492,
      "deltaTSigma": 579,
      "lunaNum": 9314,
      "sarosNum": 143,
      "eclType": "P",
      "qle": "-t",
      "gamma": -1.3312,
      "eclMag": 0.3996,
      "lat": -63,
      "long": 124,
      "sunAlt": 0,
      "pathWidth": 0,
      "centralDur": 0
    },
    {
      "tdOfGreatestEclipse": "2753-07-22T20:10:00Z",
      "deltaT": 2495,
      "deltaTSigma": 580,
      "lunaNum": 9320,
      "sarosNum": 148,
      "eclType": "T",
      "qle": "-t",
      "gamma": 0.8854,
      "eclMag": 1.0646,
      "lat": 72,
      "long": -48,
      "sunAlt": 27,
      "pathWidth": 458,
      "centralDur": 215
    },
    {
      "tdOfGreatestEclipse": "2754-01-15T13:18:41Z",
      "deltaT": 2498,
      "deltaTSigma": 581,
      "lunaNum": 9326,
      "sarosNum": 153,
      "eclType": "A",
      "qle": "-p",
      "gamma": -0.6358,
      "eclMag": 0.9356,
      "lat": -58,
      "long": 12,
      "sunAlt": 50,
      "pathWidth": 310,
      "centralDur": 339
    },
    {
      "tdOfGreatestEclipse": "2754-07-12T11:11:54Z",
      "deltaT": 2501,
      "deltaTSigma": 581,
      "lunaNum": 9332,
      "sarosNum": 158,
      "eclType": "T",
      "qle": "nn",
      "gamma": 0.148,
      "eclMag": 1.0309,
      "lat": 30,
      "long": 27,
      "sunAlt": 81,
      "pathWidth": 105,
      "centralDur": 172
    },
    {
      "tdOfGreatestEclipse": "2755-01-04T19:33:44Z",
      "deltaT": 2504,
      "deltaTSigma": 582,
      "lunaNum": 9338,
      "sarosNum": 163,
      "eclType": "A",
      "qle": "n-",
      "gamma": 0.086,
      "eclMag": 0.992,
      "lat": -18,
      "long": -103,
      "sunAlt": 85,
      "pathWidth": 28,
      "centralDur": 52
    },
    {
      "tdOfGreatestEclipse": "2755-07-01T19:55:33Z",
      "deltaT": 2507,
      "deltaTSigma": 583,
      "lunaNum": 9344,
      "sarosNum": 168,
      "eclType": "A",
      "qle": "p-",
      "gamma": -0.6501,
      "eclMag": 0.972,
      "lat": -17,
      "long": -114,
      "sunAlt": 49,
      "pathWidth": 132,
      "centralDur": 204
    },
    {
      "tdOfGreatestEclipse": "2755-12-25T08:32:16Z",
      "deltaT": 2510,
      "deltaTSigma": 583,
      "lunaNum": 9350,
      "sarosNum": 173,
      "eclType": "T",
      "qle": "p-",
      "gamma": 0.7594,
      "eclMag": 1.0335,
      "lat": 26,
      "long": 56,
      "sunAlt": 40,
      "pathWidth": 174,
      "centralDur": 185
    },
    {
      "tdOfGreatestEclipse": "2756-05-21T06:26:47Z",
      "deltaT": 2513,
      "deltaTSigma": 584,
      "lunaNum": 9355,
      "sarosNum": 140,
      "eclType": "P",
      "qle": "-t",
      "gamma": 1.449,
      "eclMag": 0.1954,
      "lat": 69,
      "long": -69,
      "sunAlt": 0,
      "pathWidth": 0,
      "centralDur": 0
    },
    {
      "tdOfGreatestEclipse": "2756-06-19T21:57:04Z",
      "deltaT": 2513,
      "deltaTSigma": 584,
      "lunaNum": 9356,
      "sarosNum": 178,
      "eclType": "P",
      "qle": "t-",
      "gamma": -1.4326,
      "eclMag": 0.2231,
      "lat": -66,
      "long": -151,
      "sunAlt": 0,
      "pathWidth": 0,
      "centralDur": 0
    },
    {
      "tdOfGreatestEclipse": "2756-11-14T13:59:49Z",
      "deltaT": 2516,
      "deltaTSigma": 584,
      "lunaNum": 9361,
      "sarosNum": 145,
      "eclType": "P",
      "qle": "-t",
      "gamma": -1.2556,
      "eclMag": 0.527,
      "lat": -70,
      "long": -176,
      "sunAlt": 0,
      "pathWidth": 0,
      "centralDur": 0
    },
    {
      "tdOfGreatestEclipse": "2756-12-14T00:20:27Z",
      "deltaT": 2516,
      "deltaTSigma": 584,
      "lunaNum": 9362,
      "sarosNum": 183,
      "eclType": "P",
      "qle": "t-",
      "gamma": 1.4119,
      "eclMag": 0.2333,
      "lat": 67,
      "long": 179,
      "sunAlt": 0,
      "pathWidth": 0,
      "centralDur": 0
    },
    {
      "tdOfGreatestEclipse": "2757-05-10T09:32:08Z",
      "deltaT": 2519,
      "deltaTSigma": 585,
      "lunaNum": 9367,
      "sarosNum": 150,
      "eclType": "A",
      "qle": "-p",
      "gamma": 0.6691,
      "eclMag": 0.9758,
      "lat": 59,
      "long": 34,
      "sunAlt": 48,
      "pathWidth": 116,
      "centralDur": 121
    },
    {
      "tdOfGreatestEclipse": "2757-11-04T01:31:48Z",
      "deltaT": 2522,
      "deltaTSigma": 586,
      "lunaNum": 9373,
      "sarosNum": 155,
      "eclType": "A",
      "qle": "-p",
      "gamma": -0.5886,
      "eclMag": 0.9811,
      "lat": -50,
      "long": 152,
      "sunAlt": 54,
      "pathWidth": 83,
      "centralDur": 99
    },
    {
      "tdOfGreatestEclipse": "2758-04-29T19:40:28Z",
      "deltaT": 2525,
      "deltaTSigma": 586,
      "lunaNum": 9379,
      "sarosNum": 160,
      "eclType": "T",
      "qle": "nn",
      "gamma": -0.1025,
      "eclMag": 1.0328,
      "lat": 9,
      "long": -104,
      "sunAlt": 84,
      "pathWidth": 111,
      "centralDur": 198
    },
    {
      "tdOfGreatestEclipse": "2758-10-24T05:56:55Z",
      "deltaT": 2528,
      "deltaTSigma": 587,
      "lunaNum": 9385,
      "sarosNum": 165,
      "eclType": "A",
      "qle": "nn",
      "gamma": 0.1364,
      "eclMag": 0.9412,
      "lat": -4,
      "long": 99,
      "sunAlt": 82,
      "pathWidth": 220,
      "centralDur": 464
    },
    {
      "tdOfGreatestEclipse": "2759-04-19T11:05:48Z",
      "deltaT": 2531,
      "deltaTSigma": 587,
      "lunaNum": 9391,
      "sarosNum": 170,
      "eclType": "T",
      "qle": "p-",
      "gamma": -0.807,
      "eclMag": 1.056,
      "lat": -41,
      "long": 40,
      "sunAlt": 36,
      "pathWidth": 311,
      "centralDur": 262
    },
    {
      "tdOfGreatestEclipse": "2759-10-13T05:50:13Z",
      "deltaT": 2534,
      "deltaTSigma": 588,
      "lunaNum": 9397,
      "sarosNum": 175,
      "eclType": "A",
      "qle": "p-",
      "gamma": 0.86,
      "eclMag": 0.9301,
      "lat": 49,
      "long": 121,
      "sunAlt": 30,
      "pathWidth": 509,
      "centralDur": 420
    },
    {
      "tdOfGreatestEclipse": "2760-03-09T16:45:52Z",
      "deltaT": 2537,
      "deltaTSigma": 588,
      "lunaNum": 9402,
      "sarosNum": 142,
      "eclType": "P",
      "qle": "-t",
      "gamma": 1.1667,
      "eclMag": 0.6886,
      "lat": 72,
      "long": -135,
      "sunAlt": 0,
      "pathWidth": 0,
      "centralDur": 0
    },
    {
      "tdOfGreatestEclipse": "2760-04-08T03:22:04Z",
      "deltaT": 2537,
      "deltaTSigma": 589,
      "lunaNum": 9403,
      "sarosNum": 180,
      "eclType": "Pb",
      "qle": "t-",
      "gamma": -1.5099,
      "eclMag": 0.0485,
      "lat": -72,
      "long": -152,
      "sunAlt": 0,
      "pathWidth": 0,
      "centralDur": 0
    },
    {
      "tdOfGreatestEclipse": "2760-09-01T20:44:16Z",
      "deltaT": 2540,
      "deltaTSigma": 589,
      "lunaNum": 9408,
      "sarosNum": 147,
      "eclType": "P",
      "qle": "-t",
      "gamma": -1.1948,
      "eclMag": 0.6371,
      "lat": -72,
      "long": 174,
      "sunAlt": 0,
      "pathWidth": 0,
      "centralDur": 0
    },
    {
      "tdOfGreatestEclipse": "2760-10-01T08:36:10Z",
      "deltaT": 2540,
      "deltaTSigma": 589,
      "lunaNum": 9409,
      "sarosNum": 185,
      "eclType": "Pb",
      "qle": "t-",
      "gamma": 1.5442,
      "eclMag": 0.0178,
      "lat": 72,
      "long": 138,
      "sunAlt": 0,
      "pathWidth": 0,
      "centralDur": 0
    },
    {
      "tdOfGreatestEclipse": "2761-02-27T01:29:36Z",
      "deltaT": 2543,
      "deltaTSigma": 590,
      "lunaNum": 9414,
      "sarosNum": 152,
      "eclType": "A",
      "qle": "-p",
      "gamma": 0.4994,
      "eclMag": 0.9543,
      "lat": 20,
      "long": 163,
      "sunAlt": 60,
      "pathWidth": 191,
      "centralDur": 317
    },
    {
      "tdOfGreatestEclipse": "2761-08-22T10:17:08Z",
      "deltaT": 2546,
      "deltaTSigma": 590,
      "lunaNum": 9420,
      "sarosNum": 157,
      "eclType": "T",
      "qle": "-n",
      "gamma": -0.4025,
      "eclMag": 1.0626,
      "lat": -12,
      "long": 31,
      "sunAlt": 66,
      "pathWidth": 223,
      "centralDur": 347
    },
    {
      "tdOfGreatestEclipse": "2762-02-16T02:58:14Z",
      "deltaT": 2549,
      "deltaTSigma": 591,
      "lunaNum": 9426,
      "sarosNum": 162,
      "eclType": "A",
      "qle": "nn",
      "gamma": -0.1958,
      "eclMag": 0.9211,
      "lat": -24,
      "long": 152,
      "sunAlt": 79,
      "pathWidth": 304,
      "centralDur": 604
    },
    {
      "tdOfGreatestEclipse": "2762-08-12T03:19:38Z",
      "deltaT": 2552,
      "deltaTSigma": 592,
      "lunaNum": 9432,
      "sarosNum": 167,
      "eclType": "T",
      "qle": "n-",
      "gamma": 0.3365,
      "eclMag": 1.0766,
      "lat": 34,
      "long": 147,
      "sunAlt": 70,
      "pathWidth": 263,
      "centralDur": 371
    },
    {
      "tdOfGreatestEclipse": "2763-02-05T02:16:44Z",
      "deltaT": 2555,
      "deltaTSigma": 592,
      "lunaNum": 9438,
      "sarosNum": 172,
      "eclType": "A",
      "qle": "p-",
      "gamma": -0.8721,
      "eclMag": 0.9233,
      "lat": -74,
      "long": -163,
      "sunAlt": 29,
      "pathWidth": 596,
      "centralDur": 358
    },
    {
      "tdOfGreatestEclipse": "2763-07-03T09:58:20Z",
      "deltaT": 2557,
      "deltaTSigma": 593,
      "lunaNum": 9443,
      "sarosNum": 139,
      "eclType": "Pe",
      "qle": "-t",
      "gamma": -1.5132,
      "eclMag": 0.0561,
      "lat": -67,
      "long": 44,
      "sunAlt": 0,
      "pathWidth": 0,
      "centralDur": 0
    },
    {
      "tdOfGreatestEclipse": "2763-08-01T19:10:31Z",
      "deltaT": 2558,
      "deltaTSigma": 593,
      "lunaNum": 9444,
      "sarosNum": 177,
      "eclType": "P",
      "qle": "t-",
      "gamma": 1.1065,
      "eclMag": 0.807,
      "lat": 70,
      "long": 55,
      "sunAlt": 0,
      "pathWidth": 0,
      "centralDur": 0
    },
    {
      "tdOfGreatestEclipse": "2763-12-26T17:23:19Z",
      "deltaT": 2560,
      "deltaTSigma": 593,
      "lunaNum": 9449,
      "sarosNum": 144,
      "eclType": "P",
      "qle": "-t",
      "gamma": 1.3098,
      "eclMag": 0.4282,
      "lat": 66,
      "long": -61,
      "sunAlt": 0,
      "pathWidth": 0,
      "centralDur": 0
    },
    {
      "tdOfGreatestEclipse": "2764-01-25T06:48:10Z",
      "deltaT": 2561,
      "deltaTSigma": 593,
      "lunaNum": 9450,
      "sarosNum": 182,
      "eclType": "P",
      "qle": "t-",
      "gamma": -1.5048,
      "eclMag": 0.0866,
      "lat": -69,
      "long": -112,
      "sunAlt": 0,
      "pathWidth": 0,
      "centralDur": 0
    },
    {
      "tdOfGreatestEclipse": "2764-06-21T16:37:00Z",
      "deltaT": 2564,
      "deltaTSigma": 594,
      "lunaNum": 9455,
      "sarosNum": 149,
      "eclType": "A",
      "qle": "-p",
      "gamma": -0.804,
      "eclMag": 0.9568,
      "lat": -30,
      "long": -53,
      "sunAlt": 36,
      "pathWidth": 265,
      "centralDur": 306
    },
    {
      "tdOfGreatestEclipse": "2764-12-15T07:39:59Z",
      "deltaT": 2567,
      "deltaTSigma": 595,
      "lunaNum": 9461,
      "sarosNum": 154,
      "eclType": "T",
      "qle": "-p",
      "gamma": 0.5984,
      "eclMag": 1.0443,
      "lat": 13,
      "long": 79,
      "sunAlt": 53,
      "pathWidth": 184,
      "centralDur": 252
    },
    {
      "tdOfGreatestEclipse": "2765-06-10T17:31:56Z",
      "deltaT": 2570,
      "deltaTSigma": 595,
      "lunaNum": 9467,
      "sarosNum": 159,
      "eclType": "Am",
      "qle": "nn",
      "gamma": -0.0521,
      "eclMag": 0.9459,
      "lat": 20,
      "long": -71,
      "sunAlt": 87,
      "pathWidth": 200,
      "centralDur": 422
    },
    {
      "tdOfGreatestEclipse": "2765-12-04T23:28:43Z",
      "deltaT": 2573,
      "deltaTSigma": 596,
      "lunaNum": 9473,
      "sarosNum": 164,
      "eclType": "T",
      "qle": "nn",
      "gamma": -0.0771,
      "eclMag": 1.0398,
      "lat": -27,
      "long": -165,
      "sunAlt": 85,
      "pathWidth": 134,
      "centralDur": 213
    },
    {
      "tdOfGreatestEclipse": "2766-05-30T19:36:00Z",
      "deltaT": 2576,
      "deltaTSigma": 596,
      "lunaNum": 9479,
      "sarosNum": 169,
      "eclType": "A",
      "qle": "p-",
      "gamma": 0.6995,
      "eclMag": 0.9686,
      "lat": 64,
      "long": -126,
      "sunAlt": 45,
      "pathWidth": 158,
      "centralDur": 149
    },
    {
      "tdOfGreatestEclipse": "2766-11-24T12:07:04Z",
      "deltaT": 2579,
      "deltaTSigma": 597,
      "lunaNum": 9485,
      "sarosNum": 174,
      "eclType": "A",
      "qle": "p-",
      "gamma": -0.8053,
      "eclMag": 0.9858,
      "lat": -68,
      "long": -35,
      "sunAlt": 36,
      "pathWidth": 85,
      "centralDur": 59
    },
    {
      "tdOfGreatestEclipse": "2767-04-20T18:51:17Z",
      "deltaT": 2581,
      "deltaTSigma": 598,
      "lunaNum": 9490,
      "sarosNum": 141,
      "eclType": "P",
      "qle": "-t",
      "gamma": -1.2336,
      "eclMag": 0.5693,
      "lat": -62,
      "long": -25,
      "sunAlt": 0,
      "pathWidth": 0,
      "centralDur": 0
    },
    {
      "tdOfGreatestEclipse": "2767-05-20T04:23:16Z",
      "deltaT": 2582,
      "deltaTSigma": 598,
      "lunaNum": 9491,
      "sarosNum": 179,
      "eclType": "P",
      "qle": "t-",
      "gamma": 1.4007,
      "eclMag": 0.2594,
      "lat": 63,
      "long": -12,
      "sunAlt": 0,
      "pathWidth": 0,
      "centralDur": 0
    },
    {
      "tdOfGreatestEclipse": "2767-10-15T01:16:19Z",
      "deltaT": 2584,
      "deltaTSigma": 598,
      "lunaNum": 9496,
      "sarosNum": 146,
      "eclType": "P",
      "qle": "-t",
      "gamma": 1.3673,
      "eclMag": 0.3366,
      "lat": 61,
      "long": -117,
      "sunAlt": 0,
      "pathWidth": 0,
      "centralDur": 0
    },
    {
      "tdOfGreatestEclipse": "2768-04-09T10:54:25Z",
      "deltaT": 2587,
      "deltaTSigma": 599,
      "lunaNum": 9502,
      "sarosNum": 151,
      "eclType": "T",
      "qle": "-p",
      "gamma": -0.5162,
      "eclMag": 1.0595,
      "lat": -20,
      "long": 42,
      "sunAlt": 59,
      "pathWidth": 225,
      "centralDur": 288
    },
    {
      "tdOfGreatestEclipse": "2768-10-03T01:16:25Z",
      "deltaT": 2591,
      "deltaTSigma": 599,
      "lunaNum": 9508,
      "sarosNum": 156,
      "eclType": "A",
      "qle": "-p",
      "gamma": 0.6427,
      "eclMag": 0.9428,
      "lat": 31,
      "long": -170,
      "sunAlt": 50,
      "pathWidth": 269,
      "centralDur": 354
    },
    {
      "tdOfGreatestEclipse": "2769-03-30T02:29:29Z",
      "deltaT": 2594,
      "deltaTSigma": 600,
      "lunaNum": 9514,
      "sarosNum": 161,
      "eclType": "T",
      "qle": "n-",
      "gamma": 0.1865,
      "eclMag": 1.0307,
      "lat": 13,
      "long": 149,
      "sunAlt": 79,
      "pathWidth": 105,
      "centralDur": 160
    },
    {
      "tdOfGreatestEclipse": "2769-09-22T05:59:20Z",
      "deltaT": 2597,
      "deltaTSigma": 601,
      "lunaNum": 9520,
      "sarosNum": 166,
      "eclType": "A",
      "qle": "nn",
      "gamma": -0.1254,
      "eclMag": 0.9944,
      "lat": -6,
      "long": 96,
      "sunAlt": 83,
      "pathWidth": 20,
      "centralDur": 33
    },
    {
      "tdOfGreatestEclipse": "2770-03-19T13:02:29Z",
      "deltaT": 2600,
      "deltaTSigma": 601,
      "lunaNum": 9526,
      "sarosNum": 171,
      "eclType": "A",
      "qle": "p-",
      "gamma": 0.9422,
      "eclMag": 0.9624,
      "lat": 56,
      "long": -57,
      "sunAlt": 19,
      "pathWidth": 401,
      "centralDur": 168
    },
    {
      "tdOfGreatestEclipse": "2770-09-11T18:04:07Z",
      "deltaT": 2603,
      "deltaTSigma": 602,
      "lunaNum": 9532,
      "sarosNum": 176,
      "eclType": "T",
      "qle": "t-",
      "gamma": -0.8582,
      "eclMag": 1.0422,
      "lat": -46,
      "long": -117,
      "sunAlt": 31,
      "pathWidth": 269,
      "centralDur": 180
    },
    {
      "tdOfGreatestEclipse": "2771-02-06T21:22:09Z",
      "deltaT": 2605,
      "deltaTSigma": 602,
      "lunaNum": 9537,
      "sarosNum": 143,
      "eclType": "P",
      "qle": "-t",
      "gamma": -1.3429,
      "eclMag": 0.3802,
      "lat": -62,
      "long": -5,
      "sunAlt": 0,
      "pathWidth": 0,
      "centralDur": 0
    },
    {
      "tdOfGreatestEclipse": "2771-08-03T03:38:31Z",
      "deltaT": 2609,
      "deltaTSigma": 603,
      "lunaNum": 9543,
      "sarosNum": 148,
      "eclType": "T",
      "qle": "-t",
      "gamma": 0.9591,
      "eclMag": 1.059,
      "lat": 70,
      "long": -131,
      "sunAlt": 16,
      "pathWidth": 704,
      "centralDur": 185
    },
    {
      "tdOfGreatestEclipse": "2772-01-26T21:31:15Z",
      "deltaT": 2612,
      "deltaTSigma": 604,
      "lunaNum": 9549,
      "sarosNum": 153,
      "eclType": "A",
      "qle": "-p",
      "gamma": -0.6427,
      "eclMag": 0.9378,
      "lat": -55,
      "long": -107,
      "sunAlt": 50,
      "pathWidth": 300,
      "centralDur": 326
    },
    {
      "tdOfGreatestEclipse": "2772-07-22T18:22:12Z",
      "deltaT": 2615,
      "deltaTSigma": 604,
      "lunaNum": 9555,
      "sarosNum": 158,
      "eclType": "T",
      "qle": "-n",
      "gamma": 0.2259,
      "eclMag": 1.0272,
      "lat": 32,
      "long": -78,
      "sunAlt": 77,
      "pathWidth": 95,
      "centralDur": 147
    },
    {
      "tdOfGreatestEclipse": "2773-01-15T04:08:30Z",
      "deltaT": 2618,
      "deltaTSigma": 605,
      "lunaNum": 9561,
      "sarosNum": 163,
      "eclType": "A",
      "qle": "n-",
      "gamma": 0.08,
      "eclMag": 0.9945,
      "lat": -17,
      "long": 129,
      "sunAlt": 86,
      "pathWidth": 19,
      "centralDur": 35
    },
    {
      "tdOfGreatestEclipse": "2773-07-12T02:38:29Z",
      "deltaT": 2621,
      "deltaTSigma": 606,
      "lunaNum": 9567,
      "sarosNum": 168,
      "eclType": "A",
      "qle": "p-",
      "gamma": -0.5686,
      "eclMag": 0.9707,
      "lat": -12,
      "long": 145,
      "sunAlt": 55,
      "pathWidth": 127,
      "centralDur": 215
    },
    {
      "tdOfGreatestEclipse": "2774-01-04T17:20:28Z",
      "deltaT": 2624,
      "deltaTSigma": 606,
      "lunaNum": 9573,
      "sarosNum": 173,
      "eclType": "T",
      "qle": "p-",
      "gamma": 0.752,
      "eclMag": 1.0342,
      "lat": 25,
      "long": -78,
      "sunAlt": 41,
      "pathWidth": 174,
      "centralDur": 187
    },
    {
      "tdOfGreatestEclipse": "2774-06-01T13:10:06Z",
      "deltaT": 2627,
      "deltaTSigma": 607,
      "lunaNum": 9578,
      "sarosNum": 140,
      "eclType": "Pe",
      "qle": "-t",
      "gamma": 1.5197,
      "eclMag": 0.0737,
      "lat": 68,
      "long": 180,
      "sunAlt": 0,
      "pathWidth": 0,
      "centralDur": 0
    },
    {
      "tdOfGreatestEclipse": "2774-07-01T04:24:51Z",
      "deltaT": 2627,
      "deltaTSigma": 607,
      "lunaNum": 9579,
      "sarosNum": 178,
      "eclType": "P",
      "qle": "t-",
      "gamma": -1.3489,
      "eclMag": 0.3658,
      "lat": -65,
      "long": 102,
      "sunAlt": 0,
      "pathWidth": 0,
      "centralDur": 0
    },
    {
      "tdOfGreatestEclipse": "2774-11-25T22:25:12Z",
      "deltaT": 2630,
      "deltaTSigma": 607,
      "lunaNum": 9584,
      "sarosNum": 145,
      "eclType": "P",
      "qle": "-t",
      "gamma": -1.2785,
      "eclMag": 0.4845,
      "lat": -69,
      "long": 46,
      "sunAlt": 0,
      "pathWidth": 0,
      "centralDur": 0
    },
    {
      "tdOfGreatestEclipse": "2774-12-25T09:06:20Z",
      "deltaT": 2630,
      "deltaTSigma": 607,
      "lunaNum": 9585,
      "sarosNum": 183,
      "eclType": "P",
      "qle": "t-",
      "gamma": 1.405,
      "eclMag": 0.247,
      "lat": 66,
      "long": 37,
      "sunAlt": 0,
      "pathWidth": 0,
      "centralDur": 0
    },
    {
      "tdOfGreatestEclipse": "2775-05-21T16:45:17Z",
      "deltaT": 2633,
      "deltaTSigma": 608,
      "lunaNum": 9590,
      "sarosNum": 150,
      "eclType": "A",
      "qle": "-p",
      "gamma": 0.7292,
      "eclMag": 0.9804,
      "lat": 67,
      "long": -73,
      "sunAlt": 43,
      "pathWidth": 102,
      "centralDur": 91
    },
    {
      "tdOfGreatestEclipse": "2775-11-15T09:28:59Z",
      "deltaT": 2636,
      "deltaTSigma": 609,
      "lunaNum": 9596,
      "sarosNum": 155,
      "eclType": "A",
      "qle": "-p",
      "gamma": -0.6196,
      "eclMag": 0.975,
      "lat": -56,
      "long": 35,
      "sunAlt": 51,
      "pathWidth": 114,
      "centralDur": 127
    },
    {
      "tdOfGreatestEclipse": "2776-05-10T03:25:47Z",
      "deltaT": 2639,
      "deltaTSigma": 609,
      "lunaNum": 9602,
      "sarosNum": 160,
      "eclType": "T",
      "qle": "nn",
      "gamma": -0.0507,
      "eclMag": 1.0386,
      "lat": 15,
      "long": 139,
      "sunAlt": 87,
      "pathWidth": 130,
      "centralDur": 230
    },
    {
      "tdOfGreatestEclipse": "2776-11-03T13:23:16Z",
      "deltaT": 2642,
      "deltaTSigma": 610,
      "lunaNum": 9608,
      "sarosNum": 165,
      "eclType": "A",
      "qle": "nn",
      "gamma": 0.0956,
      "eclMag": 0.9369,
      "lat": -10,
      "long": -13,
      "sunAlt": 85,
      "pathWidth": 236,
      "centralDur": 505
    },
    {
      "tdOfGreatestEclipse": "2777-04-29T19:10:06Z",
      "deltaT": 2645,
      "deltaTSigma": 611,
      "lunaNum": 9614,
      "sarosNum": 170,
      "eclType": "T",
      "qle": "p-",
      "gamma": -0.7631,
      "eclMag": 1.0607,
      "lat": -34,
      "long": -85,
      "sunAlt": 40,
      "pathWidth": 307,
      "centralDur": 300
    },
    {
      "tdOfGreatestEclipse": "2777-10-23T13:04:16Z",
      "deltaT": 2648,
      "deltaTSigma": 611,
      "lunaNum": 9620,
      "sarosNum": 175,
      "eclType": "A",
      "qle": "p-",
      "gamma": 0.8101,
      "eclMag": 0.9294,
      "lat": 41,
      "long": 7,
      "sunAlt": 36,
      "pathWidth": 448,
      "centralDur": 465
    },
    {
      "tdOfGreatestEclipse": "2778-03-21T01:06:34Z",
      "deltaT": 2651,
      "deltaTSigma": 612,
      "lunaNum": 9625,
      "sarosNum": 142,
      "eclType": "P",
      "qle": "-t",
      "gamma": 1.1908,
      "eclMag": 0.6445,
      "lat": 72,
      "long": 86,
      "sunAlt": 0,
      "pathWidth": 0,
      "centralDur": 0
    },
    {
      "tdOfGreatestEclipse": "2778-04-19T11:29:50Z",
      "deltaT": 2651,
      "deltaTSigma": 612,
      "lunaNum": 9626,
      "sarosNum": 180,
      "eclType": "P",
      "qle": "t-",
      "gamma": -1.477,
      "eclMag": 0.1102,
      "lat": -71,
      "long": 73,
      "sunAlt": 0,
      "pathWidth": 0,
      "centralDur": 0
    },
    {
      "tdOfGreatestEclipse": "2778-09-13T04:05:00Z",
      "deltaT": 2654,
      "deltaTSigma": 612,
      "lunaNum": 9631,
      "sarosNum": 147,
      "eclType": "P",
      "qle": "-t",
      "gamma": -1.2542,
      "eclMag": 0.529,
      "lat": -72,
      "long": 51,
      "sunAlt": 0,
      "pathWidth": 0,
      "centralDur": 0
    },
    {
      "tdOfGreatestEclipse": "2778-10-12T16:03:24Z",
      "deltaT": 2654,
      "deltaTSigma": 612,
      "lunaNum": 9632,
      "sarosNum": 185,
      "eclType": "P",
      "qle": "t-",
      "gamma": 1.4901,
      "eclMag": 0.1129,
      "lat": 72,
      "long": 13,
      "sunAlt": 0,
      "pathWidth": 0,
      "centralDur": 0
    },
    {
      "tdOfGreatestEclipse": "2779-03-10T09:33:34Z",
      "deltaT": 2657,
      "deltaTSigma": 613,
      "lunaNum": 9637,
      "sarosNum": 152,
      "eclType": "A",
      "qle": "-p",
      "gamma": 0.5194,
      "eclMag": 0.9537,
      "lat": 26,
      "long": 40,
      "sunAlt": 59,
      "pathWidth": 196,
      "centralDur": 310
    },
    {
      "tdOfGreatestEclipse": "2779-09-02T17:52:23Z",
      "deltaT": 2660,
      "deltaTSigma": 614,
      "lunaNum": 9643,
      "sarosNum": 157,
      "eclType": "T",
      "qle": "-p",
      "gamma": -0.4677,
      "eclMag": 1.0622,
      "lat": -19,
      "long": -85,
      "sunAlt": 62,
      "pathWidth": 230,
      "centralDur": 331
    },
    {
      "tdOfGreatestEclipse": "2780-02-27T10:51:51Z",
      "deltaT": 2663,
      "deltaTSigma": 614,
      "lunaNum": 9649,
      "sarosNum": 162,
      "eclType": "A",
      "qle": "nn",
      "gamma": -0.1801,
      "eclMag": 0.9221,
      "lat": -19,
      "long": 34,
      "sunAlt": 80,
      "pathWidth": 299,
      "centralDur": 603
    },
    {
      "tdOfGreatestEclipse": "2780-08-22T10:53:31Z",
      "deltaT": 2666,
      "deltaTSigma": 615,
      "lunaNum": 9655,
      "sarosNum": 167,
      "eclType": "T",
      "qle": "n-",
      "gamma": 0.2672,
      "eclMag": 1.0747,
      "lat": 26,
      "long": 33,
      "sunAlt": 74,
      "pathWidth": 251,
      "centralDur": 376
    },
    {
      "tdOfGreatestEclipse": "2781-02-15T10:20:47Z",
      "deltaT": 2669,
      "deltaTSigma": 615,
      "lunaNum": 9661,
      "sarosNum": 172,
      "eclType": "A",
      "qle": "p-",
      "gamma": -0.8594,
      "eclMag": 0.9265,
      "lat": -68,
      "long": 73,
      "sunAlt": 30,
      "pathWidth": 543,
      "centralDur": 357
    },
    {
      "tdOfGreatestEclipse": "2781-08-12T02:27:36Z",
      "deltaT": 2673,
      "deltaTSigma": 616,
      "lunaNum": 9667,
      "sarosNum": 177,
      "eclType": "P",
      "qle": "t-",
      "gamma": 1.0372,
      "eclMag": 0.9354,
      "lat": 71,
      "long": -66,
      "sunAlt": 0,
      "pathWidth": 0,
      "centralDur": 0
    },
    {
      "tdOfGreatestEclipse": "2782-01-06T02:02:14Z",
      "deltaT": 2675,
      "deltaTSigma": 617,
      "lunaNum": 9672,
      "sarosNum": 144,
      "eclType": "P",
      "qle": "-t",
      "gamma": 1.3127,
      "eclMag": 0.4227,
      "lat": 68,
      "long": 159,
      "sunAlt": 0,
      "pathWidth": 0,
      "centralDur": 0
    },
    {
      "tdOfGreatestEclipse": "2782-02-04T15:16:41Z",
      "deltaT": 2676,
      "deltaTSigma": 617,
      "lunaNum": 9673,
      "sarosNum": 182,
      "eclType": "P",
      "qle": "t-",
      "gamma": -1.4944,
      "eclMag": 0.1036,
      "lat": -70,
      "long": 109,
      "sunAlt": 0,
      "pathWidth": 0,
      "centralDur": 0
    },
    {
      "tdOfGreatestEclipse": "2782-07-02T23:15:14Z",
      "deltaT": 2678,
      "deltaTSigma": 617,
      "lunaNum": 9678,
      "sarosNum": 149,
      "eclType": "A",
      "qle": "-t",
      "gamma": -0.8886,
      "eclMag": 0.9534,
      "lat": -40,
      "long": -155,
      "sunAlt": 27,
      "pathWidth": 373,
      "centralDur": 306
    },
    {
      "tdOfGreatestEclipse": "2782-12-26T16:26:44Z",
      "deltaT": 2681,
      "deltaTSigma": 618,
      "lunaNum": 9684,
      "sarosNum": 154,
      "eclType": "T",
      "qle": "-p",
      "gamma": 0.6071,
      "eclMag": 1.0435,
      "lat": 14,
      "long": -53,
      "sunAlt": 53,
      "pathWidth": 183,
      "centralDur": 250
    },
    {
      "tdOfGreatestEclipse": "2783-06-22T00:05:16Z",
      "deltaT": 2685,
      "deltaTSigma": 619,
      "lunaNum": 9690,
      "sarosNum": 159,
      "eclType": "A",
      "qle": "nn",
      "gamma": -0.1348,
      "eclMag": 0.9477,
      "lat": 16,
      "long": -168,
      "sunAlt": 82,
      "pathWidth": 194,
      "centralDur": 424
    },
    {
      "tdOfGreatestEclipse": "2783-12-16T08:07:05Z",
      "deltaT": 2688,
      "deltaTSigma": 619,
      "lunaNum": 9696,
      "sarosNum": 164,
      "eclType": "T",
      "qle": "nn",
      "gamma": -0.0639,
      "eclMag": 1.0362,
      "lat": -27,
      "long": 67,
      "sunAlt": 86,
      "pathWidth": 122,
      "centralDur": 198
    },
    {
      "tdOfGreatestEclipse": "2784-06-10T02:32:13Z",
      "deltaT": 2691,
      "deltaTSigma": 620,
      "lunaNum": 9702,
      "sarosNum": 169,
      "eclType": "A",
      "qle": "p-",
      "gamma": 0.6244,
      "eclMag": 0.9744,
      "lat": 61,
      "long": 141,
      "sunAlt": 51,
      "pathWidth": 118,
      "centralDur": 127
    },
    {
      "tdOfGreatestEclipse": "2784-12-04T20:23:15Z",
      "deltaT": 2694,
      "deltaTSigma": 620,
      "lunaNum": 9708,
      "sarosNum": 174,
      "eclType": "A",
      "qle": "p-",
      "gamma": -0.7896,
      "eclMag": 0.981,
      "lat": -71,
      "long": -150,
      "sunAlt": 38,
      "pathWidth": 110,
      "centralDur": 79
    },
    {
      "tdOfGreatestEclipse": "2785-05-01T02:47:01Z",
      "deltaT": 2697,
      "deltaTSigma": 621,
      "lunaNum": 9713,
      "sarosNum": 141,
      "eclType": "P",
      "qle": "-t",
      "gamma": -1.2765,
      "eclMag": 0.4886,
      "lat": -62,
      "long": -152,
      "sunAlt": 0,
      "pathWidth": 0,
      "centralDur": 0
    },
    {
      "tdOfGreatestEclipse": "2785-05-30T11:50:32Z",
      "deltaT": 2697,
      "deltaTSigma": 621,
      "lunaNum": 9714,
      "sarosNum": 179,
      "eclType": "P",
      "qle": "t-",
      "gamma": 1.3346,
      "eclMag": 0.3808,
      "lat": 64,
      "long": -133,
      "sunAlt": 0,
      "pathWidth": 0,
      "centralDur": 0
    },
    {
      "tdOfGreatestEclipse": "2785-10-25T08:31:11Z",
      "deltaT": 2700,
      "deltaTSigma": 622,
      "lunaNum": 9719,
      "sarosNum": 146,
      "eclType": "P",
      "qle": "-t",
      "gamma": 1.4159,
      "eclMag": 0.2555,
      "lat": 62,
      "long": 126,
      "sunAlt": 0,
      "pathWidth": 0,
      "centralDur": 0
    },
    {
      "tdOfGreatestEclipse": "2785-11-24T01:44:23Z",
      "deltaT": 2700,
      "deltaTSigma": 622,
      "lunaNum": 9720,
      "sarosNum": 184,
      "eclType": "Pb",
      "qle": "t-",
      "gamma": -1.5497,
      "eclMag": 0.0272,
      "lat": -64,
      "long": 23,
      "sunAlt": 0,
      "pathWidth": 0,
      "centralDur": 0
    },
    {
      "tdOfGreatestEclipse": "2786-04-20T19:04:43Z",
      "deltaT": 2703,
      "deltaTSigma": 622,
      "lunaNum": 9725,
      "sarosNum": 151,
      "eclType": "T",
      "qle": "-p",
      "gamma": -0.5565,
      "eclMag": 1.0617,
      "lat": -19,
      "long": -80,
      "sunAlt": 56,
      "pathWidth": 241,
      "centralDur": 305
    },
    {
      "tdOfGreatestEclipse": "2786-10-14T08:28:02Z",
      "deltaT": 2706,
      "deltaTSigma": 623,
      "lunaNum": 9731,
      "sarosNum": 156,
      "eclType": "A",
      "qle": "-p",
      "gamma": 0.6962,
      "eclMag": 0.941,
      "lat": 31,
      "long": 83,
      "sunAlt": 46,
      "pathWidth": 296,
      "centralDur": 371
    },
    {
      "tdOfGreatestEclipse": "2787-04-10T10:38:54Z",
      "deltaT": 2709,
      "deltaTSigma": 623,
      "lunaNum": 9737,
      "sarosNum": 161,
      "eclType": "T",
      "qle": "nn",
      "gamma": 0.1525,
      "eclMag": 1.031,
      "lat": 16,
      "long": 28,
      "sunAlt": 81,
      "pathWidth": 106,
      "centralDur": 163
    },
    {
      "tdOfGreatestEclipse": "2787-10-03T13:27:26Z",
      "deltaT": 2712,
      "deltaTSigma": 624,
      "lunaNum": 9743,
      "sarosNum": 166,
      "eclType": "A",
      "qle": "nn",
      "gamma": -0.0685,
      "eclMag": 0.995,
      "lat": -8,
      "long": -15,
      "sunAlt": 86,
      "pathWidth": 18,
      "centralDur": 29
    },
    {
      "tdOfGreatestEclipse": "2788-03-29T20:59:23Z",
      "deltaT": 2715,
      "deltaTSigma": 625,
      "lunaNum": 9749,
      "sarosNum": 171,
      "eclType": "A",
      "qle": "p-",
      "gamma": 0.9158,
      "eclMag": 0.9633,
      "lat": 56,
      "long": -175,
      "sunAlt": 23,
      "pathWidth": 325,
      "centralDur": 163
    },
    {
      "tdOfGreatestEclipse": "2788-09-22T01:45:47Z",
      "deltaT": 2719,
      "deltaTSigma": 625,
      "lunaNum": 9755,
      "sarosNum": 176,
      "eclType": "T",
      "qle": "p-",
      "gamma": -0.797,
      "eclMag": 1.0439,
      "lat": -44,
      "long": 131,
      "sunAlt": 37,
      "pathWidth": 237,
      "centralDur": 188
    },
    {
      "tdOfGreatestEclipse": "2789-02-17T05:19:14Z",
      "deltaT": 2721,
      "deltaTSigma": 626,
      "lunaNum": 9760,
      "sarosNum": 143,
      "eclType": "P",
      "qle": "-t",
      "gamma": -1.3558,
      "eclMag": 0.3587,
      "lat": -62,
      "long": -132,
      "sunAlt": 0,
      "pathWidth": 0,
      "centralDur": 0
    },
    {
      "tdOfGreatestEclipse": "2789-08-13T11:07:01Z",
      "deltaT": 2724,
      "deltaTSigma": 627,
      "lunaNum": 9766,
      "sarosNum": 148,
      "eclType": "P",
      "qle": "-t",
      "gamma": 1.0326,
      "eclMag": 0.9579,
      "lat": 62,
      "long": 145,
      "sunAlt": 0,
      "pathWidth": 0,
      "centralDur": 0
    },
    {
      "tdOfGreatestEclipse": "2789-09-11T18:18:47Z",
      "deltaT": 2725,
      "deltaTSigma": 627,
      "lunaNum": 9767,
      "sarosNum": 186,
      "eclType": "Pb",
      "qle": "t-",
      "gamma": -1.4845,
      "eclMag": 0.0864,
      "lat": -61,
      "long": -166,
      "sunAlt": 0,
      "pathWidth": 0,
      "centralDur": 0
    },
    {
      "tdOfGreatestEclipse": "2790-02-06T05:44:11Z",
      "deltaT": 2728,
      "deltaTSigma": 627,
      "lunaNum": 9772,
      "sarosNum": 153,
      "eclType": "A",
      "qle": "-p",
      "gamma": -0.6495,
      "eclMag": 0.9407,
      "lat": -52,
      "long": 133,
      "sunAlt": 49,
      "pathWidth": 286,
      "centralDur": 312
    },
    {
      "tdOfGreatestEclipse": "2790-08-03T01:30:54Z",
      "deltaT": 2731,
      "deltaTSigma": 628,
      "lunaNum": 9778,
      "sarosNum": 158,
      "eclType": "T",
      "qle": "-p",
      "gamma": 0.3044,
      "eclMag": 1.0228,
      "lat": 34,
      "long": 178,
      "sunAlt": 72,
      "pathWidth": 81,
      "centralDur": 120
    },
    {
      "tdOfGreatestEclipse": "2791-01-26T12:45:13Z",
      "deltaT": 2734,
      "deltaTSigma": 628,
      "lunaNum": 9784,
      "sarosNum": 163,
      "eclType": "A",
      "qle": "nn",
      "gamma": 0.075,
      "eclMag": 0.9975,
      "lat": -15,
      "long": 1,
      "sunAlt": 86,
      "pathWidth": 9,
      "centralDur": 15
    },
    {
      "tdOfGreatestEclipse": "2791-07-23T09:20:29Z",
      "deltaT": 2737,
      "deltaTSigma": 629,
      "lunaNum": 9790,
      "sarosNum": 168,
      "eclType": "A",
      "qle": "p-",
      "gamma": -0.4869,
      "eclMag": 0.9689,
      "lat": -8,
      "long": 45,
      "sunAlt": 61,
      "pathWidth": 127,
      "centralDur": 226
    },
    {
      "tdOfGreatestEclipse": "2792-01-16T02:09:54Z",
      "deltaT": 2740,
      "deltaTSigma": 630,
      "lunaNum": 9796,
      "sarosNum": 173,
      "eclType": "T",
      "qle": "p-",
      "gamma": 0.7454,
      "eclMag": 1.0353,
      "lat": 26,
      "long": 148,
      "sunAlt": 42,
      "pathWidth": 177,
      "centralDur": 189
    },
    {
      "tdOfGreatestEclipse": "2792-07-11T10:52:59Z",
      "deltaT": 2743,
      "deltaTSigma": 630,
      "lunaNum": 9802,
      "sarosNum": 178,
      "eclType": "P",
      "qle": "t-",
      "gamma": -1.265,
      "eclMag": 0.5093,
      "lat": -64,
      "long": -4,
      "sunAlt": 0,
      "pathWidth": 0,
      "centralDur": 0
    },
    {
      "tdOfGreatestEclipse": "2792-12-06T06:55:34Z",
      "deltaT": 2746,
      "deltaTSigma": 631,
      "lunaNum": 9807,
      "sarosNum": 145,
      "eclType": "P",
      "qle": "-t",
      "gamma": -1.2974,
      "eclMag": 0.4499,
      "lat": -68,
      "long": -92,
      "sunAlt": 0,
      "pathWidth": 0,
      "centralDur": 0
    },
    {
      "tdOfGreatestEclipse": "2793-01-04T17:54:30Z",
      "deltaT": 2746,
      "deltaTSigma": 631,
      "lunaNum": 9808,
      "sarosNum": 183,
      "eclType": "P",
      "qle": "t-",
      "gamma": 1.4,
      "eclMag": 0.2569,
      "lat": 65,
      "long": -104,
      "sunAlt": 0,
      "pathWidth": 0,
      "centralDur": 0
    },
    {
      "tdOfGreatestEclipse": "2793-05-31T23:54:27Z",
      "deltaT": 2749,
      "deltaTSigma": 632,
      "lunaNum": 9813,
      "sarosNum": 150,
      "eclType": "A",
      "qle": "-p",
      "gamma": 0.7933,
      "eclMag": 0.9846,
      "lat": 75,
      "long": -174,
      "sunAlt": 37,
      "pathWidth": 90,
      "centralDur": 66
    },
    {
      "tdOfGreatestEclipse": "2793-11-25T17:32:21Z",
      "deltaT": 2752,
      "deltaTSigma": 632,
      "lunaNum": 9819,
      "sarosNum": 155,
      "eclType": "A",
      "qle": "-p",
      "gamma": -0.6448,
      "eclMag": 0.9693,
      "lat": -61,
      "long": -82,
      "sunAlt": 50,
      "pathWidth": 145,
      "centralDur": 152
    },
    {
      "tdOfGreatestEclipse": "2794-05-21T11:05:15Z",
      "deltaT": 2755,
      "deltaTSigma": 633,
      "lunaNum": 9825,
      "sarosNum": 160,
      "eclType": "T",
      "qle": "nn",
      "gamma": 0.0071,
      "eclMag": 1.0441,
      "lat": 21,
      "long": 25,
      "sunAlt": 89,
      "pathWidth": 147,
      "centralDur": 256
    },
    {
      "tdOfGreatestEclipse": "2794-11-14T20:57:51Z",
      "deltaT": 2759,
      "deltaTSigma": 633,
      "lunaNum": 9831,
      "sarosNum": 165,
      "eclType": "Am",
      "qle": "nn",
      "gamma": 0.062,
      "eclMag": 0.9329,
      "lat": -15,
      "long": -126,
      "sunAlt": 87,
      "pathWidth": 251,
      "centralDur": 542
    },
    {
      "tdOfGreatestEclipse": "2795-05-11T03:06:43Z",
      "deltaT": 2762,
      "deltaTSigma": 634,
      "lunaNum": 9837,
      "sarosNum": 170,
      "eclType": "T",
      "qle": "p-",
      "gamma": -0.7125,
      "eclMag": 1.0649,
      "lat": -27,
      "long": 152,
      "sunAlt": 44,
      "pathWidth": 302,
      "centralDur": 337
    },
    {
      "tdOfGreatestEclipse": "2795-11-03T20:29:00Z",
      "deltaT": 2765,
      "deltaTSigma": 635,
      "lunaNum": 9843,
      "sarosNum": 175,
      "eclType": "A",
      "qle": "p-",
      "gamma": 0.7682,
      "eclMag": 0.9285,
      "lat": 34,
      "long": -109,
      "sunAlt": 40,
      "pathWidth": 416,
      "centralDur": 506
    },
    {
      "tdOfGreatestEclipse": "2796-03-31T09:18:19Z",
      "deltaT": 2768,
      "deltaTSigma": 635,
      "lunaNum": 9848,
      "sarosNum": 142,
      "eclType": "P",
      "qle": "-t",
      "gamma": 1.2217,
      "eclMag": 0.5882,
      "lat": 72,
      "long": -51,
      "sunAlt": 0,
      "pathWidth": 0,
      "centralDur": 0
    },
    {
      "tdOfGreatestEclipse": "2796-04-29T19:28:54Z",
      "deltaT": 2768,
      "deltaTSigma": 635,
      "lunaNum": 9849,
      "sarosNum": 180,
      "eclType": "P",
      "qle": "t-",
      "gamma": -1.4377,
      "eclMag": 0.1841,
      "lat": -70,
      "long": -59,
      "sunAlt": 0,
      "pathWidth": 0,
      "centralDur": 0
    },
    {
      "tdOfGreatestEclipse": "2796-09-23T11:33:39Z",
      "deltaT": 2771,
      "deltaTSigma": 636,
      "lunaNum": 9854,
      "sarosNum": 147,
      "eclType": "P",
      "qle": "-t",
      "gamma": -1.3079,
      "eclMag": 0.4309,
      "lat": -72,
      "long": -75,
      "sunAlt": 0,
      "pathWidth": 0,
      "centralDur": 0
    },
    {
      "tdOfGreatestEclipse": "2796-10-22T23:40:05Z",
      "deltaT": 2771,
      "deltaTSigma": 636,
      "lunaNum": 9855,
      "sarosNum": 185,
      "eclType": "P",
      "qle": "t-",
      "gamma": 1.4425,
      "eclMag": 0.1966,
      "lat": 71,
      "long": -114,
      "sunAlt": 0,
      "pathWidth": 0,
      "centralDur": 0
    },
    {
      "tdOfGreatestEclipse": "2797-03-20T17:29:17Z",
      "deltaT": 2774,
      "deltaTSigma": 637,
      "lunaNum": 9860,
      "sarosNum": 152,
      "eclType": "A",
      "qle": "-p",
      "gamma": 0.5455,
      "eclMag": 0.9534,
      "lat": 32,
      "long": -80,
      "sunAlt": 57,
      "pathWidth": 202,
      "centralDur": 300
    },
    {
      "tdOfGreatestEclipse": "2797-09-13T01:33:02Z",
      "deltaT": 2777,
      "deltaTSigma": 637,
      "lunaNum": 9866,
      "sarosNum": 157,
      "eclType": "T",
      "qle": "-p",
      "gamma": -0.5287,
      "eclMag": 1.0611,
      "lat": -27,
      "long": 157,
      "sunAlt": 58,
      "pathWidth": 235,
      "centralDur": 311
    },
    {
      "tdOfGreatestEclipse": "2798-03-09T18:37:50Z",
      "deltaT": 2780,
      "deltaTSigma": 638,
      "lunaNum": 9872,
      "sarosNum": 162,
      "eclType": "A",
      "qle": "nn",
      "gamma": -0.1579,
      "eclMag": 0.9239,
      "lat": -13,
      "long": -83,
      "sunAlt": 81,
      "pathWidth": 291,
      "centralDur": 597
    },
    {
      "tdOfGreatestEclipse": "2798-09-02T18:30:48Z",
      "deltaT": 2784,
      "deltaTSigma": 638,
      "lunaNum": 9878,
      "sarosNum": 167,
      "eclType": "T",
      "qle": "n-",
      "gamma": 0.2008,
      "eclMag": 1.0719,
      "lat": 19,
      "long": -82,
      "sunAlt": 78,
      "pathWidth": 238,
      "centralDur": 374
    },
    {
      "tdOfGreatestEclipse": "2799-02-26T18:21:12Z",
      "deltaT": 2787,
      "deltaTSigma": 639,
      "lunaNum": 9884,
      "sarosNum": 172,
      "eclType": "A",
      "qle": "p-",
      "gamma": -0.8431,
      "eclMag": 0.9304,
      "lat": -62,
      "long": -51,
      "sunAlt": 32,
      "pathWidth": 484,
      "centralDur": 354
    },
    {
      "tdOfGreatestEclipse": "2799-08-23T09:46:29Z",
      "deltaT": 2790,
      "deltaTSigma": 640,
      "lunaNum": 9890,
      "sarosNum": 177,
      "eclType": "T",
      "qle": "t-",
      "gamma": 0.9697,
      "eclMag": 1.0204,
      "lat": 75,
      "long": 126,
      "sunAlt": 13,
      "pathWidth": 299,
      "centralDur": 71
    },
    {
      "tdOfGreatestEclipse": "2800-01-17T10:43:54Z",
      "deltaT": 2793,
      "deltaTSigma": 640,
      "lunaNum": 9895,
      "sarosNum": 144,
      "eclType": "P",
      "qle": "-t",
      "gamma": 1.3141,
      "eclMag": 0.4199,
      "lat": 69,
      "long": 18,
      "sunAlt": 0,
      "pathWidth": 0,
      "centralDur": 0
    },
    {
      "tdOfGreatestEclipse": "2800-02-15T23:44:03Z",
      "deltaT": 2793,
      "deltaTSigma": 640,
      "lunaNum": 9896,
      "sarosNum": 182,
      "eclType": "P",
      "qle": "t-",
      "gamma": -1.4823,
      "eclMag": 0.1234,
      "lat": -71,
      "long": -30,
      "sunAlt": 0,
      "pathWidth": 0,
      "centralDur": 0
    },
    {
      "tdOfGreatestEclipse": "2800-07-13T05:50:30Z",
      "deltaT": 2796,
      "deltaTSigma": 641,
      "lunaNum": 9901,
      "sarosNum": 149,
      "eclType": "A",
      "qle": "-t",
      "gamma": -0.9748,
      "eclMag": 0.9483,
      "lat": -56,
      "long": 100,
      "sunAlt": 12,
      "pathWidth": 894,
      "centralDur": 292
    }
  ]
}